Workbook

Sheet Sectorizacion Racks
B1: =IFERROR(VLOOKUP('Sectorizacion Racks'!$G1,'Consulta Stock'!$D$2:$F$5447,5,FALSE),"") | E1: Columna1 | F1: Ubicación | G1: Codigos | H1: Categoria | I1: Descripcion | J1: Cantidad | L1: Fecha | M1: Lote | N1: Fecha: | O1: =+TODAY() -> 46254
A2: 1 | B2: 1 | C2: A | D2: =IF(AND('Sectorizacion Racks'!$B2=B1,C1='Sectorizacion Racks'!$C2),D1+1,1) -> 1 | E2: =+CONCATENATE('Sectorizacion Racks'!$C2,'Sectorizacion Racks'!$D2) -> A1 | F2: =+CONCATENATE(B2,C2,D2) -> 1A1 | G2: 46694 | H2: =IFERROR(VLOOKUP(G2,'Consulta Stock'!$E$2:$G$5087,3,0),"") -> ALIMENTOS INFANTILES | I2: =IFERROR(VLOOKUP('Sectorizacion Racks'!$G2,'Consulta Stock'!$E$2:$F$5447,2,FALSE),"") -> NATURNES Carne Verduras 4(6x205g) CL 4(6x205g) | J2: 100 | L2: 46631
A3: 2 | B3: 1 | C3: A | D3: =IF(AND('Sectorizacion Racks'!$B3=B2,C2='Sectorizacion Racks'!$C3),D2+1,1) -> 2 | E3: =+CONCATENATE('Sectorizacion Racks'!$C3,'Sectorizacion Racks'!$D3) -> A2 | F3: =+CONCATENATE(B3,C3,D3) -> 1A2 | G3: 14171 | H3: =IFERROR(VLOOKUP(G3,'Consulta Stock'!$E$2:$G$5087,3,0),"") -> CAFES | I3: =IFERROR(VLOOKUP('Sectorizacion Racks'!$G3,'Consulta Stock'!$E$2:$F$5447,2,FALSE),"") -> NESCAFE Caramelo Latte 6(8x18g) CL 6(8x18g) | J3: 175 | L3: 46539 | O3: Codigo
A4: 3 | B4: 1 | C4: A | D4: =IF(AND('Sectorizacion Racks'!$B4=B3,C3='Sectorizacion Racks'!$C4),D3+1,1) -> 3 | E4: =+CONCATENATE('Sectorizacion Racks'!$C4,'Sectorizacion Racks'!$D4) -> A3 | F4: =+CONCATENATE(B4,C4,D4) -> 1A3 | H4: =IFERROR(VLOOKUP(G4,'Consulta Stock'!$E$2:$G$5087,3,0),"") | I4: =IFERROR(VLOOKUP('Sectorizacion Racks'!$G4,'Consulta Stock'!$E$2:$F$5447,2,FALSE),"") | O4: Cantidad | P4: =COUNTIF(G2:G1770,P3) -> 0
A5: 4 | B5: 1 | C5: A | D5: =IF(AND('Sectorizacion Racks'!$B5=B4,C4='Sectorizacion Racks'!$C5),D4+1,1) -> 4 | E5: =+CONCATENATE('Sectorizacion Racks'!$C5,'Sectorizacion Racks'!$D5) -> A4 | F5: =+CONCATENATE(B5,C5,D5) -> 1A4 | G5: 68130 | H5: =IFERROR(VLOOKUP(G5,'Consulta Stock'!$E$2:$G$5087,3,0),"") -> OPPB | I5: =IFERROR(VLOOKUP('Sectorizacion Racks'!$G5,'Consulta Stock'!$E$2:$F$5447,2,FALSE),"") -> MILO ACTIV-GO Stabilo 36x150g N1 CL 36x150g | J5: 48 | L5: 46753 | O5: U.V. | P5: Fracción
A6: 5 | B6: 1 | C6: A | D6: =IF(AND('Sectorizacion Racks'!$B6=B5,C5='Sectorizacion Racks'!$C6),D5+1,1) -> 5 | E6: =+CONCATENATE('Sectorizacion Racks'!$C6,'Sectorizacion Racks'!$D6) -> A5 | F6: =+CONCATENATE(B6,C6,D6) -> 1A5 | G6: 5320 | H6: =IFERROR(VLOOKUP(G6,'Consulta Stock'!$E$2:$G$5087,3,0),"") -> CAFES | I6: =IFERROR(VLOOKUP('Sectorizacion Racks'!$G6,'Consulta Stock'!$E$2:$F$5447,2,FALSE),"") -> Cafe NESCAFE Tradicion sobres 77x172.8g | J6: 6 | L6: 46935 | O6: =VLOOKUP(P3,'Stock Diario'!A2:C4000,2,FALSE) | P6: =VLOOKUP(P3,'Stock Diario'!A2:C4000,3,FALSE)
A7: 6 | B7: 1 | C7: A | D7: =IF(AND('Sectorizacion Racks'!$B7=B6,C6='Sectorizacion Racks'!$C7),D6+1,1) -> 6 | E7: =+CONCATENATE('Sectorizacion Racks'!$C7,'Sectorizacion Racks'!$D7) -> A6 | F7: =+CONCATENATE(B7,C7,D7) -> 1A6 | G7: 46694 | H7: =IFERROR(VLOOKUP(G7,'Consulta Stock'!$E$2:$G$5087,3,0),"") -> ALIMENTOS INFANTILES | I7: =IFERROR(VLOOKUP('Sectorizacion Racks'!$G7,'Consulta Stock'!$E$2:$F$5447,2,FALSE),"") -> NATURNES Carne Verduras 4(6x205g) CL 4(6x205g) | J7: 100 | L7: 46631
A8: 7 | B8: 1 | C8: A | D8: =IF(AND('Sectorizacion Racks'!$B8=B7,C7='Sectorizacion Racks'!$C8),D7+1,1) -> 7 | E8: =+CONCATENATE('Sectorizacion Racks'!$C8,'Sectorizacion Racks'!$D8) -> A7 | F8: =+CONCATENATE(B8,C8,D8) -> 1A7 | G8: 5320 | H8: =IFERROR(VLOOKUP(G8,'Consulta Stock'!$E$2:$G$5087,3,0),"") -> CAFES | I8: =IFERROR(VLOOKUP('Sectorizacion Racks'!$G8,'Consulta Stock'!$E$2:$F$5447,2,FALSE),"") -> Cafe NESCAFE Tradicion sobres 77x172.8g | J8: 6 | L8: 46569 | O8: RACKS
A9: 8 | B9: 1 | C9: A | D9: =IF(AND('Sectorizacion Racks'!$B9=B8,C8='Sectorizacion Racks'!$C9),D8+1,1) -> 8 | E9: =+CONCATENATE('Sectorizacion Racks'!$C9,'Sectorizacion Racks'!$D9) -> A8 | F9: =+CONCATENATE(B9,C9,D9) -> 1A8 | G9: 5670 | H9: =IFERROR(VLOOKUP(G9,'Consulta Stock'!$E$2:$G$5087,3,0),"") -> ALIMENTOS INFANTILES | I9: =IFERROR(VLOOKUP('Sectorizacion Racks'!$G9,'Consulta Stock'!$E$2:$F$5447,2,FALSE),"") -> Colado NESTLE NATURNES Carne Verdura 8(6x115g) | J9: 84 | L9: 46569 | O9: Vacias | P9: =COUNTBLANK(G2:G784) -> 86 | Q9: =P9/P11 -> 0.10983397
A10: 9 | B10: 1 | C10: A | D10: =IF(AND('Sectorizacion Racks'!$B10=B9,C9='Sectorizacion Racks'!$C10),D9+1,1) -> 9 | E10: =+CONCATENATE('Sectorizacion Racks'!$C10,'Sectorizacion Racks'!$D10) -> A9 | F10: =+CONCATENATE(B10,C10,D10) -> 1A9 | H10: =IFERROR(VLOOKUP(G10,'Consulta Stock'!$E$2:$G$5087,3,0),"") | I10: =IFERROR(VLOOKUP('Sectorizacion Racks'!$G10,'Consulta Stock'!$E$2:$F$5447,2,FALSE),"") | O10: Usadas | P10: =COUNTA(G2:G784) -> 697 | Q10: =P10/P11 -> 0.89016603
A11: 10 | B11: 1 | C11: A | D11: =IF(AND('Sectorizacion Racks'!$B11=B10,C10='Sectorizacion Racks'!$C11),D10+1,1) -> 10 | E11: =+CONCATENATE('Sectorizacion Racks'!$C11,'Sectorizacion Racks'!$D11) -> A10 | F11: =+CONCATENATE(B11,C11,D11) -> 1A10 | G11: 63550 | I11: =IFERROR(VLOOKUP('Sectorizacion Racks'!$G11,'Consulta Stock'!$E$2:$F$5447,2,FALSE),"") -> LECHE SUR Sucedaneo LC Tarro 48x397g | J11: 48 | L11: 46539 | O11: Total en Rack | P11: =SUM(P9:P10) -> 783 | Q11: =Q9+Q10 -> 1
A12: 11 | B12: 1 | C12: A | D12: =IF(AND('Sectorizacion Racks'!$B12=B11,C11='Sectorizacion Racks'!$C12),D11+1,1) -> 11 | E12: =+CONCATENATE('Sectorizacion Racks'!$C12,'Sectorizacion Racks'!$D12) -> A11 | F12: =+CONCATENATE(B12,C12,D12) -> 1A11 | H12: =IFERROR(VLOOKUP(G12,'Consulta Stock'!$E$2:$G$5087,3,0),"") | I12: =IFERROR(VLOOKUP('Sectorizacion Racks'!$G12,'Consulta Stock'!$E$2:$F$5447,2,FALSE),"")
A13: 12 | B13: 1 | C13: A | D13: =IF(AND('Sectorizacion Racks'!$B13=B12,C12='Sectorizacion Racks'!$C13),D12+1,1) -> 12 | E13: =+CONCATENATE('Sectorizacion Racks'!$C13,'Sectorizacion Racks'!$D13) -> A12 | F13: =+CONCATENATE(B13,C13,D13) -> 1A12 | G13: 46694 | H13: =IFERROR(VLOOKUP(G13,'Consulta Stock'!$E$2:$G$5087,3,0),"") -> ALIMENTOS INFANTILES | I13: =IFERROR(VLOOKUP('Sectorizacion Racks'!$G13,'Consulta Stock'!$E$2:$F$5447,2,FALSE),"") -> NATURNES Carne Verduras 4(6x205g) CL 4(6x205g) | J13: 100 | L13: 46631 | O13: Pulmon (a piso)
A14: 13 | B14: 1 | C14: A | D14: =IF(AND('Sectorizacion Racks'!$B14=B13,C13='Sectorizacion Racks'!$C14),D13+1,1) -> 13 | E14: =+CONCATENATE('Sectorizacion Racks'!$C14,'Sectorizacion Racks'!$D14) -> A13 | F14: =+CONCATENATE(B14,C14,D14) -> 1A13 | G14: 38850 | H14: =IFERROR(VLOOKUP(G14,'Consulta Stock'!$E$2:$G$5087,3,0),"") -> CAFES | I14: =IFERROR(VLOOKUP('Sectorizacion Racks'!$G14,'Consulta Stock'!$E$2:$F$5447,2,FALSE),"") -> Cafe NESCAFE Tradicion tarro 24x50g | J14: 98 | L14: 46905 | O14: Vacias | P14: =COUNTBLANK(G785:G1212)+COUNTBLANK(G1247:G1270)+COUNTBLANK(G1471:G1486)+COUNTBLANK(G1727:G1766) -> 208 | Q14: =P14/P16 -> 0.40944882
A15: 14 | B15: 1 | C15: A | D15: =IF(AND('Sectorizacion Racks'!$B15=B14,C14='Sectorizacion Racks'!$C15),D14+1,1) -> 14 | E15: =+CONCATENATE('Sectorizacion Racks'!$C15,'Sectorizacion Racks'!$D15) -> A14 | F15: =+CONCATENATE(B15,C15,D15) -> 1A14 | H15: =IFERROR(VLOOKUP(G15,'Consulta Stock'!$E$2:$G$5087,3,0),"") | I15: =IFERROR(VLOOKUP('Sectorizacion Racks'!$G15,'Consulta Stock'!$E$2:$F$5447,2,FALSE),"") | O15: Usadas | P15: =COUNTA(G785:G1212)+COUNTA(G1247:G1270)+COUNTA(G1471:G1486)+COUNTA(G1727:G1766) -> 300 | Q15: =P15/P16 -> 0.59055118
A16: 15 | B16: 1 | C16: A | D16: =IF(AND('Sectorizacion Racks'!$B16=B15,C15='Sectorizacion Racks'!$C16),D15+1,1) -> 15 | E16: =+CONCATENATE('Sectorizacion Racks'!$C16,'Sectorizacion Racks'!$D16) -> A15 | F16: =+CONCATENATE(B16,C16,D16) -> 1A15 | G16: 68940 | H16: =IFERROR(VLOOKUP(G16,'Consulta Stock'!$E$2:$G$5087,3,0),"") -> OPPB | I16: =IFERROR(VLOOKUP('Sectorizacion Racks'!$G16,'Consulta Stock'!$E$2:$F$5447,2,FALSE),"") -> MILO ACTIV-GO BebChocStabilo 15x1000g | J16: 24 | L16: 46692 | O16: Total a Piso | P16: =SUM(P14:P15) -> 508 | Q16: =Q14+Q15 -> 1
A17: 16 | B17: 1 | C17: A | D17: =IF(AND('Sectorizacion Racks'!$B17=B16,C16='Sectorizacion Racks'!$C17),D16+1,1) -> 16 | E17: =+CONCATENATE('Sectorizacion Racks'!$C17,'Sectorizacion Racks'!$D17) -> A16 | F17: =+CONCATENATE(B17,C17,D17) -> 1A16 | H17: =IFERROR(VLOOKUP(G17,'Consulta Stock'!$E$2:$G$5087,3,0),"") | I17: =IFERROR(VLOOKUP('Sectorizacion Racks'!$G17,'Consulta Stock'!$E$2:$F$5447,2,FALSE),"")
A18: 17 | B18: 1 | C18: A | D18: =IF(AND('Sectorizacion Racks'!$B18=B17,C17='Sectorizacion Racks'!$C18),D17+1,1) -> 17 | E18: =+CONCATENATE('Sectorizacion Racks'!$C18,'Sectorizacion Racks'!$D18) -> A17 | F18: =+CONCATENATE(B18,C18,D18) -> 1A17 | G18: 43020 | H18: =IFERROR(VLOOKUP(G18,'Consulta Stock'!$E$2:$G$5087,3,0),"") -> Lacteos Culinarios | I18: =IFERROR(VLOOKUP('Sectorizacion Racks'!$G18,'Consulta Stock'!$E$2:$F$5447,2,FALSE),"") -> Manjar NESTLE El Manjar 24x500g | J18: 66 | L18: 46478 | O18: Total Posiciones | P18: =P11+P16 -> 1291
A19: 18 | B19: 1 | C19: A | D19: =IF(AND('Sectorizacion Racks'!$B19=B18,C18='Sectorizacion Racks'!$C19),D18+1,1) -> 18 | E19: =+CONCATENATE('Sectorizacion Racks'!$C19,'Sectorizacion Racks'!$D19) -> A18 | F19: =+CONCATENATE(B19,C19,D19) -> 1A18 | G19: 68940 | H19: =IFERROR(VLOOKUP(G19,'Consulta Stock'!$E$2:$G$5087,3,0),"") -> OPPB | I19: =IFERROR(VLOOKUP('Sectorizacion Racks'!$G19,'Consulta Stock'!$E$2:$F$5447,2,FALSE),"") -> MILO ACTIV-GO BebChocStabilo 15x1000g | J19: 24 | L19: 46753
A20: 19 | B20: 1 | C20: A | D20: =IF(AND('Sectorizacion Racks'!$B20=B19,C19='Sectorizacion Racks'!$C20),D19+1,1) -> 19 | E20: =+CONCATENATE('Sectorizacion Racks'!$C20,'Sectorizacion Racks'!$D20) -> A19 | F20: =+CONCATENATE(B20,C20,D20) -> 1A19 | G20: 46716 | H20: =IFERROR(VLOOKUP(G20,'Consulta Stock'!$E$2:$G$5087,3,0),"") -> ALIMENTOS INFANTILES | I20: =IFERROR(VLOOKUP('Sectorizacion Racks'!$G20,'Consulta Stock'!$E$2:$F$5447,2,FALSE),"") -> NESTLE AIP Pollo Verduras 4(6x205g) CL 4(6x205g) | J20: 100 | L20: 46539 | O20: RECEPCION
A21: 20 | B21: 1 | C21: A | D21: =IF(AND('Sectorizacion Racks'!$B21=B20,C20='Sectorizacion Racks'!$C21),D20+1,1) -> 20 | E21: =+CONCATENATE('Sectorizacion Racks'!$C21,'Sectorizacion Racks'!$D21) -> A20 | F21: =+CONCATENATE(B21,C21,D21) -> 1A20 | G21: 36535 | H21: =IFERROR(VLOOKUP(G21,'Consulta Stock'!$E$2:$G$5087,3,0),"") -> CAFES | I21: =IFERROR(VLOOKUP('Sectorizacion Racks'!$G21,'Consulta Stock'!$E$2:$F$5447,2,FALSE),"") -> NESCAFE CAPPUCCINO 6(8x14g) N2 CL 6(8x14g) | J21: 175 | L21: 46508 | O21: Vacias | P21: =COUNTBLANK(G1327:G1470) -> 126 | Q21: =P21/P23 -> 0.875
A22: 21 | B22: 1 | C22: A | D22: =IF(AND('Sectorizacion Racks'!$B22=B21,C21='Sectorizacion Racks'!$C22),D21+1,1) -> 21 | E22: =+CONCATENATE('Sectorizacion Racks'!$C22,'Sectorizacion Racks'!$D22) -> A21 | F22: =+CONCATENATE(B22,C22,D22) -> 1A21 | G22: 46694 | H22: =IFERROR(VLOOKUP(G22,'Consulta Stock'!$E$2:$G$5087,3,0),"") -> ALIMENTOS INFANTILES | I22: =IFERROR(VLOOKUP('Sectorizacion Racks'!$G22,'Consulta Stock'!$E$2:$F$5447,2,FALSE),"") -> NATURNES Carne Verduras 4(6x205g) CL 4(6x205g) | J22: 100 | L22: 46631 | O22: Usadas | P22: =COUNTA(G1327:G1468) -> 18 | Q22: =P22/P23 -> 0.125
A23: 22 | B23: 1 | C23: A | D23: =IF(AND('Sectorizacion Racks'!$B23=B22,C22='Sectorizacion Racks'!$C23),D22+1,1) -> 22 | E23: =+CONCATENATE('Sectorizacion Racks'!$C23,'Sectorizacion Racks'!$D23) -> A22 | F23: =+CONCATENATE(B23,C23,D23) -> 1A22 | G23: 68130 | H23: =IFERROR(VLOOKUP(G23,'Consulta Stock'!$E$2:$G$5087,3,0),"") -> OPPB | I23: =IFERROR(VLOOKUP('Sectorizacion Racks'!$G23,'Consulta Stock'!$E$2:$F$5447,2,FALSE),"") -> MILO ACTIV-GO Stabilo 36x150g N1 CL 36x150g | J23: 48 | L23: 46753 | O23: Pulmon | P23: =SUM(P21:P22) -> 144 | Q23: =Q21+Q22 -> 1
A24: 23 | B24: 1 | C24: A | D24: =IF(AND('Sectorizacion Racks'!$B24=B23,C23='Sectorizacion Racks'!$C24),D23+1,1) -> 23 | E24: =+CONCATENATE('Sectorizacion Racks'!$C24,'Sectorizacion Racks'!$D24) -> A23 | F24: =+CONCATENATE(B24,C24,D24) -> 1A23 | G24: 65820 | H24: =IFERROR(VLOOKUP(G24,'Consulta Stock'!$E$2:$G$5087,3,0),"") -> Leche en Polvo | I24: =IFERROR(VLOOKUP('Sectorizacion Racks'!$G24,'Consulta Stock'!$E$2:$F$5447,2,FALSE),"") -> NIDO Buen Dia LSP Softpack 12x700g | J24: 32 | L24: 46569
A25: 24 | B25: 1 | C25: A | D25: =IF(AND('Sectorizacion Racks'!$B25=B24,C24='Sectorizacion Racks'!$C25),D24+1,1) -> 24 | E25: =+CONCATENATE('Sectorizacion Racks'!$C25,'Sectorizacion Racks'!$D25) -> A24 | F25: =+CONCATENATE(B25,C25,D25) -> 1A24 | G25: 46695 | H25: =IFERROR(VLOOKUP(G25,'Consulta Stock'!$E$2:$G$5087,3,0),"") -> ALIMENTOS INFANTILES | I25: =IFERROR(VLOOKUP('Sectorizacion Racks'!$G25,'Consulta Stock'!$E$2:$F$5447,2,FALSE),"") -> NATURNES AIP Carne Verduras 4(6x205g) CL 4(6x205g) | J25: 100 | L25: 46661 | O25: Sobre Stock (Fuera de Posiciones)
A26: 25 | B26: 1 | C26: B | D26: =IF(AND('Sectorizacion Racks'!$B26=B25,C25='Sectorizacion Racks'!$C26),D25+1,1) -> 1 | E26: =+CONCATENATE('Sectorizacion Racks'!$C26,'Sectorizacion Racks'!$D26) -> B1 | F26: =+CONCATENATE(B26,C26,D26) -> 1B1 | G26: 5320 | H26: =IFERROR(VLOOKUP(G26,'Consulta Stock'!$E$2:$G$5087,3,0),"") -> CAFES | I26: =IFERROR(VLOOKUP('Sectorizacion Racks'!$G26,'Consulta Stock'!$E$2:$F$5447,2,FALSE),"") -> Cafe NESCAFE Tradicion sobres 77x172.8g | J26: 6 | L26: 46905 | O26: Usadas | P26: =COUNTA(G1272:G1470)+COUNTA(G1487:G1725) -> 18
A27: 26 | B27: 1 | C27: B | D27: =IF(AND('Sectorizacion Racks'!$B27=B26,C26='Sectorizacion Racks'!$C27),D26+1,1) -> 2 | E27: =+CONCATENATE('Sectorizacion Racks'!$C27,'Sectorizacion Racks'!$D27) -> B2 | F27: =+CONCATENATE(B27,C27,D27) -> 1B2 | G27: 14171 | H27: =IFERROR(VLOOKUP(G27,'Consulta Stock'!$E$2:$G$5087,3,0),"") -> CAFES | I27: =IFERROR(VLOOKUP('Sectorizacion Racks'!$G27,'Consulta Stock'!$E$2:$F$5447,2,FALSE),"") -> NESCAFE Caramelo Latte 6(8x18g) CL 6(8x18g) | J27: 175 | L27: 46569
A28: 27 | B28: 1 | C28: B | D28: =IF(AND('Sectorizacion Racks'!$B28=B27,C27='Sectorizacion Racks'!$C28),D27+1,1) -> 3 | E28: =+CONCATENATE('Sectorizacion Racks'!$C28,'Sectorizacion Racks'!$D28) -> B3 | F28: =+CONCATENATE(B28,C28,D28) -> 1B3 | G28: 36540 | H28: =IFERROR(VLOOKUP(G28,'Consulta Stock'!$E$2:$G$5087,3,0),"") -> CAFES | I28: =IFERROR(VLOOKUP('Sectorizacion Racks'!$G28,'Consulta Stock'!$E$2:$F$5447,2,FALSE),"") -> NESCAFE Doble Choca Moka 6(8x23g) XR 6(8x23g) | J28: 175 | L28: 46539 | O28: Frente Camara
A29: 28 | B29: 1 | C29: B | D29: =IF(AND('Sectorizacion Racks'!$B29=B28,C28='Sectorizacion Racks'!$C29),D28+1,1) -> 4 | E29: =+CONCATENATE('Sectorizacion Racks'!$C29,'Sectorizacion Racks'!$D29) -> B4 | F29: =+CONCATENATE(B29,C29,D29) -> 1B4 | G29: 68950 | H29: =IFERROR(VLOOKUP(G29,'Consulta Stock'!$E$2:$G$5087,3,0),"") -> OPPB | I29: =IFERROR(VLOOKUP('Sectorizacion Racks'!$G29,'Consulta Stock'!$E$2:$F$5447,2,FALSE),"") -> MILO ACTIV-GO Beb Chocolate 12x700g | J29: 35 | L29: 46753 | O29: Usadas | P29: =COUNTA(G1214:G1243) -> 4
A30: 29 | B30: 1 | C30: B | D30: =IF(AND('Sectorizacion Racks'!$B30=B29,C29='Sectorizacion Racks'!$C30),D29+1,1) -> 5 | E30: =+CONCATENATE('Sectorizacion Racks'!$C30,'Sectorizacion Racks'!$D30) -> B5 | F30: =+CONCATENATE(B30,C30,D30) -> 1B5 | G30: 68130 | H30: =IFERROR(VLOOKUP(G30,'Consulta Stock'!$E$2:$G$5087,3,0),"") -> OPPB | I30: =IFERROR(VLOOKUP('Sectorizacion Racks'!$G30,'Consulta Stock'!$E$2:$F$5447,2,FALSE),"") -> MILO ACTIV-GO Stabilo 36x150g N1 CL 36x150g | J30: 48 | L30: 46753
A31: 30 | B31: 1 | C31: B | D31: =IF(AND('Sectorizacion Racks'!$B31=B30,C30='Sectorizacion Racks'!$C31),D30+1,1) -> 6 | E31: =+CONCATENATE('Sectorizacion Racks'!$C31,'Sectorizacion Racks'!$D31) -> B6 | F31: =+CONCATENATE(B31,C31,D31) -> 1B6 | G31: 65820 | H31: =IFERROR(VLOOKUP(G31,'Consulta Stock'!$E$2:$G$5087,3,0),"") -> Leche en Polvo | I31: =IFERROR(VLOOKUP('Sectorizacion Racks'!$G31,'Consulta Stock'!$E$2:$F$5447,2,FALSE),"") -> NIDO Buen Dia LSP Softpack 12x700g | J31: 32 | L31: 46569 | O31: Total Pallets Usados
A32: 31 | B32: 1 | C32: B | D32: =IF(AND('Sectorizacion Racks'!$B32=B31,C31='Sectorizacion Racks'!$C32),D31+1,1) -> 7 | E32: =+CONCATENATE('Sectorizacion Racks'!$C32,'Sectorizacion Racks'!$D32) -> B7 | F32: =+CONCATENATE(B32,C32,D32) -> 1B7 | G32: 65820 | H32: =IFERROR(VLOOKUP(G32,'Consulta Stock'!$E$2:$G$5087,3,0),"") -> Leche en Polvo | I32: =IFERROR(VLOOKUP('Sectorizacion Racks'!$G32,'Consulta Stock'!$E$2:$F$5447,2,FALSE),"") -> NIDO Buen Dia LSP Softpack 12x700g | J32: 32 | L32: 46569 | O32: =COUNTA(G2:G1770) -> 1020
A33: 32 | B33: 1 | C33: B | D33: =IF(AND('Sectorizacion Racks'!$B33=B32,C32='Sectorizacion Racks'!$C33),D32+1,1) -> 8 | E33: =+CONCATENATE('Sectorizacion Racks'!$C33,'Sectorizacion Racks'!$D33) -> B8 | F33: =+CONCATENATE(B33,C33,D33) -> 1B8 | G33: 65820 | H33: =IFERROR(VLOOKUP(G33,'Consulta Stock'!$E$2:$G$5087,3,0),"") -> Leche en Polvo | I33: =IFERROR(VLOOKUP('Sectorizacion Racks'!$G33,'Consulta Stock'!$E$2:$F$5447,2,FALSE),"") -> NIDO Buen Dia LSP Softpack 12x700g | J33: 32 | L33: 46569
A34: 33 | B34: 1 | C34: B | D34: =IF(AND('Sectorizacion Racks'!$B34=B33,C33='Sectorizacion Racks'!$C34),D33+1,1) -> 9 | E34: =+CONCATENATE('Sectorizacion Racks'!$C34,'Sectorizacion Racks'!$D34) -> B9 | F34: =+CONCATENATE(B34,C34,D34) -> 1B9 | G34: 5320 | H34: =IFERROR(VLOOKUP(G34,'Consulta Stock'!$E$2:$G$5087,3,0),"") -> CAFES | I34: =IFERROR(VLOOKUP('Sectorizacion Racks'!$G34,'Consulta Stock'!$E$2:$F$5447,2,FALSE),"") -> Cafe NESCAFE Tradicion sobres 77x172.8g | J34: 6 | L34: 46905 | O34: BODEGA EXTERNA
A35: 34 | B35: 1 | C35: B | D35: =IF(AND('Sectorizacion Racks'!$B35=B34,C34='Sectorizacion Racks'!$C35),D34+1,1) -> 10 | E35: =+CONCATENATE('Sectorizacion Racks'!$C35,'Sectorizacion Racks'!$D35) -> B10 | F35: =+CONCATENATE(B35,C35,D35) -> 1B10 | G35: 2120 | H35: =IFERROR(VLOOKUP(G35,'Consulta Stock'!$E$2:$G$5087,3,0),"") -> CAFES | I35: =IFERROR(VLOOKUP('Sectorizacion Racks'!$G35,'Consulta Stock'!$E$2:$F$5447,2,FALSE),"") -> Cafe NESCAFE Tradicion tarro 24 x 170 GRS | J35: 32 | L35: 46813 | O35: =COUNTA(G1517:G1725) -> 0
A36: 35 | B36: 1 | C36: B | D36: =IF(AND('Sectorizacion Racks'!$B36=B35,C35='Sectorizacion Racks'!$C36),D35+1,1) -> 11 | E36: =+CONCATENATE('Sectorizacion Racks'!$C36,'Sectorizacion Racks'!$D36) -> B11 | F36: =+CONCATENATE(B36,C36,D36) -> 1B11 | G36: 65820 | H36: =IFERROR(VLOOKUP(G36,'Consulta Stock'!$E$2:$G$5087,3,0),"") -> Leche en Polvo | I36: =IFERROR(VLOOKUP('Sectorizacion Racks'!$G36,'Consulta Stock'!$E$2:$F$5447,2,FALSE),"") -> NIDO Buen Dia LSP Softpack 12x700g | J36: 32 | L36: 46569
A37: 36 | B37: 1 | C37: B | D37: =IF(AND('Sectorizacion Racks'!$B37=B36,C36='Sectorizacion Racks'!$C37),D36+1,1) -> 12 | E37: =+CONCATENATE('Sectorizacion Racks'!$C37,'Sectorizacion Racks'!$D37) -> B12 | F37: =+CONCATENATE(B37,C37,D37) -> 1B12 | G37: 36120 | H37: =IFERROR(VLOOKUP(G37,'Consulta Stock'!$E$2:$G$5087,3,0),"") -> CAFES | I37: =IFERROR(VLOOKUP('Sectorizacion Racks'!$G37,'Consulta Stock'!$E$2:$F$5447,2,FALSE),"") -> NESCAFE DECAF MYW 24x100g CL 24x100g | J37: 48 | L37: 46844
A38: 37 | B38: 1 | C38: B | D38: =IF(AND('Sectorizacion Racks'!$B38=B37,C37='Sectorizacion Racks'!$C38),D37+1,1) -> 13 | E38: =+CONCATENATE('Sectorizacion Racks'!$C38,'Sectorizacion Racks'!$D38) -> B13 | F38: =+CONCATENATE(B38,C38,D38) -> 1B13 | G38: 5320 | H38: =IFERROR(VLOOKUP(G38,'Consulta Stock'!$E$2:$G$5087,3,0),"") -> CAFES | I38: =IFERROR(VLOOKUP('Sectorizacion Racks'!$G38,'Consulta Stock'!$E$2:$F$5447,2,FALSE),"") -> Cafe NESCAFE Tradicion sobres 77x172.8g | J38: 6 | L38: 46905
A39: 38 | B39: 1 | C39: B | D39: =IF(AND('Sectorizacion Racks'!$B39=B38,C38='Sectorizacion Racks'!$C39),D38+1,1) -> 14 | E39: =+CONCATENATE('Sectorizacion Racks'!$C39,'Sectorizacion Racks'!$D39) -> B14 | F39: =+CONCATENATE(B39,C39,D39) -> 1B14 | G39: 5320 | H39: =IFERROR(VLOOKUP(G39,'Consulta Stock'!$E$2:$G$5087,3,0),"") -> CAFES | I39: =IFERROR(VLOOKUP('Sectorizacion Racks'!$G39,'Consulta Stock'!$E$2:$F$5447,2,FALSE),"") -> Cafe NESCAFE Tradicion sobres 77x172.8g | J39: 6 | L39: 46935
A40: 39 | B40: 1 | C40: B | D40: =IF(AND('Sectorizacion Racks'!$B40=B39,C39='Sectorizacion Racks'!$C40),D39+1,1) -> 15 | E40: =+CONCATENATE('Sectorizacion Racks'!$C40,'Sectorizacion Racks'!$D40) -> B15 | F40: =+CONCATENATE(B40,C40,D40) -> 1B15 | G40: 5320 | H40: =IFERROR(VLOOKUP(G40,'Consulta Stock'!$E$2:$G$5087,3,0),"") -> CAFES | I40: =IFERROR(VLOOKUP('Sectorizacion Racks'!$G40,'Consulta Stock'!$E$2:$F$5447,2,FALSE),"") -> Cafe NESCAFE Tradicion sobres 77x172.8g | J40: 6 | L40: 46905
A41: 40 | B41: 1 | C41: B | D41: =IF(AND('Sectorizacion Racks'!$B41=B40,C40='Sectorizacion Racks'!$C41),D40+1,1) -> 16 | E41: =+CONCATENATE('Sectorizacion Racks'!$C41,'Sectorizacion Racks'!$D41) -> B16 | F41: =+CONCATENATE(B41,C41,D41) -> 1B16 | G41: 2130 | H41: =IFERROR(VLOOKUP(G41,'Consulta Stock'!$E$2:$G$5087,3,0),"") -> CAFES | I41: =IFERROR(VLOOKUP('Sectorizacion Racks'!$G41,'Consulta Stock'!$E$2:$F$5447,2,FALSE),"") -> Cafe NESCAFE Tradicion tarro 24 x 100 GRS | J41: 48 | L41: 46874
A42: 41 | B42: 1 | C42: B | D42: =IF(AND('Sectorizacion Racks'!$B42=B41,C41='Sectorizacion Racks'!$C42),D41+1,1) -> 17 | E42: =+CONCATENATE('Sectorizacion Racks'!$C42,'Sectorizacion Racks'!$D42) -> B17 | F42: =+CONCATENATE(B42,C42,D42) -> 1B17 | G42: 5320 | H42: =IFERROR(VLOOKUP(G42,'Consulta Stock'!$E$2:$G$5087,3,0),"") -> CAFES | I42: =IFERROR(VLOOKUP('Sectorizacion Racks'!$G42,'Consulta Stock'!$E$2:$F$5447,2,FALSE),"") -> Cafe NESCAFE Tradicion sobres 77x172.8g | J42: 6 | L42: 46935
A43: 42 | B43: 1 | C43: B | D43: =IF(AND('Sectorizacion Racks'!$B43=B42,C42='Sectorizacion Racks'!$C43),D42+1,1) -> 18 | E43: =+CONCATENATE('Sectorizacion Racks'!$C43,'Sectorizacion Racks'!$D43) -> B18 | F43: =+CONCATENATE(B43,C43,D43) -> 1B18 | G43: 68130 | H43: =IFERROR(VLOOKUP(G43,'Consulta Stock'!$E$2:$G$5087,3,0),"") -> OPPB | I43: =IFERROR(VLOOKUP('Sectorizacion Racks'!$G43,'Consulta Stock'!$E$2:$F$5447,2,FALSE),"") -> MILO ACTIV-GO Stabilo 36x150g N1 CL 36x150g | J43: 48 | L43: 46753
A44: 43 | B44: 1 | C44: B | D44: =IF(AND('Sectorizacion Racks'!$B44=B43,C43='Sectorizacion Racks'!$C44),D43+1,1) -> 19 | E44: =+CONCATENATE('Sectorizacion Racks'!$C44,'Sectorizacion Racks'!$D44) -> B19 | F44: =+CONCATENATE(B44,C44,D44) -> 1B19 | G44: 36535 | H44: =IFERROR(VLOOKUP(G44,'Consulta Stock'!$E$2:$G$5087,3,0),"") -> CAFES | I44: =IFERROR(VLOOKUP('Sectorizacion Racks'!$G44,'Consulta Stock'!$E$2:$F$5447,2,FALSE),"") -> NESCAFE CAPPUCCINO 6(8x14g) N2 CL 6(8x14g) | J44: 175 | L44: 46508
A45: 44 | B45: 1 | C45: B | D45: =IF(AND('Sectorizacion Racks'!$B45=B44,C44='Sectorizacion Racks'!$C45),D44+1,1) -> 20 | E45: =+CONCATENATE('Sectorizacion Racks'!$C45,'Sectorizacion Racks'!$D45) -> B20 | F45: =+CONCATENATE(B45,C45,D45) -> 1B20 | G45: 68940 | H45: =IFERROR(VLOOKUP(G45,'Consulta Stock'!$E$2:$G$5087,3,0),"") -> OPPB | I45: =IFERROR(VLOOKUP('Sectorizacion Racks'!$G45,'Consulta Stock'!$E$2:$F$5447,2,FALSE),"") -> MILO ACTIV-GO BebChocStabilo 15x1000g | J45: 24 | L45: 46753
A46: 45 | B46: 1 | C46: B | D46: =IF(AND('Sectorizacion Racks'!$B46=B45,C45='Sectorizacion Racks'!$C46),D45+1,1) -> 21 | E46: =+CONCATENATE('Sectorizacion Racks'!$C46,'Sectorizacion Racks'!$D46) -> B21 | F46: =+CONCATENATE(B46,C46,D46) -> 1B21 | G46: 36540 | H46: =IFERROR(VLOOKUP(G46,'Consulta Stock'!$E$2:$G$5087,3,0),"") -> CAFES | I46: =IFERROR(VLOOKUP('Sectorizacion Racks'!$G46,'Consulta Stock'!$E$2:$F$5447,2,FALSE),"") -> NESCAFE Doble Choca Moka 6(8x23g) XR 6(8x23g) | J46: 175 | L46: 46539
A47: 46 | B47: 1 | C47: B | D47: =IF(AND('Sectorizacion Racks'!$B47=B46,C46='Sectorizacion Racks'!$C47),D46+1,1) -> 22 | E47: =+CONCATENATE('Sectorizacion Racks'!$C47,'Sectorizacion Racks'!$D47) -> B22 | F47: =+CONCATENATE(B47,C47,D47) -> 1B22 | G47: 36540 | H47: =IFERROR(VLOOKUP(G47,'Consulta Stock'!$E$2:$G$5087,3,0),"") -> CAFES | I47: =IFERROR(VLOOKUP('Sectorizacion Racks'!$G47,'Consulta Stock'!$E$2:$F$5447,2,FALSE),"") -> NESCAFE Doble Choca Moka 6(8x23g) XR 6(8x23g) | J47: 175 | L47: 46539
... A70: 69 | B70: 1 | C70: C | D70: =IF(AND('Sectorizacion Racks'!$B70=B69,C69='Sectorizacion Racks'!$C70),D69+1,1) -> 21 | E70: =+CONCATENATE('Sectorizacion Racks'!$C70,'Sectorizacion Racks'!$D70) -> C21 | F70: =+CONCATENATE(B70,C70,D70) -> 1C21 | G70: 2130 | H70: =IFERROR(VLOOKUP(G70,'Consulta Stock'!$E$2:$G$5087,3,0),"") -> CAFES | I70: =IFERROR(VLOOKUP('Sectorizacion Racks'!$G70,'Consulta Stock'!$E$2:$F$5447,2,FALSE),"") -> Cafe NESCAFE Tradicion tarro 24 x 100 GRS | J70: 48 | L70: 46874
A71: 70 | B71: 1 | C71: C | D71: =IF(AND('Sectorizacion Racks'!$B71=B70,C70='Sectorizacion Racks'!$C71),D70+1,1) -> 22 | E71: =+CONCATENATE('Sectorizacion Racks'!$C71,'Sectorizacion Racks'!$D71) -> C22 | F71: =+CONCATENATE(B71,C71,D71) -> 1C22 | H71: =IFERROR(VLOOKUP(G71,'Consulta Stock'!$E$2:$G$5087,3,0),"") | I71: =IFERROR(VLOOKUP('Sectorizacion Racks'!$G71,'Consulta Stock'!$E$2:$F$5447,2,FALSE),"")
A72: 71 | B72: 1 | C72: C | D72: =IF(AND('Sectorizacion Racks'!$B72=B71,C71='Sectorizacion Racks'!$C72),D71+1,1) -> 23 | E72: =+CONCATENATE('Sectorizacion Racks'!$C72,'Sectorizacion Racks'!$D72) -> C23 | F72: =+CONCATENATE(B72,C72,D72) -> 1C23 | G72: 36540 | H72: =IFERROR(VLOOKUP(G72,'Consulta Stock'!$E$2:$G$5087,3,0),"") -> CAFES | I72: =IFERROR(VLOOKUP('Sectorizacion Racks'!$G72,'Consulta Stock'!$E$2:$F$5447,2,FALSE),"") -> NESCAFE Doble Choca Moka 6(8x23g) XR 6(8x23g) | J72: 175 | L72: 46539
A73: 72 | B73: 1 | C73: C | D73: =IF(AND('Sectorizacion Racks'!$B73=B72,C72='Sectorizacion Racks'!$C73),D72+1,1) -> 24 | E73: =+CONCATENATE('Sectorizacion Racks'!$C73,'Sectorizacion Racks'!$D73) -> C24 | F73: =+CONCATENATE(B73,C73,D73) -> 1C24 | G73: 38850 | H73: =IFERROR(VLOOKUP(G73,'Consulta Stock'!$E$2:$G$5087,3,0),"") -> CAFES | I73: =IFERROR(VLOOKUP('Sectorizacion Racks'!$G73,'Consulta Stock'!$E$2:$F$5447,2,FALSE),"") -> Cafe NESCAFE Tradicion tarro 24x50g | J73: 98 | L73: 46813
A74: 73 | B74: 2 | C74: A | D74: =IF(AND('Sectorizacion Racks'!$B74=B73,C73='Sectorizacion Racks'!$C74),D73+1,1) -> 1 | E74: =+CONCATENATE('Sectorizacion Racks'!$C74,'Sectorizacion Racks'!$D74) -> A1 | F74: =+CONCATENATE(B74,C74,D74) -> 2A1 | G74: 5480 | H74: =IFERROR(VLOOKUP(G74,'Consulta Stock'!$E$2:$G$5087,3,0),"") -> CULINARIOS | I74: =IFERROR(VLOOKUP('Sectorizacion Racks'!$G74,'Consulta Stock'!$E$2:$F$5447,2,FALSE),"") -> MAGGI SOPA Pollo Fideos 20x70g | J74: 216 | L74: 46600
A75: 74 | B75: 2 | C75: A | D75: =IF(AND('Sectorizacion Racks'!$B75=B74,C74='Sectorizacion Racks'!$C75),D74+1,1) -> 2 | E75: =+CONCATENATE('Sectorizacion Racks'!$C75,'Sectorizacion Racks'!$D75) -> A2 | F75: =+CONCATENATE(B75,C75,D75) -> 2A2 | G75: 46740 | H75: =IFERROR(VLOOKUP(G75,'Consulta Stock'!$E$2:$G$5087,3,0),"") -> ALIMENTOS INFANTILES | I75: =IFERROR(VLOOKUP('Sectorizacion Racks'!$G75,'Consulta Stock'!$E$2:$F$5447,2,FALSE),"") -> Picado NESTLE NATURNES Cazuela de Ave 24x250g | J75: 77 | L75: 46600
A76: 75 | B76: 2 | C76: A | D76: =IF(AND('Sectorizacion Racks'!$B76=B75,C75='Sectorizacion Racks'!$C76),D75+1,1) -> 3 | E76: =+CONCATENATE('Sectorizacion Racks'!$C76,'Sectorizacion Racks'!$D76) -> A3 | F76: =+CONCATENATE(B76,C76,D76) -> 2A3 | G76: 58120 | H76: =IFERROR(VLOOKUP(G76,'Consulta Stock'!$E$2:$G$5087,3,0),"") -> ALIMENTOS INFANTILES | I76: =IFERROR(VLOOKUP('Sectorizacion Racks'!$G76,'Consulta Stock'!$E$2:$F$5447,2,FALSE),"") -> Picado NESTLE NATURNES Pollo Arvejado 24x250g | J76: 77 | L76: 46478
A77: 76 | B77: 2 | C77: A | D77: =IF(AND('Sectorizacion Racks'!$B77=B76,C76='Sectorizacion Racks'!$C77),D76+1,1) -> 4 | E77: =+CONCATENATE('Sectorizacion Racks'!$C77,'Sectorizacion Racks'!$D77) -> A4 | F77: =+CONCATENATE(B77,C77,D77) -> 2A4 | G77: 5480 | H77: =IFERROR(VLOOKUP(G77,'Consulta Stock'!$E$2:$G$5087,3,0),"") -> CULINARIOS | I77: =IFERROR(VLOOKUP('Sectorizacion Racks'!$G77,'Consulta Stock'!$E$2:$F$5447,2,FALSE),"") -> MAGGI SOPA Pollo Fideos 20x70g | J77: 216 | L77: 46631
A78: 77 | B78: 2 | C78: A | D78: =IF(AND('Sectorizacion Racks'!$B78=B77,C77='Sectorizacion Racks'!$C78),D77+1,1) -> 5 | E78: =+CONCATENATE('Sectorizacion Racks'!$C78,'Sectorizacion Racks'!$D78) -> A5 | F78: =+CONCATENATE(B78,C78,D78) -> 2A5 | G78: 8100 | H78: =IFERROR(VLOOKUP(G78,'Consulta Stock'!$E$2:$G$5087,3,0),"") -> CULINARIOS | I78: =IFERROR(VLOOKUP('Sectorizacion Racks'!$G78,'Consulta Stock'!$E$2:$F$5447,2,FALSE),"") -> MAGGI Crema Esparragos 20x68g | J78: 216 | L78: 46600
A79: 78 | B79: 2 | C79: A | D79: =IF(AND('Sectorizacion Racks'!$B79=B78,C78='Sectorizacion Racks'!$C79),D78+1,1) -> 6 | E79: =+CONCATENATE('Sectorizacion Racks'!$C79,'Sectorizacion Racks'!$D79) -> A6 | F79: =+CONCATENATE(B79,C79,D79) -> 2A6 | G79: 69780 | H79: =IFERROR(VLOOKUP(G79,'Consulta Stock'!$E$2:$G$5087,3,0),"") -> Lacteos Culinarios | I79: =IFERROR(VLOOKUP('Sectorizacion Racks'!$G79,'Consulta Stock'!$E$2:$F$5447,2,FALSE),"") -> NESTLE EL MANJAR Bolsa 48x200g | J79: 75 | L79: 46478
A80: 79 | B80: 2 | C80: A | D80: =IF(AND('Sectorizacion Racks'!$B80=B79,C79='Sectorizacion Racks'!$C80),D79+1,1) -> 7 | E80: =+CONCATENATE('Sectorizacion Racks'!$C80,'Sectorizacion Racks'!$D80) -> A7 | F80: =+CONCATENATE(B80,C80,D80) -> 2A7 | G80: 30200 | I80: =IFERROR(VLOOKUP('Sectorizacion Racks'!$G80,'Consulta Stock'!$E$2:$F$5447,2,FALSE),"") -> Crema MAGGI sabor Pollo Sobre 20 x 72 GRM | J80: 216 | L80: 46661
A81: 80 | B81: 2 | C81: A | D81: =IF(AND('Sectorizacion Racks'!$B81=B80,C80='Sectorizacion Racks'!$C81),D80+1,1) -> 8 | E81: =+CONCATENATE('Sectorizacion Racks'!$C81,'Sectorizacion Racks'!$D81) -> A8 | F81: =+CONCATENATE(B81,C81,D81) -> 2A8 | G81: 69780 | H81: =IFERROR(VLOOKUP(G81,'Consulta Stock'!$E$2:$G$5087,3,0),"") -> Lacteos Culinarios | I81: =IFERROR(VLOOKUP('Sectorizacion Racks'!$G81,'Consulta Stock'!$E$2:$F$5447,2,FALSE),"") -> NESTLE EL MANJAR Bolsa 48x200g | J81: 75 | L81: 46478
A82: 81 | B82: 2 | C82: A | D82: =IF(AND('Sectorizacion Racks'!$B82=B81,C81='Sectorizacion Racks'!$C82),D81+1,1) -> 9 | E82: =+CONCATENATE('Sectorizacion Racks'!$C82,'Sectorizacion Racks'!$D82) -> A9 | F82: =+CONCATENATE(B82,C82,D82) -> 2A9 | G82: 65820 | H82: =IFERROR(VLOOKUP(G82,'Consulta Stock'!$E$2:$G$5087,3,0),"") -> Leche en Polvo | I82: =IFERROR(VLOOKUP('Sectorizacion Racks'!$G82,'Consulta Stock'!$E$2:$F$5447,2,FALSE),"") -> NIDO Buen Dia LSP Softpack 12x700g | J82: 32 | L82: 46569
A83: 82 | B83: 2 | C83: A | D83: =IF(AND('Sectorizacion Racks'!$B83=B82,C82='Sectorizacion Racks'!$C83),D82+1,1) -> 10 | E83: =+CONCATENATE('Sectorizacion Racks'!$C83,'Sectorizacion Racks'!$D83) -> A10 | F83: =+CONCATENATE(B83,C83,D83) -> 2A10 | H83: =IFERROR(VLOOKUP(G83,'Consulta Stock'!$E$2:$G$5087,3,0),"") | I83: =IFERROR(VLOOKUP('Sectorizacion Racks'!$G83,'Consulta Stock'!$E$2:$F$5447,2,FALSE),"")
A84: 83 | B84: 2 | C84: A | D84: =IF(AND('Sectorizacion Racks'!$B84=B83,C83='Sectorizacion Racks'!$C84),D83+1,1) -> 11 | E84: =+CONCATENATE('Sectorizacion Racks'!$C84,'Sectorizacion Racks'!$D84) -> A11 | F84: =+CONCATENATE(B84,C84,D84) -> 2A11 | G84: 301601 | H84: =IFERROR(VLOOKUP(G84,'Consulta Stock'!$E$2:$G$5087,3,0),"") -> CULINARIOS | I84: =IFERROR(VLOOKUP('Sectorizacion Racks'!$G84,'Consulta Stock'!$E$2:$F$5447,2,FALSE),"") -> MAGGI Sopa Caracolitos 16x76g CL 16x76g | J84: 216 | L84: 46631
A85: 84 | B85: 2 | C85: A | D85: =IF(AND('Sectorizacion Racks'!$B85=B84,C84='Sectorizacion Racks'!$C85),D84+1,1) -> 12 | E85: =+CONCATENATE('Sectorizacion Racks'!$C85,'Sectorizacion Racks'!$D85) -> A12 | F85: =+CONCATENATE(B85,C85,D85) -> 2A12 | H85: =IFERROR(VLOOKUP(G85,'Consulta Stock'!$E$2:$G$5087,3,0),"") | I85: =IFERROR(VLOOKUP('Sectorizacion Racks'!$G85,'Consulta Stock'!$E$2:$F$5447,2,FALSE),"")
A86: 85 | B86: 2 | C86: A | D86: =IF(AND('Sectorizacion Racks'!$B86=B85,C85='Sectorizacion Racks'!$C86),D85+1,1) -> 13 | E86: =+CONCATENATE('Sectorizacion Racks'!$C86,'Sectorizacion Racks'!$D86) -> A13 | F86: =+CONCATENATE(B86,C86,D86) -> 2A13 | G86: 301601 | H86: =IFERROR(VLOOKUP(G86,'Consulta Stock'!$E$2:$G$5087,3,0),"") -> CULINARIOS | I86: =IFERROR(VLOOKUP('Sectorizacion Racks'!$G86,'Consulta Stock'!$E$2:$F$5447,2,FALSE),"") -> MAGGI Sopa Caracolitos 16x76g CL 16x76g | J86: 216 | L86: 46631
A87: 86 | B87: 2 | C87: A | D87: =IF(AND('Sectorizacion Racks'!$B87=B86,C86='Sectorizacion Racks'!$C87),D86+1,1) -> 14 | E87: =+CONCATENATE('Sectorizacion Racks'!$C87,'Sectorizacion Racks'!$D87) -> A14 | F87: =+CONCATENATE(B87,C87,D87) -> 2A14 | G87: 1330 | H87: =IFERROR(VLOOKUP(G87,'Consulta Stock'!$E$2:$G$5087,3,0),"") -> Lacteos Culinarios | I87: =IFERROR(VLOOKUP('Sectorizacion Racks'!$G87,'Consulta Stock'!$E$2:$F$5447,2,FALSE),"") -> Crema de leche NESTLE Lata 48x157g | J87: 80 | L87: 46753
A88: 87 | B88: 2 | C88: A | D88: =IF(AND('Sectorizacion Racks'!$B88=B87,C87='Sectorizacion Racks'!$C88),D87+1,1) -> 15 | E88: =+CONCATENATE('Sectorizacion Racks'!$C88,'Sectorizacion Racks'!$D88) -> A15 | F88: =+CONCATENATE(B88,C88,D88) -> 2A15 | G88: 63550 | H88: =IFERROR(VLOOKUP(G88,'Consulta Stock'!$E$2:$G$5087,3,0),"") -> Lacteos Culinarios | I88: =IFERROR(VLOOKUP('Sectorizacion Racks'!$G88,'Consulta Stock'!$E$2:$F$5447,2,FALSE),"") -> LECHE SUR Sucedaneo LC Tarro 48x397g | J88: 48 | L88: 46569
A89: 88 | B89: 2 | C89: A | D89: =IF(AND('Sectorizacion Racks'!$B89=B88,C88='Sectorizacion Racks'!$C89),D88+1,1) -> 16 | E89: =+CONCATENATE('Sectorizacion Racks'!$C89,'Sectorizacion Racks'!$D89) -> A16 | F89: =+CONCATENATE(B89,C89,D89) -> 2A16 | G89: 90420 | H89: =IFERROR(VLOOKUP(G89,'Consulta Stock'!$E$2:$G$5087,3,0),"") -> Leche en Polvo | I89: =IFERROR(VLOOKUP('Sectorizacion Racks'!$G89,'Consulta Stock'!$E$2:$F$5447,2,FALSE),"") -> NIDO Buen Dia LSP PDQ 384x700g | J89: 1 | L89: 46631
A90: 89 | B90: 2 | C90: A | D90: =IF(AND('Sectorizacion Racks'!$B90=B89,C89='Sectorizacion Racks'!$C90),D89+1,1) -> 17 | E90: =+CONCATENATE('Sectorizacion Racks'!$C90,'Sectorizacion Racks'!$D90) -> A17 | F90: =+CONCATENATE(B90,C90,D90) -> 2A17 | G90: 81250 | H90: =IFERROR(VLOOKUP(G90,'Consulta Stock'!$E$2:$G$5087,3,0),"") -> OPPB | I90: =IFERROR(VLOOKUP('Sectorizacion Racks'!$G90,'Consulta Stock'!$E$2:$F$5447,2,FALSE),"") -> Saborizante NESQUIK OPTISTAR Chocolate 18x180g | J90: 72 | L90: 46905
A91: 90 | B91: 2 | C91: A | D91: =IF(AND('Sectorizacion Racks'!$B91=B90,C90='Sectorizacion Racks'!$C91),D90+1,1) -> 18 | E91: =+CONCATENATE('Sectorizacion Racks'!$C91,'Sectorizacion Racks'!$D91) -> A18 | F91: =+CONCATENATE(B91,C91,D91) -> 2A18 | G91: 63550 | H91: =IFERROR(VLOOKUP(G91,'Consulta Stock'!$E$2:$G$5087,3,0),"") -> Lacteos Culinarios | I91: =IFERROR(VLOOKUP('Sectorizacion Racks'!$G91,'Consulta Stock'!$E$2:$F$5447,2,FALSE),"") -> LECHE SUR Sucedaneo LC Tarro 48x397g | J91: 48 | L91: 46569
A92: 91 | B92: 2 | C92: A | D92: =IF(AND('Sectorizacion Racks'!$B92=B91,C91='Sectorizacion Racks'!$C92),D91+1,1) -> 19 | E92: =+CONCATENATE('Sectorizacion Racks'!$C92,'Sectorizacion Racks'!$D92) -> A19 | F92: =+CONCATENATE(B92,C92,D92) -> 2A19 | G92: 69780 | H92: =IFERROR(VLOOKUP(G92,'Consulta Stock'!$E$2:$G$5087,3,0),"") -> Lacteos Culinarios | I92: =IFERROR(VLOOKUP('Sectorizacion Racks'!$G92,'Consulta Stock'!$E$2:$F$5447,2,FALSE),"") -> NESTLE EL MANJAR Bolsa 48x200g | J92: 75 | L92: 46478
A93: 92 | B93: 2 | C93: A | D93: =IF(AND('Sectorizacion Racks'!$B93=B92,C92='Sectorizacion Racks'!$C93),D92+1,1) -> 20 | E93: =+CONCATENATE('Sectorizacion Racks'!$C93,'Sectorizacion Racks'!$D93) -> A20 | F93: =+CONCATENATE(B93,C93,D93) -> 2A20 | G93: 38850 | H93: =IFERROR(VLOOKUP(G93,'Consulta Stock'!$E$2:$G$5087,3,0),"") -> CAFES | I93: =IFERROR(VLOOKUP('Sectorizacion Racks'!$G93,'Consulta Stock'!$E$2:$F$5447,2,FALSE),"") -> Cafe NESCAFE Tradicion tarro 24x50g | J93: 98 | L93: 46844
A94: 93 | B94: 2 | C94: A | D94: =IF(AND('Sectorizacion Racks'!$B94=B93,C93='Sectorizacion Racks'!$C94),D93+1,1) -> 21 | E94: =+CONCATENATE('Sectorizacion Racks'!$C94,'Sectorizacion Racks'!$D94) -> A21 | F94: =+CONCATENATE(B94,C94,D94) -> 2A21 | H94: =IFERROR(VLOOKUP(G94,'Consulta Stock'!$E$2:$G$5087,3,0),"") | I94: =IFERROR(VLOOKUP('Sectorizacion Racks'!$G94,'Consulta Stock'!$E$2:$F$5447,2,FALSE),"")
A95: 94 | B95: 2 | C95: A | D95: =IF(AND('Sectorizacion Racks'!$B95=B94,C94='Sectorizacion Racks'!$C95),D94+1,1) -> 22 | E95: =+CONCATENATE('Sectorizacion Racks'!$C95,'Sectorizacion Racks'!$D95) -> A22 | F95: =+CONCATENATE(B95,C95,D95) -> 2A22 | G95: 36602 | H95: =IFERROR(VLOOKUP(G95,'Consulta Stock'!$E$2:$G$5087,3,0),"") -> CAFES | I95: =IFERROR(VLOOKUP('Sectorizacion Racks'!$G95,'Consulta Stock'!$E$2:$F$5447,2,FALSE),"") -> NESCAFE Moka 6(8x18g) N2 CL 6(8x18g) | J95: 175 | L95: 46447
A96: 95 | B96: 2 | C96: A | D96: =IF(AND('Sectorizacion Racks'!$B96=B95,C95='Sectorizacion Racks'!$C96),D95+1,1) -> 23 | E96: =+CONCATENATE('Sectorizacion Racks'!$C96,'Sectorizacion Racks'!$D96) -> A23 | F96: =+CONCATENATE(B96,C96,D96) -> 2A23 | G96: 2320 | H96: =IFERROR(VLOOKUP(G96,'Consulta Stock'!$E$2:$G$5087,3,0),"") -> CAFES | I96: =IFERROR(VLOOKUP('Sectorizacion Racks'!$G96,'Consulta Stock'!$E$2:$F$5447,2,FALSE),"") -> Bebida a base de cebada ECCO 24 x 170 GRM | J96: 32 | L96: 46874
A97: 96 | B97: 2 | C97: A | D97: =IF(AND('Sectorizacion Racks'!$B97=B96,C96='Sectorizacion Racks'!$C97),D96+1,1) -> 24 | E97: =+CONCATENATE('Sectorizacion Racks'!$C97,'Sectorizacion Racks'!$D97) -> A24 | F97: =+CONCATENATE(B97,C97,D97) -> 2A24 | G97: 1340 | H97: =IFERROR(VLOOKUP(G97,'Consulta Stock'!$E$2:$G$5087,3,0),"") -> Lacteos Culinarios | I97: =IFERROR(VLOOKUP('Sectorizacion Racks'!$G97,'Consulta Stock'!$E$2:$F$5447,2,FALSE),"") -> Crema de leche NESTLE Lata 48 x 236 GRM | J97: 56 | L97: 46874
A98: 97 | B98: 2 | C98: B | D98: =IF(AND('Sectorizacion Racks'!$B98=B97,C97='Sectorizacion Racks'!$C98),D97+1,1) -> 1 | E98: =+CONCATENATE('Sectorizacion Racks'!$C98,'Sectorizacion Racks'!$D98) -> B1 | F98: =+CONCATENATE(B98,C98,D98) -> 2B1 | G98: 38850 | H98: =IFERROR(VLOOKUP(G98,'Consulta Stock'!$E$2:$G$5087,3,0),"") -> CAFES | I98: =IFERROR(VLOOKUP('Sectorizacion Racks'!$G98,'Consulta Stock'!$E$2:$F$5447,2,FALSE),"") -> Cafe NESCAFE Tradicion tarro 24x50g | J98: 98 | L98: 46844
A99: 98 | B99: 2 | C99: B | D99: =IF(AND('Sectorizacion Racks'!$B99=B98,C98='Sectorizacion Racks'!$C99),D98+1,1) -> 2 | E99: =+CONCATENATE('Sectorizacion Racks'!$C99,'Sectorizacion Racks'!$D99) -> B2 | F99: =+CONCATENATE(B99,C99,D99) -> 2B2 | G99: 2320 | H99: =IFERROR(VLOOKUP(G99,'Consulta Stock'!$E$2:$G$5087,3,0),"") -> CAFES | I99: =IFERROR(VLOOKUP('Sectorizacion Racks'!$G99,'Consulta Stock'!$E$2:$F$5447,2,FALSE),"") -> Bebida a base de cebada ECCO 24 x 170 GRM | J99: 32 | L99: 46844
A100: 99 | B100: 2 | C100: B | D100: =IF(AND('Sectorizacion Racks'!$B100=B99,C99='Sectorizacion Racks'!$C100),D99+1,1) -> 3 | E100: =+CONCATENATE('Sectorizacion Racks'!$C100,'Sectorizacion Racks'!$D100) -> B3 | F100: =+CONCATENATE(B100,C100,D100) -> 2B3 | G100: 90630 | H100: =IFERROR(VLOOKUP(G100,'Consulta Stock'!$E$2:$G$5087,3,0),"") -> CULINARIOS | I100: =IFERROR(VLOOKUP('Sectorizacion Racks'!$G100,'Consulta Stock'!$E$2:$F$5447,2,FALSE),"") -> MAGGI Sopa Costilla 20x60g N2 CL | J100: 216 | L100: 46600
A101: 100 | B101: 2 | C101: B | D101: =IF(AND('Sectorizacion Racks'!$B101=B100,C100='Sectorizacion Racks'!$C101),D100+1,1) -> 4 | E101: =+CONCATENATE('Sectorizacion Racks'!$C101,'Sectorizacion Racks'!$D101) -> B4 | F101: =+CONCATENATE(B101,C101,D101) -> 2B4 | G101: 36540 | H101: =IFERROR(VLOOKUP(G101,'Consulta Stock'!$E$2:$G$5087,3,0),"") -> CAFES | I101: =IFERROR(VLOOKUP('Sectorizacion Racks'!$G101,'Consulta Stock'!$E$2:$F$5447,2,FALSE),"") -> NESCAFE Doble Choca Moka 6(8x23g) XR 6(8x23g) | J101: 175 | L101: 46539
A102: 101 | B102: 2 | C102: B | D102: =IF(AND('Sectorizacion Racks'!$B102=B101,C101='Sectorizacion Racks'!$C102),D101+1,1) -> 5 | E102: =+CONCATENATE('Sectorizacion Racks'!$C102,'Sectorizacion Racks'!$D102) -> B5 | F102: =+CONCATENATE(B102,C102,D102) -> 2B5 | G102: 2320 | H102: =IFERROR(VLOOKUP(G102,'Consulta Stock'!$E$2:$G$5087,3,0),"") -> CAFES | I102: =IFERROR(VLOOKUP('Sectorizacion Racks'!$G102,'Consulta Stock'!$E$2:$F$5447,2,FALSE),"") -> Bebida a base de cebada ECCO 24 x 170 GRM | J102: 32 | L102: 46844
A103: 102 | B103: 2 | C103: B | D103: =IF(AND('Sectorizacion Racks'!$B103=B102,C102='Sectorizacion Racks'!$C103),D102+1,1) -> 6 | E103: =+CONCATENATE('Sectorizacion Racks'!$C103,'Sectorizacion Racks'!$D103) -> B6 | F103: =+CONCATENATE(B103,C103,D103) -> 2B6 | G103: 90630 | H103: =IFERROR(VLOOKUP(G103,'Consulta Stock'!$E$2:$G$5087,3,0),"") -> CULINARIOS | I103: =IFERROR(VLOOKUP('Sectorizacion Racks'!$G103,'Consulta Stock'!$E$2:$F$5447,2,FALSE),"") -> MAGGI Sopa Costilla 20x60g N2 CL | J103: 216 | L103: 46600
A104: 103 | B104: 2 | C104: B | D104: =IF(AND('Sectorizacion Racks'!$B104=B103,C103='Sectorizacion Racks'!$C104),D103+1,1) -> 7 | E104: =+CONCATENATE('Sectorizacion Racks'!$C104,'Sectorizacion Racks'!$D104) -> B7 | F104: =+CONCATENATE(B104,C104,D104) -> 2B7 | G104: 36540 | H104: =IFERROR(VLOOKUP(G104,'Consulta Stock'!$E$2:$G$5087,3,0),"") -> CAFES | I104: =IFERROR(VLOOKUP('Sectorizacion Racks'!$G104,'Consulta Stock'!$E$2:$F$5447,2,FALSE),"") -> NESCAFE Doble Choca Moka 6(8x23g) XR 6(8x23g) | J104: 175 | L104: 46539
A105: 104 | B105: 2 | C105: B | D105: =IF(AND('Sectorizacion Racks'!$B105=B104,C104='Sectorizacion Racks'!$C105),D104+1,1) -> 8 | E105: =+CONCATENATE('Sectorizacion Racks'!$C105,'Sectorizacion Racks'!$D105) -> B8 | F105: =+CONCATENATE(B105,C105,D105) -> 2B8 | G105: 90630 | H105: =IFERROR(VLOOKUP(G105,'Consulta Stock'!$E$2:$G$5087,3,0),"") -> CULINARIOS | I105: =IFERROR(VLOOKUP('Sectorizacion Racks'!$G105,'Consulta Stock'!$E$2:$F$5447,2,FALSE),"") -> MAGGI Sopa Costilla 20x60g N2 CL | J105: 216 | L105: 46600
A106: 105 | B106: 2 | C106: B | D106: =IF(AND('Sectorizacion Racks'!$B106=B105,C105='Sectorizacion Racks'!$C106),D105+1,1) -> 9 | E106: =+CONCATENATE('Sectorizacion Racks'!$C106,'Sectorizacion Racks'!$D106) -> B9 | F106: =+CONCATENATE(B106,C106,D106) -> 2B9 | G106: 90630 | H106: =IFERROR(VLOOKUP(G106,'Consulta Stock'!$E$2:$G$5087,3,0),"") -> CULINARIOS | I106: =IFERROR(VLOOKUP('Sectorizacion Racks'!$G106,'Consulta Stock'!$E$2:$F$5447,2,FALSE),"") -> MAGGI Sopa Costilla 20x60g N2 CL | J106: 216 | L106: 46600
... A124: 123 | B124: 2 | C124: C | D124: =IF(AND('Sectorizacion Racks'!$B124=B123,C123='Sectorizacion Racks'!$C124),D123+1,1) -> 3 | E124: =+CONCATENATE('Sectorizacion Racks'!$C124,'Sectorizacion Racks'!$D124) -> C3 | F124: =+CONCATENATE(B124,C124,D124) -> 2C3 | G124: 38850 | H124: =IFERROR(VLOOKUP(G124,'Consulta Stock'!$E$2:$G$5087,3,0),"") -> CAFES | I124: =IFERROR(VLOOKUP('Sectorizacion Racks'!$G124,'Consulta Stock'!$E$2:$F$5447,2,FALSE),"") -> Cafe NESCAFE Tradicion tarro 24x50g | J124: 98 | L124: 46844
A125: 124 | B125: 2 | C125: C | D125: =IF(AND('Sectorizacion Racks'!$B125=B124,C124='Sectorizacion Racks'!$C125),D124+1,1) -> 4 | E125: =+CONCATENATE('Sectorizacion Racks'!$C125,'Sectorizacion Racks'!$D125) -> C4 | F125: =+CONCATENATE(B125,C125,D125) -> 2C4 | H125: =IFERROR(VLOOKUP(G125,'Consulta Stock'!$E$2:$G$5087,3,0),"") | I125: =IFERROR(VLOOKUP('Sectorizacion Racks'!$G125,'Consulta Stock'!$E$2:$F$5447,2,FALSE),"")
A126: 125 | B126: 2 | C126: C | D126: =IF(AND('Sectorizacion Racks'!$B126=B125,C125='Sectorizacion Racks'!$C126),D125+1,1) -> 5 | E126: =+CONCATENATE('Sectorizacion Racks'!$C126,'Sectorizacion Racks'!$D126) -> C5 | F126: =+CONCATENATE(B126,C126,D126) -> 2C5 | H126: =IFERROR(VLOOKUP(G126,'Consulta Stock'!$E$2:$G$5087,3,0),"") | I126: =IFERROR(VLOOKUP('Sectorizacion Racks'!$G126,'Consulta Stock'!$E$2:$F$5447,2,FALSE),"")
A127: 126 | B127: 2 | C127: C | D127: =IF(AND('Sectorizacion Racks'!$B127=B126,C126='Sectorizacion Racks'!$C127),D126+1,1) -> 6 | E127: =+CONCATENATE('Sectorizacion Racks'!$C127,'Sectorizacion Racks'!$D127) -> C6 | F127: =+CONCATENATE(B127,C127,D127) -> 2C6 | G127: 5480 | H127: =IFERROR(VLOOKUP(G127,'Consulta Stock'!$E$2:$G$5087,3,0),"") -> CULINARIOS | I127: =IFERROR(VLOOKUP('Sectorizacion Racks'!$G127,'Consulta Stock'!$E$2:$F$5447,2,FALSE),"") -> MAGGI SOPA Pollo Fideos 20x70g | J127: 216 | L127: 46631
A128: 127 | B128: 2 | C128: C | D128: =IF(AND('Sectorizacion Racks'!$B128=B127,C127='Sectorizacion Racks'!$C128),D127+1,1) -> 7 | E128: =+CONCATENATE('Sectorizacion Racks'!$C128,'Sectorizacion Racks'!$D128) -> C7 | F128: =+CONCATENATE(B128,C128,D128) -> 2C7 | G128: 36602 | H128: =IFERROR(VLOOKUP(G128,'Consulta Stock'!$E$2:$G$5087,3,0),"") -> CAFES | I128: =IFERROR(VLOOKUP('Sectorizacion Racks'!$G128,'Consulta Stock'!$E$2:$F$5447,2,FALSE),"") -> NESCAFE Moka 6(8x18g) N2 CL 6(8x18g) | J128: 175 | L128: 46447
A129: 128 | B129: 2 | C129: C | D129: =IF(AND('Sectorizacion Racks'!$B129=B128,C128='Sectorizacion Racks'!$C129),D128+1,1) -> 8 | E129: =+CONCATENATE('Sectorizacion Racks'!$C129,'Sectorizacion Racks'!$D129) -> C8 | F129: =+CONCATENATE(B129,C129,D129) -> 2C8 | G129: 67290 | H129: =IFERROR(VLOOKUP(G129,'Consulta Stock'!$E$2:$G$5087,3,0),"") -> CULINARIOS | I129: =IFERROR(VLOOKUP('Sectorizacion Racks'!$G129,'Consulta Stock'!$E$2:$F$5447,2,FALSE),"") -> MAGGI Pure de Papas 12x187g CL 12x187g | J129: 50 | L129: 46569
A130: 129 | B130: 2 | C130: C | D130: =IF(AND('Sectorizacion Racks'!$B130=B129,C129='Sectorizacion Racks'!$C130),D129+1,1) -> 9 | E130: =+CONCATENATE('Sectorizacion Racks'!$C130,'Sectorizacion Racks'!$D130) -> C9 | F130: =+CONCATENATE(B130,C130,D130) -> 2C9 | G130: 67290 | H130: =IFERROR(VLOOKUP(G130,'Consulta Stock'!$E$2:$G$5087,3,0),"") -> CULINARIOS | I130: =IFERROR(VLOOKUP('Sectorizacion Racks'!$G130,'Consulta Stock'!$E$2:$F$5447,2,FALSE),"") -> MAGGI Pure de Papas 12x187g CL 12x187g | J130: 50 | L130: 46569
A131: 130 | B131: 2 | C131: C | D131: =IF(AND('Sectorizacion Racks'!$B131=B130,C130='Sectorizacion Racks'!$C131),D130+1,1) -> 10 | E131: =+CONCATENATE('Sectorizacion Racks'!$C131,'Sectorizacion Racks'!$D131) -> C10 | F131: =+CONCATENATE(B131,C131,D131) -> 2C10 | G131: 5480 | H131: =IFERROR(VLOOKUP(G131,'Consulta Stock'!$E$2:$G$5087,3,0),"") -> CULINARIOS | I131: =IFERROR(VLOOKUP('Sectorizacion Racks'!$G131,'Consulta Stock'!$E$2:$F$5447,2,FALSE),"") -> MAGGI SOPA Pollo Fideos 20x70g | J131: 216 | L131: 46631
A132: 131 | B132: 2 | C132: C | D132: =IF(AND('Sectorizacion Racks'!$B132=B131,C131='Sectorizacion Racks'!$C132),D131+1,1) -> 11 | E132: =+CONCATENATE('Sectorizacion Racks'!$C132,'Sectorizacion Racks'!$D132) -> C11 | F132: =+CONCATENATE(B132,C132,D132) -> 2C11 | G132: 5480 | H132: =IFERROR(VLOOKUP(G132,'Consulta Stock'!$E$2:$G$5087,3,0),"") -> CULINARIOS | I132: =IFERROR(VLOOKUP('Sectorizacion Racks'!$G132,'Consulta Stock'!$E$2:$F$5447,2,FALSE),"") -> MAGGI SOPA Pollo Fideos 20x70g | J132: 216 | L132: 46631
A133: 132 | B133: 2 | C133: C | D133: =IF(AND('Sectorizacion Racks'!$B133=B132,C132='Sectorizacion Racks'!$C133),D132+1,1) -> 12 | E133: =+CONCATENATE('Sectorizacion Racks'!$C133,'Sectorizacion Racks'!$D133) -> C12 | F133: =+CONCATENATE(B133,C133,D133) -> 2C12 | G133: 50940 | H133: =IFERROR(VLOOKUP(G133,'Consulta Stock'!$E$2:$G$5087,3,0),"") -> CAFES | I133: =IFERROR(VLOOKUP('Sectorizacion Racks'!$G133,'Consulta Stock'!$E$2:$F$5447,2,FALSE),"") -> Cafe NESCAFE Tradicion tarro 12X400G | J133: 30 | L133: 46905
A134: 133 | B134: 2 | C134: C | D134: =IF(AND('Sectorizacion Racks'!$B134=B133,C133='Sectorizacion Racks'!$C134),D133+1,1) -> 13 | E134: =+CONCATENATE('Sectorizacion Racks'!$C134,'Sectorizacion Racks'!$D134) -> C13 | F134: =+CONCATENATE(B134,C134,D134) -> 2C13 | H134: =IFERROR(VLOOKUP(G134,'Consulta Stock'!$E$2:$G$5087,3,0),"") | I134: =IFERROR(VLOOKUP('Sectorizacion Racks'!$G134,'Consulta Stock'!$E$2:$F$5447,2,FALSE),"")
A135: 134 | B135: 2 | C135: C | D135: =IF(AND('Sectorizacion Racks'!$B135=B134,C134='Sectorizacion Racks'!$C135),D134+1,1) -> 14 | E135: =+CONCATENATE('Sectorizacion Racks'!$C135,'Sectorizacion Racks'!$D135) -> C14 | F135: =+CONCATENATE(B135,C135,D135) -> 2C14 | G135: 25770 | H135: =IFERROR(VLOOKUP(G135,'Consulta Stock'!$E$2:$G$5087,3,0),"") -> CEREALES PARA EL DESAYUNO | I135: =IFERROR(VLOOKUP('Sectorizacion Racks'!$G135,'Consulta Stock'!$E$2:$F$5447,2,FALSE),"") -> Cereal MILO 60 x 30g | J135: 72 | L135: 46357
A136: 135 | B136: 2 | C136: C | D136: =IF(AND('Sectorizacion Racks'!$B136=B135,C135='Sectorizacion Racks'!$C136),D135+1,1) -> 15 | E136: =+CONCATENATE('Sectorizacion Racks'!$C136,'Sectorizacion Racks'!$D136) -> C15 | F136: =+CONCATENATE(B136,C136,D136) -> 2C15 | G136: 62620 | H136: =IFERROR(VLOOKUP(G136,'Consulta Stock'!$E$2:$G$5087,3,0),"") -> CEREALES PARA EL DESAYUNO | I136: =IFERROR(VLOOKUP('Sectorizacion Racks'!$G136,'Consulta Stock'!$E$2:$F$5447,2,FALSE),"") -> CHOCAPIC Cer N1 CL 18x350g | J136: 48 | L136: 46478
A137: 136 | B137: 2 | C137: C | D137: =IF(AND('Sectorizacion Racks'!$B137=B136,C136='Sectorizacion Racks'!$C137),D136+1,1) -> 16 | E137: =+CONCATENATE('Sectorizacion Racks'!$C137,'Sectorizacion Racks'!$D137) -> C16 | F137: =+CONCATENATE(B137,C137,D137) -> 2C16 | G137: 50940 | H137: =IFERROR(VLOOKUP(G137,'Consulta Stock'!$E$2:$G$5087,3,0),"") -> CAFES | I137: =IFERROR(VLOOKUP('Sectorizacion Racks'!$G137,'Consulta Stock'!$E$2:$F$5447,2,FALSE),"") -> Cafe NESCAFE Tradicion tarro 12X400G | J137: 30 | L137: 46905
A138: 137 | B138: 2 | C138: C | D138: =IF(AND('Sectorizacion Racks'!$B138=B137,C137='Sectorizacion Racks'!$C138),D137+1,1) -> 17 | E138: =+CONCATENATE('Sectorizacion Racks'!$C138,'Sectorizacion Racks'!$D138) -> C17 | F138: =+CONCATENATE(B138,C138,D138) -> 2C17 | G138: 65820 | H138: =IFERROR(VLOOKUP(G138,'Consulta Stock'!$E$2:$G$5087,3,0),"") -> Leche en Polvo | I138: =IFERROR(VLOOKUP('Sectorizacion Racks'!$G138,'Consulta Stock'!$E$2:$F$5447,2,FALSE),"") -> NIDO Buen Dia LSP Softpack 12x700g | J138: 32 | L138: 46569
A139: 138 | B139: 2 | C139: C | D139: =IF(AND('Sectorizacion Racks'!$B139=B138,C138='Sectorizacion Racks'!$C139),D138+1,1) -> 18 | E139: =+CONCATENATE('Sectorizacion Racks'!$C139,'Sectorizacion Racks'!$D139) -> C18 | F139: =+CONCATENATE(B139,C139,D139) -> 2C18 | G139: 50810 | H139: =IFERROR(VLOOKUP(G139,'Consulta Stock'!$E$2:$G$5087,3,0),"") -> CAFES | I139: =IFERROR(VLOOKUP('Sectorizacion Racks'!$G139,'Consulta Stock'!$E$2:$F$5447,2,FALSE),"") -> Cafe NESCAFE 3 en 1 24(8X24G) | J139: 60 | L139: 46508
...

Sheet Stock InfoDia
A1: Consulta_Stock_20251215 | B1: SOCIEDAD COMERCIAL PAN DE AZUCAR S.P.A.
A5: Fecha: 15-12-2025
A6: Sucursal: MATRI
A7: Bodega: BOD01
I8: Disponible | K8: Reservado | M8: Mal Estado | O8: Total
A9: Línea | B9: Categoría | C9: Agrupación | D9: Prod. Base | E9: Articulo | G9: Descripción | H9: Medidas | I9: U.V | J9: Fracción | K9: U.V | L9: Fracción | M9: U.V | N9: Fracción | O9: U.V | P9: Fracción
A10: DESHABILITADOS | B10: DESHABILITADOS | C10: DESHABILITADOS | D10: DESHABILITADOS | E10: 2 | F10: 0 | G10: PROMO AZUCAR ABL | I10: 0 | J10: 0 | K10: 0 | L10: 0 | M10: 0 | N10: 0 | O10: 0 | P10: 0
A11: DESHABILITADOS | B11: DESHABILITADOS | C11: DESHABILITADOS | D11: DESHABILITADOS | E11: 3 | F11: 0 | G11: PROMO FIDEOS | I11: 0 | J11: 0 | K11: 0 | L11: 0 | M11: 0 | N11: 0 | O11: 0 | P11: 0
A12: DESHABILITADOS | B12: DESHABILITADOS | C12: DESHABILITADOS | D12: DESHABILITADOS | E12: 4 | F12: 0 | G12: PROMO AZUCAR | I12: 0 | J12: 0 | K12: 0 | L12: 0 | M12: 0 | N12: 0 | O12: 0 | P12: 0
A13: DESHABILITADOS | B13: DESHABILITADOS | C13: DESHABILITADOS | D13: DESHABILITADOS | E13: 5 | F13: 0 | G13: COMBO 12.000 CFT BACK TO SCHOOL | I13: 0 | J13: 0 | K13: 0 | L13: 0 | M13: 0 | N13: 0 | O13: 0 | P13: 0
A14: DESHABILITADOS | B14: DESHABILITADOS | C14: DESHABILITADOS | D14: DESHABILITADOS | E14: 6 | F14: 0 | G14: COMBO 17.000 CFT BACK TO SCHOOL | I14: 0 | J14: 0 | K14: 0 | L14: 0 | M14: 0 | N14: 0 | O14: 0 | P14: 0
A15: DESHABILITADOS | B15: DESHABILITADOS | C15: DESHABILITADOS | D15: DESHABILITADOS | E15: 7 | F15: 0 | G15: COMBO 23.000 CFT BACK TO SCHOOL | I15: 0 | J15: 0 | K15: 0 | L15: 0 | M15: 0 | N15: 0 | O15: 0 | P15: 0
A16: DESHABILITADOS | B16: DESHABILITADOS | C16: DESHABILITADOS | D16: DESHABILITADOS | E16: 8 | F16: 0 | G16: SET ESCOLAR COLLEGE | I16: 0 | J16: 0 | K16: 0 | L16: 0 | M16: 0 | N16: 0 | O16: 0 | P16: 0
A17: DESHABILITADOS | B17: DESHABILITADOS | C17: DESHABILITADOS | D17: DESHABILITADOS | E17: 9 | F17: 0 | G17: SET ESCOLAR JUNIOR | I17: 0 | J17: 0 | K17: 0 | L17: 0 | M17: 0 | N17: 0 | O17: 0 | P17: 0
A18: CONFITES | B18: CHOCOLATES | C18: BOLSAS PROMO | D18: PROMO BOLSAS | E18: 10 | F18: 0 | G18: BOLSAS PROMO | H18: 28 x 35 GRS | I18: 0 | J18: 0 | K18: 0 | L18: 0 | M18: 0 | N18: 0 | O18: 0 | P18: 0
A19: TRADICIONAL | B19: CULINARIOS | C19: SET DE CUBIERTOS | D19: PROMO CUBIERTOS | E19: 11 | F19: 0 | G19: SET DE CUBIERTOS | I19: 0 | J19: 0 | K19: 0 | L19: 0 | M19: 0 | N19: 0 | O19: 0 | P19: 0
A20: TRADICIONAL | B20: CULINARIOS | C20: PROMO CULINARIO | D20: PROMO CULINARIO | E20: 12 | F20: 0 | G20: Regalo Promocional Maggi | I20: 0 | J20: 0 | K20: 0 | L20: 0 | M20: 0 | N20: 0 | O20: 0 | P20: 0
A21: TRADICIONAL | B21: CAFES | C21: EXHIBIDOR | D21: NDG Trade | E21: 13 | F21: 0 | G21: EXHIBIDOR NESCAFE | H21: 1 | I21: 0 | J21: 0 | K21: 0 | L21: 0 | M21: 0 | N21: 0 | O21: 0 | P21: 0
A22: TRADICIONAL | B22: CULINARIOS | C22: EXHIBIDOR2 | D22: EXHIBIDOR CALDOS | E22: 14 | F22: 0 | G22: DISPENSADOR MAGGI | H22: 1 | I22: 0 | J22: 0 | K22: 0 | L22: 0 | M22: 0 | N22: 0 | O22: 0 | P22: 0
A23: DESHABILITADOS | B23: DESHABILITADOS | C23: DESHABILITADOS | D23: DESHABILITADOS | E23: 15 | F23: 0 | G23: PACK 2 UNIDADES PROMO (VIN) | I23: 0 | J23: 0 | K23: 0 | L23: 0 | M23: 0 | N23: 0 | O23: 0 | P23: 0
A24: DESHABILITADOS | B24: DESHABILITADOS | C24: DESHABILITADOS | D24: DESHABILITADOS | E24: 16 | F24: 0 | G24: BANDEJA DE HUEVOS REGALO | I24: 0 | J24: 0 | K24: 0 | L24: 0 | M24: 0 | N24: 0 | O24: 0 | P24: 0
A25: DESHABILITADOS | B25: DESHABILITADOS | C25: DESHABILITADOS | D25: DESHABILITADOS | E25: 18 | F25: 0 | G25: MUEBLE GALLETA | I25: 0 | J25: 0 | K25: 0 | L25: 0 | M25: 0 | N25: 0 | O25: 0 | P25: 0
A26: CONFITES | B26: CHOCOLATES | C26: BOLSAS PROMO | D26: PROMO BOLSAS | E26: 20 | F26: 0 | G26: BOLSAS PROMO | H26: 33 x 40 GRS | I26: 0 | J26: 0 | K26: 0 | L26: 0 | M26: 0 | N26: 0 | O26: 0 | P26: 0
A27: DESHABILITADOS | B27: DESHABILITADOS | C27: DESHABILITADOS | D27: DESHABILITADOS | E27: 21 | F27: 0 | G27: KIT 2 VISIBILIDAD GALLETAS Y CHOCOLATES | H27: 1 | I27: 0 | J27: 0 | K27: 0 | L27: 0 | M27: 0 | N27: 0 | O27: 0 | P27: 0
A28: DESHABILITADOS | B28: DESHABILITADOS | C28: DESHABILITADOS | D28: DESHABILITADOS | E28: 25 | F28: 0 | G28: LAMPARA DE EMERGENCIA | H28: 1 | I28: 0 | J28: 0 | K28: 0 | L28: 0 | M28: 0 | N28: 0 | O28: 0 | P28: 0
A29: DESHABILITADOS | B29: DESHABILITADOS | C29: DESHABILITADOS | D29: DESHABILITADOS | E29: 26 | F29: 0 | G29: COMBO 1 VUELTA A CLASES | H29: 1 | I29: 0 | J29: 0 | K29: 0 | L29: 0 | M29: 0 | N29: 0 | O29: 0 | P29: 0
A30: DESHABILITADOS | B30: DESHABILITADOS | C30: DESHABILITADOS | D30: DESHABILITADOS | E30: 27 | F30: 0 | G30: COMBO 2 VUELTA A CLASES | H30: 1 | I30: 0 | J30: 0 | K30: 0 | L30: 0 | M30: 0 | N30: 0 | O30: 0 | P30: 0
A31: DESHABILITADOS | B31: DESHABILITADOS | C31: DESHABILITADOS | D31: DESHABILITADOS | E31: 28 | F31: 0 | G31: COMBO 3 VUELTA A CLASES | H31: 1 | I31: 0 | J31: 0 | K31: 0 | L31: 0 | M31: 0 | N31: 0 | O31: 0 | P31: 0
A32: DESHABILITADOS | B32: DESHABILITADOS | C32: DESHABILITADOS | D32: DESHABILITADOS | E32: 30 | F32: 0 | G32: HUEVOS + MINI BEBIDA | H32: 2 x 5 GRM | I32: 0 | J32: 0 | K32: 0 | L32: 0 | M32: 0 | N32: 0 | O32: 0 | P32: 0
A33: TRADICIONAL | B33: CAFES | C33: STANDARD | D33: Nescafe Trad | E33: 36 | F33: 0 | G33: NESCAFE TRADICIÓN TARRO | H33: 9 x 6 x 50 GRS | I33: 0 | J33: 0 | K33: 0 | L33: 0 | M33: 0 | N33: 0 | O33: 0 | P33: 0
A34: TRADICIONAL | B34: CAFES | C34: STANDARD | D34: Nescafe Trad | E34: 37 | F34: 0 | G34: NESCAFE TRADICIÓN TARRO | H34: 9 x 6 x 50 GRM | I34: 0 | J34: 0 | K34: 0 | L34: 0 | M34: 0 | N34: 0 | O34: 0 | P34: 0
A35: DESHABILITADOS | B35: DESHABILITADOS | C35: DESHABILITADOS | D35: DESHABILITADOS | E35: 39 | F35: 0 | G35: MCKAY VINO VO | H35: 28 x 155 GRM | I35: 0 | J35: 0 | K35: 0 | L35: 0 | M35: 0 | N35: 0 | O35: 0 | P35: 0
A36: TRADICIONAL | B36: OPPB | C36: NESQUIK | D36: NESQUIK | E36: 40 | F36: 0 | G36: NESQUIK NUTRB Frutilla | H36: 8 x 20 x 15 GRM | I36: 0 | J36: 0 | K36: 0 | L36: 0 | M36: 0 | N36: 0 | O36: 0 | P36: 0
A37: TRADICIONAL | B37: OPPB | C37: NESQUIK | D37: NESQUIK | E37: 41 | F37: 0 | G37: NESQUIK FRUTILLA | H37: 8 x 20 x 15 GRM | I37: 0 | J37: 0 | K37: 0 | L37: 0 | M37: 0 | N37: 0 | O37: 0 | P37: 0
A38: DESHABILITADOS | B38: DESHABILITADOS | C38: DESHABILITADOS | D38: DESHABILITADOS | E38: 43 | F38: 0 | G38: Maq Afeitar + S.Nuss 250 gr | H38: 1 | I38: 0 | J38: 0 | K38: 0 | L38: 0 | M38: 0 | N38: 0 | O38: 0 | P38: 0
A39: DESHABILITADOS | B39: DESHABILITADOS | C39: DESHABILITADOS | D39: DESHABILITADOS | E39: 44 | F39: 0 | G39: Regalo Pack x Galletas | H39: 1 | I39: 0 | J39: 0 | K39: 0 | L39: 0 | M39: 0 | N39: 0 | O39: 0 | P39: 0
A40: TRADICIONAL | B40: CAFES | C40: PACK CAFE | D40: PACK CAFE | E40: 47 | F40: 0 | G40: PACK CAFE 1 | H40: 1 | I40: 0 | J40: 0 | K40: 0 | L40: 0 | M40: 0 | N40: 0 | O40: 0 | P40: 0
A41: DESHABILITADOS | B41: DESHABILITADOS | C41: DESHABILITADOS | D41: DESHABILITADOS | E41: 49 | F41: 0 | G41: PROMO JUGO | I41: 0 | J41: 0 | K41: 0 | L41: 0 | M41: 0 | N41: 0 | O41: 0 | P41: 0
A42: CONFITES | B42: GALLETAS | C42: PACK GALLETAS | D42: PACK GALLETAS | E42: 52 | F42: 0 | G42: PACK TRITON+KUKY+MTORTA | H42: 1 | I42: 0 | J42: 0 | K42: 0 | L42: 0 | M42: 0 | N42: 0 | O42: 0 | P42: 0
A43: TRADICIONAL | B43: CULINARIOS | C43: PACK CULINARIOS | D43: PACK CULINARIOS | E43: 54 | F43: 0 | G43: PACK CULINARIO 1 | H43: 1 | I43: 0 | J43: 0 | K43: 0 | L43: 0 | M43: 0 | N43: 0 | O43: 0 | P43: 0
A44: TRADICIONAL | B44: CULINARIOS | C44: PACK CULINARIOS | D44: PACK CULINARIOS | E44: 55 | F44: 0 | G44: PACK CULINARIO 2 | H44: 1 | I44: 0 | J44: 0 | K44: 0 | L44: 0 | M44: 0 | N44: 0 | O44: 0 | P44: 0
A45: TRADICIONAL | B45: CAFES | C45: PACK CAFE | D45: PACK CAFE | E45: 56 | F45: 0 | G45: PACK CAFE | H45: 1 | I45: 0 | J45: 0 | K45: 0 | L45: 0 | M45: 0 | N45: 0 | O45: 0 | P45: 0
A46: DESHABILITADOS | B46: DESHABILITADOS | C46: DESHABILITADOS | D46: DESHABILITADOS | E46: 58 | F46: 0 | G46: MUEBLE CHOCO ESCALON | H46: 1 | I46: 0 | J46: 0 | K46: 0 | L46: 0 | M46: 0 | N46: 0 | O46: 0 | P46: 0
A47: DESHABILITADOS | B47: DESHABILITADOS | C47: DESHABILITADOS | D47: DESHABILITADOS | E47: 59 | F47: 0 | G47: GANCHERAS PROMOCION | H47: 1 | I47: 0 | J47: 0 | K47: 0 | L47: 0 | M47: 0 | N47: 0 | O47: 0 | P47: 0
A48: TRADICIONAL | B48: CAFES | C48: PACK CAFE | D48: PACK CAFE | E48: 60 | F48: 0 | G48: PACK CAFE CUCHARA | H48: 1 | I48: 0 | J48: 0 | K48: 0 | L48: 0 | M48: 0 | N48: 0 | O48: 0 | P48: 0
A49: TRADICIONAL | B49: CAFES | C49: PACK CAFE | D49: PACK CAFE | E49: 61 | F49: 0 | G49: PACK CAFE AZUCARERO1 | H49: 1 | I49: 0 | J49: 0 | K49: 0 | L49: 0 | M49: 0 | N49: 0 | O49: 0 | P49: 0
A50: TRADICIONAL | B50: CAFES | C50: PACK CAFE | D50: PACK CAFE | E50: 63 | F50: 0 | G50: PACK CAFE VASO ROJO1 | H50: 1 | I50: 0 | J50: 0 | K50: 0 | L50: 0 | M50: 0 | N50: 0 | O50: 0 | P50: 0
A51: TRADICIONAL | B51: CAFES | C51: PACK CAFE | D51: PACK CAFE | E51: 65 | F51: 0 | G51: PACK CAFE TAZON | H51: 1 | I51: 0 | J51: 0 | K51: 0 | L51: 0 | M51: 0 | N51: 0 | O51: 0 | P51: 0
A52: DESHABILITADOS | B52: DESHABILITADOS | C52: DESHABILITADOS | D52: DESHABILITADOS | E52: 67 | F52: 0 | G52: PACK SUPER 8 CHUAAAA | H52: 1 | I52: 0 | J52: 0 | K52: 0 | L52: 0 | M52: 0 | N52: 0 | O52: 0 | P52: 0
A53: DESHABILITADOS | B53: DESHABILITADOS | C53: DESHABILITADOS | D53: DESHABILITADOS | E53: 69 | F53: 0 | G53: PROMO HALLOWEEN 1 | H53: 18 x 250 GRM | I53: 0 | J53: 0 | K53: 0 | L53: 0 | M53: 0 | N53: 0 | O53: 0 | P53: 0
A54: DESHABILITADOS | B54: DESHABILITADOS | C54: DESHABILITADOS | D54: DESHABILITADOS | E54: 70 | F54: 0 | G54: PROMO HALLOWEEN 2 | H54: 12 x 25 x 8,5 GRM | I54: 0 | J54: 0 | K54: 0 | L54: 0 | M54: 0 | N54: 0 | O54: 0 | P54: 0
A55: TRADICIONAL | B55: CAFES | C55: PACK CAFE | D55: PACK CAFE | E55: 71 | F55: 0 | G55: PACK CAFE CUCHARA2 | H55: 1 | I55: 0 | J55: 0 | K55: 0 | L55: 0 | M55: 0 | N55: 0 | O55: 0 | P55: 0
A56: TRADICIONAL | B56: CULINARIOS | C56: AYUDANTES CULINARIOS | D56: BASES P COCINAR | E56: 72 | F56: 0 | G56: PACK CULINARIO | H56: 1 | I56: 0 | J56: 0 | K56: 0 | L56: 0 | M56: 0 | N56: 0 | O56: 0 | P56: 0
A57: DESHABILITADOS | B57: DESHABILITADOS | C57: DESHABILITADOS | D57: DESHABILITADOS | E57: 75 | F57: 0 | G57: S NUSS 140GR PROMO | H57: 22 x 140 GRM | I57: 0 | J57: 0 | K57: 0 | L57: 0 | M57: 0 | N57: 0 | O57: 0 | P57: 0
A58: DESHABILITADOS | B58: DESHABILITADOS | C58: DESHABILITADOS | D58: DESHABILITADOS | E58: 76 | F58: 0 | G58: BONIF ALTEZA | I58: 0 | J58: 0 | K58: 0 | L58: 0 | M58: 0 | N58: 0 | O58: 0 | P58: 0
A59: DESHABILITADOS | B59: DESHABILITADOS | C59: DESHABILITADOS | D59: DESHABILITADOS | E59: 77 | F59: 0 | G59: PROMOCION TRENCITO150GR | H59: 14 x 150 GRM | I59: 0 | J59: 0 | K59: 0 | L59: 0 | M59: 0 | N59: 0 | O59: 0 | P59: 0
A60: TRADICIONAL | B60: CULINARIOS | C60: PACK CULINARIOS | D60: PACK CULINARIOS | E60: 78 | F60: 0 | G60: PACK1 CULINARIOS | H60: 1 | I60: 0 | J60: 0 | K60: 0 | L60: 0 | M60: 0 | N60: 0 | O60: 0 | P60: 0
A61: TRADICIONAL | B61: CULINARIOS | C61: PACK CULINARIOS | D61: PACK CULINARIOS | E61: 79 | F61: 0 | G61: PACK2 CULINARIOS | H61: 1 | I61: 0 | J61: 0 | K61: 0 | L61: 0 | M61: 0 | N61: 0 | O61: 0 | P61: 0
A62: TRADICIONAL | B62: CULINARIOS | C62: PACK CULINARIOS | D62: PACK CULINARIOS | E62: 80 | F62: 0 | G62: PACK CULIN P.AZUCAR | H62: 1 | I62: 0 | J62: 0 | K62: 0 | L62: 0 | M62: 0 | N62: 0 | O62: 0 | P62: 0
A63: TRADICIONAL | B63: CAFES | C63: STANDARD | D63: Nescafe Trad | E63: 81 | F63: 0 | G63: NESCAFE TRAD PRM | H63: 24 x 170 GRS | I63: 0 | J63: 0 | K63: 0 | L63: 0 | M63: 0 | N63: 0 | O63: 0 | P63: 0
A64: TRADICIONAL | B64: CAFES | C64: STANDARD | D64: Nescafe Trad | E64: 82 | F64: 0 | G64: NESCAFE TRAD PRM | H64: 48 x 50 GRS | I64: 0 | J64: 0 | K64: 0 | L64: 0 | M64: 0 | N64: 0 | O64: 0 | P64: 0
A65: TRADICIONAL | B65: CAFES | C65: STANDARD | D65: Nescafe Trad | E65: 85 | F65: 0 | G65: MPOP RELOJ NESCAFE | H65: . | I65: 0 | J65: 0 | K65: 0 | L65: 0 | M65: 0 | N65: 0 | O65: 0 | P65: 0
A66: TRADICIONAL | B66: CULINARIOS | C66: CALDOS | D66: CALDOS ESPECIALIDADES | E66: 87 | F66: 0 | G66: CALDO LONGANIZA | H66: 36 x 24 x 10 GRS | I66: 0 | J66: 0 | K66: 0 | L66: 0 | M66: 0 | N66: 0 | O66: 0 | P66: 0
A67: CONFITES | B67: GALLETAS | C67: IMPULSIVA BANDA | D67: SODA | E67: 89 | F67: 0 | G67: SODA FAM PAZUCAR | I67: 0 | J67: 0 | K67: 0 | L67: 0 | M67: 0 | N67: 0 | O67: 0 | P67: 0
A68: CONFITES | B68: GALLETAS | C68: HOGAR | D68: TRITON | E68: 91 | F68: 0 | G68: GALLETA TRITON BONIF VAINI | H68: 30 x 126 GRS | I68: 0 | J68: 0 | K68: 0 | L68: 0 | M68: 0 | N68: 0 | O68: 0 | P68: 0
A69: CONFITES | B69: GALLETAS | C69: HOGAR | D69: TRITON | E69: 92 | F69: 0 | G69: GALLETA TRITON CHOC BONIF | H69: 30 x 126 GRS | I69: 0 | J69: 0 | K69: 0 | L69: 0 | M69: 0 | N69: 0 | O69: 0 | P69: 0
A70: CONFITES | B70: GALLETAS | C70: HOGAR | D70: TRITON | E70: 93 | F70: 0 | G70: GALLETA TRITON NAR BONIF | H70: 30 x 126 GRS | I70: 0 | J70: 0 | K70: 0 | L70: 0 | M70: 0 | N70: 0 | O70: 0 | P70: 0
A71: CONFITES | B71: CHOCOLATES | C71: NIBBLING | D71: TRENCITO | E71: 97 | F71: 0 | G71: TRENCITO BONIF PAZUCAR | I71: 0 | J71: 0 | K71: 0 | L71: 0 | M71: 0 | N71: 0 | O71: 0 | P71: 0
A72: DESHABILITADOS | B72: DESHABILITADOS | C72: DESHABILITADOS | D72: DESHABILITADOS | E72: 109 | F72: 0 | G72: PARRILLA A CARBÓN DE SOBREMESA | I72: 0 | J72: 0 | K72: 0 | L72: 0 | M72: 0 | N72: 0 | O72: 0 | P72: 0
A73: CONFITES | B73: CHOCOLATES | C73: ESTACIONALES | D73: Figuras Pascua | E73: 115 | F73: 0 | G73: TRENCITO Huevo Choc Bolsa | H73: 12x208gCL | I73: 0 | J73: 0 | K73: 0 | L73: 0 | M73: 0 | N73: 0 | O73: 0 | P73: 0
A74: TRADICIONAL | B74: Lacteos Culinarios | C74: Regular | D74: L.CONDENSADA | E74: 116 | F74: 4 | G74: PK4Leche con397g Nestle + 4Crema leche157g 10% (B2B) | H74: . | I74: 0 | J74: 0 | K74: 0 | L74: 0 | M74: 0 | N74: 0 | O74: 0 | P74: 0
A75: TRADICIONAL | B75: Lacteos Culinarios | C75: Regular | D75: L.CONDENSADA | E75: 116 | F75: 9 | G75: PK 6 LECHE CONDENSADA 397g 20% DCTO | H75: . | I75: 0 | J75: 0 | K75: 0 | L75: 0 | M75: 0 | N75: 0 | O75: 0 | P75: 0
A76: TRADICIONAL | B76: Lacteos Culinarios | C76: Regular | D76: L.CONDENSADA | E76: 116 | F76: 0 | G76: Leche condensada NESTLE Azucarada Lata | H76: 48x397gr | I76: 712 | J76: 24 | K76: 0 | L76: 0 | M76: 0 | N76: 0 | O76: 712 | P76: 24
A77: TRADICIONAL | B77: Lacteos Culinarios | C77: Regular | D77: L.CONDENSADA | E77: 116 | F77: 10 | G77: PK 6 LECHE CONDENSADA 397g 20% DCTO (B2B) | H77: . | I77: 0 | J77: 0 | K77: 0 | L77: 0 | M77: 0 | N77: 0 | O77: 0 | P77: 0
A78: TRADICIONAL | B78: Lacteos Culinarios | C78: Regular | D78: L.CONDENSADA | E78: 116 | F78: 8 | G78: Pk 4 Leches condensadas 397 gr+2 Manjar 800 gr doypack+12% dcto | H78: . | I78: 0 | J78: 0 | K78: 0 | L78: 0 | M78: 0 | N78: 0 | O78: 0 | P78: 0
A79: TRADICIONAL | B79: Lacteos Culinarios | C79: Regular | D79: L.CONDENSADA | E79: 116 | F79: 7 | G79: Pk 4 Leches condensadas 397 gr+2 Manjar 400 gr doypack+12% dcto | H79: . | I79: 0 | J79: 0 | K79: 0 | L79: 0 | M79: 0 | N79: 0 | O79: 0 | P79: 0
A80: TRADICIONAL | B80: Lacteos Culinarios | C80: Regular | D80: L.CONDENSADA | E80: 116 | F80: 17 | G80: PK Cyber 6 Leche condensada 397- 25% (B2B) (DV) | H80: . | I80: 0 | J80: 0 | K80: 0 | L80: 0 | M80: 0 | N80: 0 | O80: 0 | P80: 0
A81: TRADICIONAL | B81: Lacteos Culinarios | C81: Regular | D81: L.CONDENSADA | E81: 116 | F81: 6 | G81: PK 6 LECHE CONDENSADA 397g 10% DCTO | H81: . | I81: 2 | J81: 0 | K81: 0 | L81: 0 | M81: 0 | N81: 0 | O81: 2 | P81: 0
A82: TRADICIONAL | B82: Lacteos Culinarios | C82: Regular | D82: L.CONDENSADA | E82: 116 | F82: 16 | G82: PK 5+1 LECHE CONDENSADA 397g (B2B)(DV) | H82: . | I82: 0 | J82: 0 | K82: 0 | L82: 0 | M82: 0 | N82: 0 | O82: 0 | P82: 0
A83: TRADICIONAL | B83: Lacteos Culinarios | C83: Regular | D83: L.CONDENSADA | E83: 116 | F83: 12 | G83: Leche condensada Nestle 397gr + Stick LCA | H83: . | I83: 0 | J83: 0 | K83: 0 | L83: 0 | M83: 0 | N83: 0 | O83: 0 | P83: 0
A84: TRADICIONAL | B84: Lacteos Culinarios | C84: Regular | D84: L.CONDENSADA | E84: 116 | F84: 5 | G84: PK 6 LECHE CONDENSADA 397g 10% DCTO (B2B) | H84: . | I84: 0 | J84: 0 | K84: 0 | L84: 0 | M84: 0 | N84: 0 | O84: 0 | P84: 0
... A88: TRADICIONAL | B88: Lacteos Culinarios | C88: Regular | D88: L.CONDENSADA | E88: 116 | F88: 1 | G88: PK 4 NESTLE LECHE CONDENSADA 397g + 1 gratis + 20% Dcto | H88: . | I88: 0 | J88: 0 | K88: 0 | L88: 0 | M88: 0 | N88: 0 | O88: 0 | P88: 0
A89: DESHABILITADOS | B89: DESHABILITADOS | C89: DESHABILITADOS | D89: DESHABILITADOS | E89: 117 | F89: 0 | G89: 100 SACHET DE AZUCAR | I89: 0 | J89: 0 | K89: 0 | L89: 0 | M89: 0 | N89: 0 | O89: 0 | P89: 0
A90: TRADICIONAL | B90: CAFES | C90: STANDARD | D90: NESCAFE DECAF TARRO | E90: 118 | F90: 0 | G90: Cafe NESCAFE Decaf frasco | H90: 12x50g N3 CL | I90: 0 | J90: 0 | K90: 0 | L90: 0 | M90: 0 | N90: 0 | O90: 0 | P90: 0
A91: TRADICIONAL | B91: CAFES | C91: STANDARD | D91: NESCAFE DECAF TARRO | E91: 119 | F91: 0 | G91: Cafe NESCAFE Decaf frasco | H91: 12x100g N3 CL | I91: 0 | J91: 0 | K91: 0 | L91: 0 | M91: 0 | N91: 0 | O91: 0 | P91: 0
A92: TRADICIONAL | B92: CAFES | C92: STANDARD | D92: NESCAFE DECAF TARRO | E92: 120 | F92: 0 | G92: Cafe NESCAFE Decaf descafeinado frasco | H92: 12x170g N3 CL | I92: 0 | J92: 0 | K92: 0 | L92: 0 | M92: 0 | N92: 0 | O92: 0 | P92: 0
A93: TRADICIONAL | B93: CAFES | C93: STANDARD | D93: NESCAFE DECAF TARRO | E93: 121 | F93: 0 | G93: Cafe NESCAFE Decaf sobres | H93: 24(20x1.8g) | I93: 0 | J93: 0 | K93: 0 | L93: 0 | M93: 0 | N93: 0 | O93: 0 | P93: 0
A94: CONFITES | B94: CHOCOLATES | C94: ESTACIONALES | D94: Figuras Pascua | E94: 128 | F94: 0 | G94: TRENCITO CHOC BANDEJA HUEVOS | H94: 18X250G N1CL | I94: 0 | J94: 0 | K94: 0 | L94: 0 | M94: 0 | N94: 0 | O94: 0 | P94: 0
A95: TRADICIONAL | B95: Lacteos Culinarios | C95: MANJAR | D95: MANJAR ABL | E95: 129 | F95: 0 | G95: NESTLE EL MANJAR | H95: 48 x 380 GRM | I95: 0 | J95: 0 | K95: 0 | L95: 0 | M95: 0 | N95: 0 | O95: 0 | P95: 0
A96: TRADICIONAL | B96: CULINARIOS | C96: CALDOS | D96: CALDOS ESPECIALIDADES | E96: 130 | F96: 0 | G96: CALDO DE COSTILLA | H96: 6 x 30 x 8 x 11 GRM | I96: 0 | J96: 0 | K96: 0 | L96: 0 | M96: 0 | N96: 0 | O96: 0 | P96: 0
A97: TRADICIONAL | B97: Lacteos Culinarios | C97: Regular | D97: CREMA NESTLE | E97: 131 | F97: 0 | G97: CREMA NESTLE TARRO | H97: 48 x 160 GRM | I97: 0 | J97: 0 | K97: 0 | L97: 0 | M97: 0 | N97: 0 | O97: 0 | P97: 0
A98: TRADICIONAL | B98: Lacteos Culinarios | C98: Regular | D98: CREMA NESTLE | E98: 133 | F98: 2 | G98: PK 4 NESTLE CREMA DE LECHE TARRO 157G + 1 gratis + 20% Dcto | H98: . | I98: 0 | J98: 0 | K98: 0 | L98: 0 | M98: 0 | N98: 0 | O98: 0 | P98: 0
A99: TRADICIONAL | B99: Lacteos Culinarios | C99: Regular | D99: CREMA NESTLE | E99: 133 | F99: 13 | G99: PK 8 crema 157g + 20% DCTO | H99: . | I99: 0 | J99: 0 | K99: 0 | L99: 0 | M99: 0 | N99: 0 | O99: 0 | P99: 0
A100: TRADICIONAL | B100: Lacteos Culinarios | C100: Regular | D100: CREMA NESTLE | E100: 133 | F100: 9 | G100: PK 6 Crema tarro 157g 25%DCTO BlackWeek | H100: . | I100: 0 | J100: 0 | K100: 0 | L100: 0 | M100: 0 | N100: 0 | O100: 0 | P100: 0
A101: TRADICIONAL | B101: Lacteos Culinarios | C101: Regular | D101: CREMA NESTLE | E101: 133 | F101: 7 | G101: PK 8 CREMA DE LECHE TARRO 157g 10% DCTO | H101: . | I101: 0 | J101: 0 | K101: 0 | L101: 0 | M101: 0 | N101: 0 | O101: 0 | P101: 0
... A112: TRADICIONAL | B112: Lacteos Culinarios | C112: Regular | D112: CREMA NESTLE | E112: 138 | F112: 0 | G112: NESTLE CREMA CHAMPIÑONES | H112: 48 x 157 GRM | I112: 0 | J112: 0 | K112: 0 | L112: 0 | M112: 0 | N112: 0 | O112: 0 | P112: 0
A113: CONFITES | B113: GALLETAS | C113: IMPULSIVA BANDA | D113: KUKY MINI | E113: 139 | F113: 0 | G113: PACK GALL MINI 20+3 | I113: 0 | J113: 0 | K113: 0 | L113: 0 | M113: 0 | N113: 0 | O113: 0 | P113: 0
A114: CONFITES | B114: CHOCOLATES | C114: ESTACIONALES | D114: Figuras Pascua | E114: 145 | F114: 0 | G114: CAPRI Huevos Chocolate Manjar | H114: 10x208gCL | I114: 0 | J114: 0 | K114: 0 | L114: 0 | M114: 0 | N114: 0 | O114: 0 | P114: 0
A115: CONFITES | B115: CHOCOLATES | C115: ESTACIONALES | D115: Figuras Pascua | E115: 146 | F115: 0 | G115: TRENCITO Bolsa Huevitos | H115: 12x500g N1 CL | I115: 0 | J115: 0 | K115: 0 | L115: 0 | M115: 0 | N115: 0 | O115: 0 | P115: 0
A116: TRADICIONAL | B116: CAFES | C116: PREMIUMS | D116: NESCAFE F/S | E116: 150 | F116: 0 | G116: NESCAFE FINA SELECCIÓN TARRO | H116: 24 x 170 GRS | I116: 0 | J116: 0 | K116: 0 | L116: 0 | M116: 0 | N116: 0 | O116: 0 | P116: 0
...

Sheet Stock Diario
A1: Articulo | B1: U.V | C1: Fracción
A2: =VALUE(CONCATENATE('Stock InfoDia'!E10,'Stock InfoDia'!F10)) -> 20 | B2: ='Stock InfoDia'!I10 -> 0 | C2: ='Stock InfoDia'!J10 -> 0
A3: =VALUE(CONCATENATE('Stock InfoDia'!E11,'Stock InfoDia'!F11)) -> 30 | B3: ='Stock InfoDia'!I11 -> 0 | C3: ='Stock InfoDia'!J11 -> 0
A4: =VALUE(CONCATENATE('Stock InfoDia'!E12,'Stock InfoDia'!F12)) -> 40 | B4: ='Stock InfoDia'!I12 -> 0 | C4: ='Stock InfoDia'!J12 -> 0
A5: =VALUE(CONCATENATE('Stock InfoDia'!E13,'Stock InfoDia'!F13)) -> 50 | B5: ='Stock InfoDia'!I13 -> 0 | C5: ='Stock InfoDia'!J13 -> 0
A6: =VALUE(CONCATENATE('Stock InfoDia'!E14,'Stock InfoDia'!F14)) -> 60 | B6: ='Stock InfoDia'!I14 -> 0 | C6: ='Stock InfoDia'!J14 -> 0
A7: =VALUE(CONCATENATE('Stock InfoDia'!E15,'Stock InfoDia'!F15)) -> 70 | B7: ='Stock InfoDia'!I15 -> 0 | C7: ='Stock InfoDia'!J15 -> 0
A8: =VALUE(CONCATENATE('Stock InfoDia'!E16,'Stock InfoDia'!F16)) -> 80 | B8: ='Stock InfoDia'!I16 -> 0 | C8: ='Stock InfoDia'!J16 -> 0
A9: =VALUE(CONCATENATE('Stock InfoDia'!E17,'Stock InfoDia'!F17)) -> 90 | B9: ='Stock InfoDia'!I17 -> 0 | C9: ='Stock InfoDia'!J17 -> 0
A10: =VALUE(CONCATENATE('Stock InfoDia'!E18,'Stock InfoDia'!F18)) -> 100 | B10: ='Stock InfoDia'!I18 -> 0 | C10: ='Stock InfoDia'!J18 -> 0
A11: =VALUE(CONCATENATE('Stock InfoDia'!E19,'Stock InfoDia'!F19)) -> 110 | B11: ='Stock InfoDia'!I19 -> 0 | C11: ='Stock InfoDia'!J19 -> 0
A12: =VALUE(CONCATENATE('Stock InfoDia'!E20,'Stock InfoDia'!F20)) -> 120 | B12: ='Stock InfoDia'!I20 -> 0 | C12: ='Stock InfoDia'!J20 -> 0
A13: =VALUE(CONCATENATE('Stock InfoDia'!E21,'Stock InfoDia'!F21)) -> 130 | B13: ='Stock InfoDia'!I21 -> 0 | C13: ='Stock InfoDia'!J21 -> 0
... A4000: =VALUE(CONCATENATE('Stock InfoDia'!E4008,'Stock InfoDia'!F4008)) -> 0 | B4000: ='Stock InfoDia'!I4008 | C4000: ='Stock InfoDia'!J4008

Sheet Cod. Concuna
A1: COD | B1: COD | C1: COD
A2: =Concuna!C2 -> 46694 | B2: =VLOOKUP(A2,Concuna!C2:E398,2,FALSE) -> Posición A01 | C2: =VLOOKUP(A2,Concuna!C2:F398,3,FALSE) -> NATURNES Carne Verduras 4(6x205g) CL
A3: =Concuna!C3 -> 46669 | B3: =VLOOKUP(A3,Concuna!C3:E399,2,FALSE) -> Posición A02 | C3: =VLOOKUP(A3,Concuna!C3:F399,3,FALSE) -> NATURNES Pollo Verduras 4(6x205g) CL
A4: =Concuna!C4 -> 46695 | B4: =VLOOKUP(A4,Concuna!C4:E400,2,FALSE) -> Posición A03 | C4: =VLOOKUP(A4,Concuna!C4:F400,3,FALSE) -> NATURNES AIP Carne Verduras 4(6x205g) CL
A5: =Concuna!C5 -> 46716 | B5: =VLOOKUP(A5,Concuna!C5:E401,2,FALSE) -> Posición A04 | C5: =VLOOKUP(A5,Concuna!C5:F401,3,FALSE) -> NESTLE AIP Pollo Verduras 4(6x205g) CL
A6: =Concuna!C6 -> 46730 | B6: =VLOOKUP(A6,Concuna!C6:E402,2,FALSE) -> Posición A05 | C6: =VLOOKUP(A6,Concuna!C6:F402,3,FALSE) -> Picado NESTLE NATURNES Carbonada12x250g
A7: =Concuna!C7 -> 46740 | B7: =VLOOKUP(A7,Concuna!C7:E403,2,FALSE) -> Posición A06 | C7: =VLOOKUP(A7,Concuna!C7:F403,3,FALSE) -> Picado NESTLE NATURNES Cazuela de Ave 24x250g
A8: =Concuna!C8 -> 46750 | B8: =VLOOKUP(A8,Concuna!C8:E404,2,FALSE) -> Posición A07 | C8: =VLOOKUP(A8,Concuna!C8:F404,3,FALSE) -> Picado NESTLE NATURNES Cazuela de Vacuno24x250g
A9: =Concuna!C9 -> 46760 | B9: =VLOOKUP(A9,Concuna!C9:E405,2,FALSE) -> Posición A08 | C9: =VLOOKUP(A9,Concuna!C9:F405,3,FALSE) -> Picado NESTLE NATURNES Charquican12x250g
A10: =Concuna!C10 -> 5670 | B10: =VLOOKUP(A10,Concuna!C10:E406,2,FALSE) -> Posición A09 | C10: =VLOOKUP(A10,Concuna!C10:F406,3,FALSE) -> Colado NESTLE NATURNES Carne Verdura 8(6x115g)
A11: =Concuna!C11 -> 56420 | B11: =VLOOKUP(A11,Concuna!C11:E407,2,FALSE) -> Posición A10 | C11: =VLOOKUP(A11,Concuna!C11:F407,3,FALSE) -> Colado NESTLE NATURNES Pollo Verduras 8x6x115g
A12: =Concuna!C12 -> 1330 | B12: =VLOOKUP(A12,Concuna!C12:E408,2,FALSE) -> Posición A11 | C12: =VLOOKUP(A12,Concuna!C12:F408,3,FALSE) -> Crema de leche NESTLE Lata48 x 157 GRM
A13: =Concuna!C13 -> 79760 | B13: =VLOOKUP(A13,Concuna!C13:E409,2,FALSE) -> Posición A11 | C13: =VLOOKUP(A13,Concuna!C13:F409,3,FALSE) -> NESTLE Crema de leche tarro 3840x157g
... A326: =Concuna!C326 -> 8410 | B326: =VLOOKUP(A326,Concuna!C326:E722,2,FALSE) -> Posición N05 | C326: =VLOOKUP(A326,Concuna!C326:F722,3,FALSE) -> TRENCITO Galleta Cubierta 40x130g
A328: =Concuna!C327 -> 36720 | B328: =VLOOKUP(A328,Concuna!C327:E723,2,FALSE) -> Posición N06 | C328: =VLOOKUP(A328,Concuna!C327:F723,3,FALSE) -> TRITON GallVainilla Tripack 10(3x116g)CL
A329: =Concuna!C328 -> 81990 | B329: =VLOOKUP(A329,Concuna!C328:E724,2,FALSE) -> Posición N07 | C329: =VLOOKUP(A329,Concuna!C328:F724,3,FALSE) -> Galletas MCKAY Niza24 x 150 GRM
A330: =Concuna!C329 -> 59010 | B330: =VLOOKUP(A330,Concuna!C329:E725,2,FALSE) -> Posición N08 | C330: =VLOOKUP(A330,Concuna!C329:F725,3,FALSE) -> Galleta GRILL Clasica12x140g
A331: =Concuna!C330 -> 36840 | B331: =VLOOKUP(A331,Concuna!C330:E726,2,FALSE) -> Posición N09 | C331: =VLOOKUP(A331,Concuna!C330:F726,3,FALSE) -> TRITON Regular ChocoWhite 30x116g CL
A332: =Concuna!C331 -> 81170 | B332: =VLOOKUP(A332,Concuna!C331:E727,2,FALSE) -> Posición N10 | C332: =VLOOKUP(A332,Concuna!C331:F727,3,FALSE) -> Galleta chip KUKY Chocolate30 x 120 GRM
A333: =Concuna!C332 -> 81160 | B333: =VLOOKUP(A333,Concuna!C332:E728,2,FALSE) -> Posición N11 | C333: =VLOOKUP(A333,Concuna!C332:F728,3,FALSE) -> Galleta chip KUKY Clasica30 x 120 GRM
A334: =Concuna!C333 -> 81160 | B334: =VLOOKUP(A334,Concuna!C333:E729,2,FALSE) -> Posición N11 | C334: =VLOOKUP(A334,Concuna!C333:F729,3,FALSE) -> Galleta chip KUKY Clasica30 x 120 GRM
A335: =Concuna!C334 -> 7910 | B335: =VLOOKUP(A335,Concuna!C334:E730,2,FALSE) -> Posición N11 | C335: =VLOOKUP(A335,Concuna!C334:F730,3,FALSE) -> MCKAY KUKY CLASICA 120g PDQ
A336: =Concuna!C335 -> 36270 | B336: =VLOOKUP(A336,Concuna!C335:E731,2,FALSE) -> Posición N12 | C336: =VLOOKUP(A336,Concuna!C335:F731,3,FALSE) -> TRENCITO ChocoCookies Brownie 40x120g CL
A337: =Concuna!C336 -> 90720 | B337: =VLOOKUP(A337,Concuna!C336:E732,2,FALSE) -> Posición N13 | C337: =VLOOKUP(A337,Concuna!C336:F732,3,FALSE) -> MOROCHA Mini Galleta 24x50g N1 CL
A338: =Concuna!C337 -> 63540 | B338: =VLOOKUP(A338,Concuna!C337:E733,2,FALSE) -> Posición N13 | C338: =VLOOKUP(A338,Concuna!C337:F733,3,FALSE) -> MOROCHA Mini Galleta PDQ
A339: =Concuna!C338 -> 68681 | B339: =VLOOKUP(A339,Concuna!C338:E734,2,FALSE) -> Posición N14 | C339: =VLOOKUP(A339,Concuna!C338:F734,3,FALSE) -> TRITON Reg GallChocolate Medio PDQ 127.6kg CL
... A351: =Concuna!C350 -> 86649 | B351: =VLOOKUP(A351,Concuna!C350:E746,2,FALSE) -> Posición O09 | C351: =VLOOKUP(A351,Concuna!C350:F746,3,FALSE) -> PK 4 SODA180GR+1TRENCITO CHOCOBISCUIT +15%DCTO
A352: =Concuna!C351 -> 357219 | B352: =VLOOKUP(A353,Concuna!C352:E748,2,FALSE) -> Posición O11 | C352: =VLOOKUP(A352,Concuna!C351:F747,3,FALSE) -> PK 2ALTFRUT +2ALTBOCA +1TRENCOATED 15%DCTO
A353: =Concuna!C352 -> 36683 | C353: =VLOOKUP(A353,Concuna!C352:F748,3,FALSE) -> PK ALTEZAS 2HELADO+2BOCADO +1CHOCOVAINILLA+15%DCTO
A354: =Concuna!C353 -> 357218 | B354: =VLOOKUP(A354,Concuna!C353:E749,2,FALSE) -> Posición O12 | C354: =VLOOKUP(A354,Concuna!C353:F749,3,FALSE) -> PK 5 Alteza Frutilla + 1 Gratis (B2B).
A355: =Concuna!C354 -> 370512 | B355: =VLOOKUP(A355,Concuna!C354:E750,2,FALSE) -> Posición O13 | C355: =VLOOKUP(A355,Concuna!C354:F750,3,FALSE) -> PK 5 Alteza Chirimoya + 1 Gratis (B2B) (DV).
A356: =Concuna!C355 -> 88824 | B356: =VLOOKUP(A356,Concuna!C355:E751,2,FALSE) -> Posición O14 | C356: =VLOOKUP(A356,Concuna!C355:F751,3,FALSE) -> PK MinTriVa+MinTriCho+MinMor+MinKu + 19.98% DCTO (B2B)
A357: =Concuna!C356 -> 87331 | B357: =VLOOKUP(A357,Concuna!C356:E752,2,FALSE) -> Posición O15 | C357: =VLOOKUP(A357,Concuna!C356:F752,3,FALSE) -> PK 4 MINI NIZA + 21.20% DCTO (B2B)
A358: =Concuna!C357 -> 87332 | B358: =VLOOKUP(A358,Concuna!C357:E753,2,FALSE) -> Posición O16 | C358: =VLOOKUP(A358,Concuna!C357:F753,3,FALSE) -> PK 4 MINI NIZA + 21.20% DCTO (DV)
A359: =Concuna!C358 -> 7282 | B359: =VLOOKUP(A359,Concuna!C358:E754,2,FALSE) -> Posición O17 | C359: =VLOOKUP(A359,Concuna!C358:F754,3,FALSE) -> PK 4 MINI MANTEQUILLA 21.20% DCTO (B2B)
A360: =Concuna!C359 -> 7283 | B360: =VLOOKUP(A360,Concuna!C359:E755,2,FALSE) -> Posición O18 | C360: =VLOOKUP(A360,Concuna!C359:F755,3,FALSE) -> PK 4 MINI MANTEQUILLA + 21.20% DCTO (DV)
A361: =Concuna!C360 -> 874613 | B361: =VLOOKUP(A361,Concuna!C360:E756,2,FALSE) -> Posición O19 | C361: =VLOOKUP(A361,Concuna!C360:F756,3,FALSE) -> PK 4 MINI VINO + 21.20% DCTO (B2B)
A362: =Concuna!C361 -> 874614 | B362: =VLOOKUP(A362,Concuna!C361:E757,2,FALSE) -> Posición O20 | C362: =VLOOKUP(A362,Concuna!C361:F757,3,FALSE) -> PK 4 MINI VINO 21.20% DCTO (DV)
A363: =Concuna!C362 -> 90711 | B363: =VLOOKUP(A363,Concuna!C362:E758,2,FALSE) -> Posición O21 | C363: =VLOOKUP(A363,Concuna!C362:F758,3,FALSE) -> PK 4 MINI LIMON + 21.20% DCTO (B2B)
A364: =Concuna!C363 -> 90712 | B364: =VLOOKUP(A364,Concuna!C363:E759,2,FALSE) -> Posición O22 | C364: =VLOOKUP(A364,Concuna!C363:F759,3,FALSE) -> PK 4 MINI LIMON + 21.20% DCTO (DV)
A365: =Concuna!C364 -> 72712 | B365: =VLOOKUP(A365,Concuna!C364:E760,2,FALSE) -> Posición O23 | C365: =VLOOKUP(A365,Concuna!C364:F760,3,FALSE) -> PK 4 MINI COCO + 21.20% DCTO (B2B)
... A470: =Concuna!C469 -> a | B470: =VLOOKUP(A470,Concuna!C469:E865,2,FALSE) -> Posición S27 | C470: =VLOOKUP(A470,Concuna!C469:F865,3,FALSE)

Sheet Consulta Stock
A2: CATEGORIA | B2: COD. ARTICULO | C2: DESCRIPCION | D2: MEDIDA | E2: Cod | F2: Descripcion 1 | G2: Categoria1
A3: DESHABILITADOS | B3: 02 - 0 | C3: PROMO AZUCAR ABL | E3: =VALUE(SUBSTITUTE(SUBSTITUTE(B3," ",""),"-","")) -> 20 | F3: =+CONCATENATE(C3," ",D3) -> PROMO AZUCAR ABL | G3: =A3 -> DESHABILITADOS
A4: DESHABILITADOS | B4: 03 - 0 | C4: PROMO FIDEOS | E4: =VALUE(SUBSTITUTE(SUBSTITUTE(B4," ",""),"-","")) -> 30 | F4: =+CONCATENATE(C4," ",D4) -> PROMO FIDEOS | G4: =A4 -> DESHABILITADOS
A5: DESHABILITADOS | B5: 04 - 0 | C5: PROMO AZUCAR | E5: =VALUE(SUBSTITUTE(SUBSTITUTE(B5," ",""),"-","")) -> 40 | F5: =+CONCATENATE(C5," ",D5) -> PROMO AZUCAR | G5: =A5 -> DESHABILITADOS
A6: DESHABILITADOS | B6: 05 - 0 | C6: COMBO 12.000 CFT BACK TO SCHOOL | E6: =VALUE(SUBSTITUTE(SUBSTITUTE(B6," ",""),"-","")) -> 50 | F6: =+CONCATENATE(C6," ",D6) -> COMBO 12.000 CFT BACK TO SCHOOL | G6: =A6 -> DESHABILITADOS
A7: DESHABILITADOS | B7: 06 - 0 | C7: COMBO 17.000 CFT BACK TO SCHOOL | E7: =VALUE(SUBSTITUTE(SUBSTITUTE(B7," ",""),"-","")) -> 60 | F7: =+CONCATENATE(C7," ",D7) -> COMBO 17.000 CFT BACK TO SCHOOL | G7: =A7 -> DESHABILITADOS
A8: DESHABILITADOS | B8: 07 - 0 | C8: COMBO 23.000 CFT BACK TO SCHOOL | E8: =VALUE(SUBSTITUTE(SUBSTITUTE(B8," ",""),"-","")) -> 70 | F8: =+CONCATENATE(C8," ",D8) -> COMBO 23.000 CFT BACK TO SCHOOL | G8: =A8 -> DESHABILITADOS
A9: DESHABILITADOS | B9: 08 - 0 | C9: SET ESCOLAR COLLEGE | E9: =VALUE(SUBSTITUTE(SUBSTITUTE(B9," ",""),"-","")) -> 80 | F9: =+CONCATENATE(C9," ",D9) -> SET ESCOLAR COLLEGE | G9: =A9 -> DESHABILITADOS
A10: DESHABILITADOS | B10: 09 - 0 | C10: SET ESCOLAR JUNIOR | E10: =VALUE(SUBSTITUTE(SUBSTITUTE(B10," ",""),"-","")) -> 90 | F10: =+CONCATENATE(C10," ",D10) -> SET ESCOLAR JUNIOR | G10: =A10 -> DESHABILITADOS
A11: CHOCOLATES | B11: 10 - 0 | C11: BOLSAS PROMO | D11: 28 x 35 GRS | E11: =VALUE(SUBSTITUTE(SUBSTITUTE(B11," ",""),"-","")) -> 100 | F11: =+CONCATENATE(C11," ",D11) -> BOLSAS PROMO 28 x 35 GRS | G11: =A11 -> CHOCOLATES
A12: CULINARIOS | B12: 11 - 0 | C12: SET DE CUBIERTOS | E12: =VALUE(SUBSTITUTE(SUBSTITUTE(B12," ",""),"-","")) -> 110 | F12: =+CONCATENATE(C12," ",D12) -> SET DE CUBIERTOS | G12: =A12 -> CULINARIOS
A13: CULINARIOS | B13: 12 - 0 | C13: Regalo Promocional Maggi | E13: =VALUE(SUBSTITUTE(SUBSTITUTE(B13," ",""),"-","")) -> 120 | F13: =+CONCATENATE(C13," ",D13) -> Regalo Promocional Maggi | G13: =A13 -> CULINARIOS
A14: CAFES | B14: 13 - 0 | C14: EXHIBIDOR NESCAFE | D14: 1 | E14: =VALUE(SUBSTITUTE(SUBSTITUTE(B14," ",""),"-","")) -> 130 | F14: =+CONCATENATE(C14," ",D14) -> EXHIBIDOR NESCAFE 1 | G14: =A14 -> CAFES
A15: CULINARIOS | B15: 14 - 0 | C15: DISPENSADOR MAGGI | D15: 1 | E15: =VALUE(SUBSTITUTE(SUBSTITUTE(B15," ",""),"-","")) -> 140 | F15: =+CONCATENATE(C15," ",D15) -> DISPENSADOR MAGGI 1 | G15: =A15 -> CULINARIOS
A16: DESHABILITADOS | B16: 15 - 0 | C16: PACK 2 UNIDADES PROMO (VIN) | E16: =VALUE(SUBSTITUTE(SUBSTITUTE(B16," ",""),"-","")) -> 150 | F16: =+CONCATENATE(C16," ",D16) -> PACK 2 UNIDADES PROMO (VIN) | G16: =A16 -> DESHABILITADOS
A17: DESHABILITADOS | B17: 16 - 0 | C17: BANDEJA DE HUEVOS REGALO | E17: =VALUE(SUBSTITUTE(SUBSTITUTE(B17," ",""),"-","")) -> 160 | F17: =+CONCATENATE(C17," ",D17) -> BANDEJA DE HUEVOS REGALO | G17: =A17 -> DESHABILITADOS
A18: DESHABILITADOS | B18: 18 - 0 | C18: MUEBLE GALLETA | E18: =VALUE(SUBSTITUTE(SUBSTITUTE(B18," ",""),"-","")) -> 180 | F18: =+CONCATENATE(C18," ",D18) -> MUEBLE GALLETA | G18: =A18 -> DESHABILITADOS
A19: CHOCOLATES | B19: 20 - 0 | C19: BOLSAS PROMO | D19: 33 x 40 GRS | E19: =VALUE(SUBSTITUTE(SUBSTITUTE(B19," ",""),"-","")) -> 200 | F19: =+CONCATENATE(C19," ",D19) -> BOLSAS PROMO 33 x 40 GRS | G19: =A19 -> CHOCOLATES
A20: DESHABILITADOS | B20: 21 - 0 | C20: KIT 2 VISIBILIDAD GALLETAS Y CHOCOLATES | D20: 1 | E20: =VALUE(SUBSTITUTE(SUBSTITUTE(B20," ",""),"-","")) -> 210 | F20: =+CONCATENATE(C20," ",D20) -> KIT 2 VISIBILIDAD GALLETAS Y CHOCOLATES 1 | G20: =A20 -> DESHABILITADOS
A21: DESHABILITADOS | B21: 25 - 0 | C21: LAMPARA DE EMERGENCIA | D21: 1 | E21: =VALUE(SUBSTITUTE(SUBSTITUTE(B21," ",""),"-","")) -> 250 | F21: =+CONCATENATE(C21," ",D21) -> LAMPARA DE EMERGENCIA 1 | G21: =A21 -> DESHABILITADOS
A22: DESHABILITADOS | B22: 26 - 0 | C22: COMBO 1 VUELTA A CLASES | D22: 1 | E22: =VALUE(SUBSTITUTE(SUBSTITUTE(B22," ",""),"-","")) -> 260 | F22: =+CONCATENATE(C22," ",D22) -> COMBO 1 VUELTA A CLASES 1 | G22: =A22 -> DESHABILITADOS
A23: DESHABILITADOS | B23: 27 - 0 | C23: COMBO 2 VUELTA A CLASES | D23: 1 | E23: =VALUE(SUBSTITUTE(SUBSTITUTE(B23," ",""),"-","")) -> 270 | F23: =+CONCATENATE(C23," ",D23) -> COMBO 2 VUELTA A CLASES 1 | G23: =A23 -> DESHABILITADOS
A24: DESHABILITADOS | B24: 28 - 0 | C24: COMBO 3 VUELTA A CLASES | D24: 1 | E24: =VALUE(SUBSTITUTE(SUBSTITUTE(B24," ",""),"-","")) -> 280 | F24: =+CONCATENATE(C24," ",D24) -> COMBO 3 VUELTA A CLASES 1 | G24: =A24 -> DESHABILITADOS
A25: DESHABILITADOS | B25: 30 - 0 | C25: HUEVOS + MINI BEBIDA | D25: 2 x 5 GRM | E25: =VALUE(SUBSTITUTE(SUBSTITUTE(B25," ",""),"-","")) -> 300 | F25: =+CONCATENATE(C25," ",D25) -> HUEVOS + MINI BEBIDA 2 x 5 GRM | G25: =A25 -> DESHABILITADOS
A26: CAFES | B26: 36 - 0 | C26: NESCAFE TRADICIÓN TARRO | D26: 9 x 6 x 50 GRS | E26: =VALUE(SUBSTITUTE(SUBSTITUTE(B26," ",""),"-","")) -> 360 | F26: =+CONCATENATE(C26," ",D26) -> NESCAFE TRADICIÓN TARRO 9 x 6 x 50 GRS | G26: =A26 -> CAFES
A27: CAFES | B27: 37 - 0 | C27: NESCAFE TRADICIÓN TARRO | D27: 9 x 6 x 50 GRM | E27: =VALUE(SUBSTITUTE(SUBSTITUTE(B27," ",""),"-","")) -> 370 | F27: =+CONCATENATE(C27," ",D27) -> NESCAFE TRADICIÓN TARRO 9 x 6 x 50 GRM | G27: =A27 -> CAFES
A28: DESHABILITADOS | B28: 39 - 0 | C28: MCKAY VINO VO | D28: 28 x 155 GRM | E28: =VALUE(SUBSTITUTE(SUBSTITUTE(B28," ",""),"-","")) -> 390 | F28: =+CONCATENATE(C28," ",D28) -> MCKAY VINO VO 28 x 155 GRM | G28: =A28 -> DESHABILITADOS
A29: OPPB | B29: 40 - 0 | C29: NESQUIK NUTRB Frutilla | D29: 8 x 20 x 15 GRM | E29: =VALUE(SUBSTITUTE(SUBSTITUTE(B29," ",""),"-","")) -> 400 | F29: =+CONCATENATE(C29," ",D29) -> NESQUIK NUTRB Frutilla 8 x 20 x 15 GRM | G29: =A29 -> OPPB
A30: OPPB | B30: 41 - 0 | C30: NESQUIK FRUTILLA | D30: 8 x 20 x 15 GRM | E30: =VALUE(SUBSTITUTE(SUBSTITUTE(B30," ",""),"-","")) -> 410 | F30: =+CONCATENATE(C30," ",D30) -> NESQUIK FRUTILLA 8 x 20 x 15 GRM | G30: =A30 -> OPPB
A31: DESHABILITADOS | B31: 43 - 0 | C31: Maq Afeitar + S.Nuss 250 gr | D31: 1 | E31: =VALUE(SUBSTITUTE(SUBSTITUTE(B31," ",""),"-","")) -> 430 | F31: =+CONCATENATE(C31," ",D31) -> Maq Afeitar + S.Nuss 250 gr 1 | G31: =A31 -> DESHABILITADOS
A32: DESHABILITADOS | B32: 44 - 0 | C32: Regalo Pack x Galletas | D32: 1 | E32: =VALUE(SUBSTITUTE(SUBSTITUTE(B32," ",""),"-","")) -> 440 | F32: =+CONCATENATE(C32," ",D32) -> Regalo Pack x Galletas 1 | G32: =A32 -> DESHABILITADOS
A33: CAFES | B33: 47 - 0 | C33: PACK CAFE 1 | D33: 1 | E33: =VALUE(SUBSTITUTE(SUBSTITUTE(B33," ",""),"-","")) -> 470 | F33: =+CONCATENATE(C33," ",D33) -> PACK CAFE 1 1 | G33: =A33 -> CAFES
A34: DESHABILITADOS | B34: 49 - 0 | C34: PROMO JUGO | E34: =VALUE(SUBSTITUTE(SUBSTITUTE(B34," ",""),"-","")) -> 490 | F34: =+CONCATENATE(C34," ",D34) -> PROMO JUGO | G34: =A34 -> DESHABILITADOS
A35: GALLETAS | B35: 52 - 0 | C35: PACK TRITON+KUKY+MTORTA | D35: 1 | E35: =VALUE(SUBSTITUTE(SUBSTITUTE(B35," ",""),"-","")) -> 520 | F35: =+CONCATENATE(C35," ",D35) -> PACK TRITON+KUKY+MTORTA 1 | G35: =A35 -> GALLETAS
A36: CULINARIOS | B36: 54 - 0 | C36: PACK CULINARIO 1 | D36: 1 | E36: =VALUE(SUBSTITUTE(SUBSTITUTE(B36," ",""),"-","")) -> 540 | F36: =+CONCATENATE(C36," ",D36) -> PACK CULINARIO 1 1 | G36: =A36 -> CULINARIOS
A37: CULINARIOS | B37: 55 - 0 | C37: PACK CULINARIO 2 | D37: 1 | E37: =VALUE(SUBSTITUTE(SUBSTITUTE(B37," ",""),"-","")) -> 550 | F37: =+CONCATENATE(C37," ",D37) -> PACK CULINARIO 2 1 | G37: =A37 -> CULINARIOS
A38: CAFES | B38: 56 - 0 | C38: PACK CAFE | D38: 1 | E38: =VALUE(SUBSTITUTE(SUBSTITUTE(B38," ",""),"-","")) -> 560 | F38: =+CONCATENATE(C38," ",D38) -> PACK CAFE 1 | G38: =A38 -> CAFES
A39: DESHABILITADOS | B39: 58 - 0 | C39: MUEBLE CHOCO ESCALON | D39: 1 | E39: =VALUE(SUBSTITUTE(SUBSTITUTE(B39," ",""),"-","")) -> 580 | F39: =+CONCATENATE(C39," ",D39) -> MUEBLE CHOCO ESCALON 1 | G39: =A39 -> DESHABILITADOS
A40: DESHABILITADOS | B40: 59 - 0 | C40: GANCHERAS PROMOCION | D40: 1 | E40: =VALUE(SUBSTITUTE(SUBSTITUTE(B40," ",""),"-","")) -> 590 | F40: =+CONCATENATE(C40," ",D40) -> GANCHERAS PROMOCION 1 | G40: =A40 -> DESHABILITADOS
A41: CAFES | B41: 60 - 0 | C41: PACK CAFE CUCHARA | D41: 1 | E41: =VALUE(SUBSTITUTE(SUBSTITUTE(B41," ",""),"-","")) -> 600 | F41: =+CONCATENATE(C41," ",D41) -> PACK CAFE CUCHARA 1 | G41: =A41 -> CAFES
A42: CAFES | B42: 61 - 0 | C42: PACK CAFE AZUCARERO1 | D42: 1 | E42: =VALUE(SUBSTITUTE(SUBSTITUTE(B42," ",""),"-","")) -> 610 | F42: =+CONCATENATE(C42," ",D42) -> PACK CAFE AZUCARERO1 1 | G42: =A42 -> CAFES
A43: CAFES | B43: 63 - 0 | C43: PACK CAFE VASO ROJO1 | D43: 1 | E43: =VALUE(SUBSTITUTE(SUBSTITUTE(B43," ",""),"-","")) -> 630 | F43: =+CONCATENATE(C43," ",D43) -> PACK CAFE VASO ROJO1 1 | G43: =A43 -> CAFES
A44: CAFES | B44: 65 - 0 | C44: PACK CAFE TAZON | D44: 1 | E44: =VALUE(SUBSTITUTE(SUBSTITUTE(B44," ",""),"-","")) -> 650 | F44: =+CONCATENATE(C44," ",D44) -> PACK CAFE TAZON 1 | G44: =A44 -> CAFES
A45: DESHABILITADOS | B45: 67 - 0 | C45: PACK SUPER 8 CHUAAAA | D45: 1 | E45: =VALUE(SUBSTITUTE(SUBSTITUTE(B45," ",""),"-","")) -> 670 | F45: =+CONCATENATE(C45," ",D45) -> PACK SUPER 8 CHUAAAA 1 | G45: =A45 -> DESHABILITADOS
A46: DESHABILITADOS | B46: 69 - 0 | C46: PROMO HALLOWEEN 1 | D46: 18 x 250 GRM | E46: =VALUE(SUBSTITUTE(SUBSTITUTE(B46," ",""),"-","")) -> 690 | F46: =+CONCATENATE(C46," ",D46) -> PROMO HALLOWEEN 1 18 x 250 GRM | G46: =A46 -> DESHABILITADOS
A47: DESHABILITADOS | B47: 70 - 0 | C47: PROMO HALLOWEEN 2 | D47: 12 x 25 x 8,5 GRM | E47: =VALUE(SUBSTITUTE(SUBSTITUTE(B47," ",""),"-","")) -> 700 | F47: =+CONCATENATE(C47," ",D47) -> PROMO HALLOWEEN 2 12 x 25 x 8,5 GRM | G47: =A47 -> DESHABILITADOS
A48: CAFES | B48: 71 - 0 | C48: PACK CAFE CUCHARA2 | D48: 1 | E48: =VALUE(SUBSTITUTE(SUBSTITUTE(B48," ",""),"-","")) -> 710 | F48: =+CONCATENATE(C48," ",D48) -> PACK CAFE CUCHARA2 1 | G48: =A48 -> CAFES
A49: CULINARIOS | B49: 72 - 0 | C49: PACK CULINARIO | D49: 1 | E49: =VALUE(SUBSTITUTE(SUBSTITUTE(B49," ",""),"-","")) -> 720 | F49: =+CONCATENATE(C49," ",D49) -> PACK CULINARIO 1 | G49: =A49 -> CULINARIOS
A50: DESHABILITADOS | B50: 75 - 0 | C50: S NUSS 140GR PROMO | D50: 22 x 140 GRM | E50: =VALUE(SUBSTITUTE(SUBSTITUTE(B50," ",""),"-","")) -> 750 | F50: =+CONCATENATE(C50," ",D50) -> S NUSS 140GR PROMO 22 x 140 GRM | G50: =A50 -> DESHABILITADOS
A51: DESHABILITADOS | B51: 76 - 0 | C51: BONIF ALTEZA | E51: =VALUE(SUBSTITUTE(SUBSTITUTE(B51," ",""),"-","")) -> 760 | F51: =+CONCATENATE(C51," ",D51) -> BONIF ALTEZA | G51: =A51 -> DESHABILITADOS
A52: DESHABILITADOS | B52: 77 - 0 | C52: PROMOCION TRENCITO150GR | D52: 14 x 150 GRM | E52: =VALUE(SUBSTITUTE(SUBSTITUTE(B52," ",""),"-","")) -> 770 | F52: =+CONCATENATE(C52," ",D52) -> PROMOCION TRENCITO150GR 14 x 150 GRM | G52: =A52 -> DESHABILITADOS
A53: CULINARIOS | B53: 78 - 0 | C53: PACK1 CULINARIOS | D53: 1 | E53: =VALUE(SUBSTITUTE(SUBSTITUTE(B53," ",""),"-","")) -> 780 | F53: =+CONCATENATE(C53," ",D53) -> PACK1 CULINARIOS 1 | G53: =A53 -> CULINARIOS
A54: CULINARIOS | B54: 79 - 0 | C54: PACK2 CULINARIOS | D54: 1 | E54: =VALUE(SUBSTITUTE(SUBSTITUTE(B54," ",""),"-","")) -> 790 | F54: =+CONCATENATE(C54," ",D54) -> PACK2 CULINARIOS 1 | G54: =A54 -> CULINARIOS
A55: CULINARIOS | B55: 80 - 0 | C55: PACK CULIN P.AZUCAR | D55: 1 | E55: =VALUE(SUBSTITUTE(SUBSTITUTE(B55," ",""),"-","")) -> 800 | F55: =+CONCATENATE(C55," ",D55) -> PACK CULIN P.AZUCAR 1 | G55: =A55 -> CULINARIOS
A56: CAFES | B56: 81 - 0 | C56: NESCAFE TRAD PRM | D56: 24 x 170 GRS | E56: =VALUE(SUBSTITUTE(SUBSTITUTE(B56," ",""),"-","")) -> 810 | F56: =+CONCATENATE(C56," ",D56) -> NESCAFE TRAD PRM 24 x 170 GRS | G56: =A56 -> CAFES
A57: CAFES | B57: 82 - 0 | C57: NESCAFE TRAD PRM | D57: 48 x 50 GRS | E57: =VALUE(SUBSTITUTE(SUBSTITUTE(B57," ",""),"-","")) -> 820 | F57: =+CONCATENATE(C57," ",D57) -> NESCAFE TRAD PRM 48 x 50 GRS | G57: =A57 -> CAFES
A58: CAFES | B58: 85 - 0 | C58: MPOP RELOJ NESCAFE | D58: . | E58: =VALUE(SUBSTITUTE(SUBSTITUTE(B58," ",""),"-","")) -> 850 | F58: =+CONCATENATE(C58," ",D58) -> MPOP RELOJ NESCAFE . | G58: =A58 -> CAFES
A59: CULINARIOS | B59: 87 - 0 | C59: CALDO LONGANIZA | D59: 36 x 24 x 10 GRS | E59: =VALUE(SUBSTITUTE(SUBSTITUTE(B59," ",""),"-","")) -> 870 | F59: =+CONCATENATE(C59," ",D59) -> CALDO LONGANIZA 36 x 24 x 10 GRS | G59: =A59 -> CULINARIOS
A60: GALLETAS | B60: 89 - 0 | C60: SODA FAM PAZUCAR | E60: =VALUE(SUBSTITUTE(SUBSTITUTE(B60," ",""),"-","")) -> 890 | F60: =+CONCATENATE(C60," ",D60) -> SODA FAM PAZUCAR | G60: =A60 -> GALLETAS
A61: GALLETAS | B61: 91 - 0 | C61: GALLETA TRITON BONIF VAINI | D61: 30 x 126 GRS | E61: =VALUE(SUBSTITUTE(SUBSTITUTE(B61," ",""),"-","")) -> 910 | F61: =+CONCATENATE(C61," ",D61) -> GALLETA TRITON BONIF VAINI 30 x 126 GRS | G61: =A61 -> GALLETAS
A62: GALLETAS | B62: 92 - 0 | C62: GALLETA TRITON CHOC BONIF | D62: 30 x 126 GRS | E62: =VALUE(SUBSTITUTE(SUBSTITUTE(B62," ",""),"-","")) -> 920 | F62: =+CONCATENATE(C62," ",D62) -> GALLETA TRITON CHOC BONIF 30 x 126 GRS | G62: =A62 -> GALLETAS
A63: GALLETAS | B63: 93 - 0 | C63: GALLETA TRITON NAR BONIF | D63: 30 x 126 GRS | E63: =VALUE(SUBSTITUTE(SUBSTITUTE(B63," ",""),"-","")) -> 930 | F63: =+CONCATENATE(C63," ",D63) -> GALLETA TRITON NAR BONIF 30 x 126 GRS | G63: =A63 -> GALLETAS
A64: CHOCOLATES | B64: 97 - 0 | C64: TRENCITO BONIF PAZUCAR | E64: =VALUE(SUBSTITUTE(SUBSTITUTE(B64," ",""),"-","")) -> 970 | F64: =+CONCATENATE(C64," ",D64) -> TRENCITO BONIF PAZUCAR | G64: =A64 -> CHOCOLATES
A65: DESHABILITADOS | B65: 109 - 0 | C65: PARRILLA A CARBÓN DE SOBREMESA | E65: =VALUE(SUBSTITUTE(SUBSTITUTE(B65," ",""),"-","")) -> 1090 | F65: =+CONCATENATE(C65," ",D65) -> PARRILLA A CARBÓN DE SOBREMESA | G65: =A65 -> DESHABILITADOS
A66: Lacteos Culinarios | B66: 113 - 15 | C66: PK 4 CREMAS NESTLE 157 GR 15% DESCUENTO | D66: . | E66: =VALUE(SUBSTITUTE(SUBSTITUTE(B66," ",""),"-","")) -> 11315 | F66: =+CONCATENATE(C66," ",D66) -> PK 4 CREMAS NESTLE 157 GR 15% DESCUENTO . | G66: =A66 -> Lacteos Culinarios
A67: CHOCOLATES | B67: 115 - 0 | C67: TRENCITO Huevo Choc Bolsa | D67: 12x208gCL | E67: =VALUE(SUBSTITUTE(SUBSTITUTE(B67," ",""),"-","")) -> 1150 | F67: =+CONCATENATE(C67," ",D67) -> TRENCITO Huevo Choc Bolsa 12x208gCL | G67: =A67 -> CHOCOLATES
A68: Lacteos Culinarios | B68: 116 - 0 | C68: Leche condensada NESTLE Azucarada Lata | D68: 48x397gr | E68: =VALUE(SUBSTITUTE(SUBSTITUTE(B68," ",""),"-","")) -> 1160 | F68: =+CONCATENATE(C68," ",D68) -> Leche condensada NESTLE Azucarada Lata 48x397gr | G68: =A68 -> Lacteos Culinarios
A69: Lacteos Culinarios | B69: 116 - 1 | C69: PK 4 NESTLE LECHE CONDENSADA 397g + 1 gratis + 20% Dcto | D69: . | E69: =VALUE(SUBSTITUTE(SUBSTITUTE(B69," ",""),"-","")) -> 1161 | F69: =+CONCATENATE(C69," ",D69) -> PK 4 NESTLE LECHE CONDENSADA 397g + 1 gratis + 20% Dcto . | G69: =A69 -> Lacteos Culinarios
A70: Lacteos Culinarios | B70: 116 - 2 | C70: PK 4 NESTLE LECHE CONDENSADA 397g + 1 gratis + 20% Dcto (B2B) | D70: . | E70: =VALUE(SUBSTITUTE(SUBSTITUTE(B70," ",""),"-","")) -> 1162 | F70: =+CONCATENATE(C70," ",D70) -> PK 4 NESTLE LECHE CONDENSADA 397g + 1 gratis + 20% Dcto (B2B) . | G70: =A70 -> Lacteos Culinarios
A71: Lacteos Culinarios | B71: 116 - 3 | C71: PK 4 Leche con397g Nestle + 4 Crema leche157g 10% | D71: . | E71: =VALUE(SUBSTITUTE(SUBSTITUTE(B71," ",""),"-","")) -> 1163 | F71: =+CONCATENATE(C71," ",D71) -> PK 4 Leche con397g Nestle + 4 Crema leche157g 10% . | G71: =A71 -> Lacteos Culinarios
A72: Lacteos Culinarios | B72: 116 - 4 | C72: PK4Leche con397g Nestle + 4Crema leche157g 10% (B2B) | D72: . | E72: =VALUE(SUBSTITUTE(SUBSTITUTE(B72," ",""),"-","")) -> 1164 | F72: =+CONCATENATE(C72," ",D72) -> PK4Leche con397g Nestle + 4Crema leche157g 10% (B2B) . | G72: =A72 -> Lacteos Culinarios
A73: Lacteos Culinarios | B73: 116 - 5 | C73: PK 6 LECHE CONDENSADA 397g 10% DCTO (B2B) | D73: . | E73: =VALUE(SUBSTITUTE(SUBSTITUTE(B73," ",""),"-","")) -> 1165 | F73: =+CONCATENATE(C73," ",D73) -> PK 6 LECHE CONDENSADA 397g 10% DCTO (B2B) . | G73: =A73 -> Lacteos Culinarios
A74: Lacteos Culinarios | B74: 116 - 6 | C74: PK 6 LECHE CONDENSADA 397g 10% DCTO | D74: . | E74: =VALUE(SUBSTITUTE(SUBSTITUTE(B74," ",""),"-","")) -> 1166 | F74: =+CONCATENATE(C74," ",D74) -> PK 6 LECHE CONDENSADA 397g 10% DCTO . | G74: =A74 -> Lacteos Culinarios
A75: Lacteos Culinarios | B75: 116 - 7 | C75: Pk 4 Leches condensadas 397 gr+2 Manjar 400 gr doypack+12% dcto | D75: . | E75: =VALUE(SUBSTITUTE(SUBSTITUTE(B75," ",""),"-","")) -> 1167 | F75: =+CONCATENATE(C75," ",D75) -> Pk 4 Leches condensadas 397 gr+2 Manjar 400 gr doypack+12% dcto . | G75: =A75 -> Lacteos Culinarios
A76: Lacteos Culinarios | B76: 116 - 8 | C76: Pk 4 Leches condensadas 397 gr+2 Manjar 800 gr doypack+12% dcto | D76: . | E76: =VALUE(SUBSTITUTE(SUBSTITUTE(B76," ",""),"-","")) -> 1168 | F76: =+CONCATENATE(C76," ",D76) -> Pk 4 Leches condensadas 397 gr+2 Manjar 800 gr doypack+12% dcto . | G76: =A76 -> Lacteos Culinarios
A77: Lacteos Culinarios | B77: 116 - 9 | C77: PK 6 LECHE CONDENSADA 397g 20% DCTO | D77: . | E77: =VALUE(SUBSTITUTE(SUBSTITUTE(B77," ",""),"-","")) -> 1169 | F77: =+CONCATENATE(C77," ",D77) -> PK 6 LECHE CONDENSADA 397g 20% DCTO . | G77: =A77 -> Lacteos Culinarios
... A87: Lacteos Culinarios | B87: 116 - 25 | C87: PK 3 LC NESTLE 397G + 1 LC NESTLE 265G + 15% DCTO | D87: . | E87: =VALUE(SUBSTITUTE(SUBSTITUTE(B87," ",""),"-","")) -> 11625 | F87: =+CONCATENATE(C87," ",D87) -> PK 3 LC NESTLE 397G + 1 LC NESTLE 265G + 15% DCTO . | G87: =A87 -> Lacteos Culinarios
A88: DESHABILITADOS | B88: 117 - 0 | C88: 100 SACHET DE AZUCAR | E88: =VALUE(SUBSTITUTE(SUBSTITUTE(B88," ",""),"-","")) -> 1170 | F88: =+CONCATENATE(C88," ",D88) -> 100 SACHET DE AZUCAR | G88: =A88 -> DESHABILITADOS
A89: CAFES | B89: 118 - 0 | C89: Cafe NESCAFE Decaf frasco | D89: 12x50g N3 CL | E89: =VALUE(SUBSTITUTE(SUBSTITUTE(B89," ",""),"-","")) -> 1180 | F89: =+CONCATENATE(C89," ",D89) -> Cafe NESCAFE Decaf frasco 12x50g N3 CL | G89: =A89 -> CAFES
A90: CAFES | B90: 119 - 0 | C90: Cafe NESCAFE Decaf frasco | D90: 12x100g N3 CL | E90: =VALUE(SUBSTITUTE(SUBSTITUTE(B90," ",""),"-","")) -> 1190 | F90: =+CONCATENATE(C90," ",D90) -> Cafe NESCAFE Decaf frasco 12x100g N3 CL | G90: =A90 -> CAFES
A91: CAFES | B91: 120 - 0 | C91: Cafe NESCAFE Decaf descafeinado frasco | D91: 12x170g N3 CL | E91: =VALUE(SUBSTITUTE(SUBSTITUTE(B91," ",""),"-","")) -> 1200 | F91: =+CONCATENATE(C91," ",D91) -> Cafe NESCAFE Decaf descafeinado frasco 12x170g N3 CL | G91: =A91 -> CAFES
A92: CAFES | B92: 121 - 0 | C92: Cafe NESCAFE Decaf sobres | D92: 24(20x1.8g) | E92: =VALUE(SUBSTITUTE(SUBSTITUTE(B92," ",""),"-","")) -> 1210 | F92: =+CONCATENATE(C92," ",D92) -> Cafe NESCAFE Decaf sobres 24(20x1.8g) | G92: =A92 -> CAFES
A93: CHOCOLATES | B93: 128 - 0 | C93: TRENCITO CHOC BANDEJA HUEVOS | D93: 18X250G N1CL | E93: =VALUE(SUBSTITUTE(SUBSTITUTE(B93," ",""),"-","")) -> 1280 | F93: =+CONCATENATE(C93," ",D93) -> TRENCITO CHOC BANDEJA HUEVOS 18X250G N1CL | G93: =A93 -> CHOCOLATES
A94: Lacteos Culinarios | B94: 129 - 0 | C94: NESTLE EL MANJAR | D94: 48 x 380 GRM | E94: =VALUE(SUBSTITUTE(SUBSTITUTE(B94," ",""),"-","")) -> 1290 | F94: =+CONCATENATE(C94," ",D94) -> NESTLE EL MANJAR 48 x 380 GRM | G94: =A94 -> Lacteos Culinarios
A95: CULINARIOS | B95: 130 - 0 | C95: CALDO DE COSTILLA | D95: 6 x 30 x 8 x 11 GRM | E95: =VALUE(SUBSTITUTE(SUBSTITUTE(B95," ",""),"-","")) -> 1300 | F95: =+CONCATENATE(C95," ",D95) -> CALDO DE COSTILLA 6 x 30 x 8 x 11 GRM | G95: =A95 -> CULINARIOS
A96: Lacteos Culinarios | B96: 131 - 0 | C96: CREMA NESTLE TARRO | D96: 48 x 160 GRM | E96: =VALUE(SUBSTITUTE(SUBSTITUTE(B96," ",""),"-","")) -> 1310 | F96: =+CONCATENATE(C96," ",D96) -> CREMA NESTLE TARRO 48 x 160 GRM | G96: =A96 -> Lacteos Culinarios
A97: Lacteos Culinarios | B97: 133 - 0 | C97: Crema de leche NESTLE Lata | D97: 48x157g | E97: =VALUE(SUBSTITUTE(SUBSTITUTE(B97," ",""),"-","")) -> 1330 | F97: =+CONCATENATE(C97," ",D97) -> Crema de leche NESTLE Lata 48x157g | G97: =A97 -> Lacteos Culinarios
A98: Lacteos Culinarios | B98: 133 - 2 | C98: PK 4 NESTLE CREMA DE LECHE TARRO 157G + 1 gratis + 20% Dcto | D98: . | E98: =VALUE(SUBSTITUTE(SUBSTITUTE(B98," ",""),"-","")) -> 1332 | F98: =+CONCATENATE(C98," ",D98) -> PK 4 NESTLE CREMA DE LECHE TARRO 157G + 1 gratis + 20% Dcto . | G98: =A98 -> Lacteos Culinarios
A99: Lacteos Culinarios | B99: 133 - 3 | C99: PK 8 CREMA DE LECHE TARRO 157g 15% DCTO (B2B) | D99: . | E99: =VALUE(SUBSTITUTE(SUBSTITUTE(B99," ",""),"-","")) -> 1333 | F99: =+CONCATENATE(C99," ",D99) -> PK 8 CREMA DE LECHE TARRO 157g 15% DCTO (B2B) . | G99: =A99 -> Lacteos Culinarios
A100: Lacteos Culinarios | B100: 133 - 4 | C100: PK 8 CREMA DE LECHE TARRO 157g 15% DCTO | D100: . | E100: =VALUE(SUBSTITUTE(SUBSTITUTE(B100," ",""),"-","")) -> 1334 | F100: =+CONCATENATE(C100," ",D100) -> PK 8 CREMA DE LECHE TARRO 157g 15% DCTO . | G100: =A100 -> Lacteos Culinarios
... A112: Lacteos Culinarios | B112: 138 - 0 | C112: NESTLE CREMA CHAMPIÑONES | D112: 48 x 157 GRM | E112: =VALUE(SUBSTITUTE(SUBSTITUTE(B112," ",""),"-","")) -> 1380 | F112: =+CONCATENATE(C112," ",D112) -> NESTLE CREMA CHAMPIÑONES 48 x 157 GRM | G112: =A112 -> Lacteos Culinarios
A113: GALLETAS | B113: 139 - 0 | C113: PACK GALL MINI 20+3 | E113: =VALUE(SUBSTITUTE(SUBSTITUTE(B113," ",""),"-","")) -> 1390 | F113: =+CONCATENATE(C113," ",D113) -> PACK GALL MINI 20+3 | G113: =A113 -> GALLETAS
A114: CHOCOLATES | B114: 145 - 0 | C114: CAPRI Huevos Chocolate Manjar | D114: 10x208gCL | E114: =VALUE(SUBSTITUTE(SUBSTITUTE(B114," ",""),"-","")) -> 1450 | F114: =+CONCATENATE(C114," ",D114) -> CAPRI Huevos Chocolate Manjar 10x208gCL | G114: =A114 -> CHOCOLATES
A115: CHOCOLATES | B115: 146 - 0 | C115: TRENCITO Bolsa Huevitos | D115: 12x500g N1 CL | E115: =VALUE(SUBSTITUTE(SUBSTITUTE(B115," ",""),"-","")) -> 1460 | F115: =+CONCATENATE(C115," ",D115) -> TRENCITO Bolsa Huevitos 12x500g N1 CL | G115: =A115 -> CHOCOLATES
A116: CAFES | B116: 150 - 0 | C116: NESCAFE FINA SELECCIÓN TARRO | D116: 24 x 170 GRS | E116: =VALUE(SUBSTITUTE(SUBSTITUTE(B116," ",""),"-","")) -> 1500 | F116: =+CONCATENATE(C116," ",D116) -> NESCAFE FINA SELECCIÓN TARRO 24 x 170 GRS | G116: =A116 -> CAFES
A117: DESHABILITADOS | B117: 152 - 0 | C117: POLAR | E117: =VALUE(SUBSTITUTE(SUBSTITUTE(B117," ",""),"-","")) -> 1520 | F117: =+CONCATENATE(C117," ",D117) -> POLAR | G117: =A117 -> DESHABILITADOS
A118: CAFES | B118: 154 - 0 | C118: NESCAFE FINA SELECCIÓN TARRO | D118: 24 x 100 GRS | E118: =VALUE(SUBSTITUTE(SUBSTITUTE(B118," ",""),"-","")) -> 1540 | F118: =+CONCATENATE(C118," ",D118) -> NESCAFE FINA SELECCIÓN TARRO 24 x 100 GRS | G118: =A118 -> CAFES
A119: DESHABILITADOS | B119: 155 - 0 | C119: PROMOCION BASURERO ABL | E119: =VALUE(SUBSTITUTE(SUBSTITUTE(B119," ",""),"-","")) -> 1550 | F119: =+CONCATENATE(C119," ",D119) -> PROMOCION BASURERO ABL | G119: =A119 -> DESHABILITADOS
A120: DESHABILITADOS | B120: 157 - 0 | C120: Pizarra Lácteos Culinarios | E120: =VALUE(SUBSTITUTE(SUBSTITUTE(B120," ",""),"-","")) -> 1570 | F120: =+CONCATENATE(C120," ",D120) -> Pizarra Lácteos Culinarios | G120: =A120 -> DESHABILITADOS
A121: DESHABILITADOS | B121: 158 - 0 | C121: Pizarra Nescafé Pai | E121: =VALUE(SUBSTITUTE(SUBSTITUTE(B121," ",""),"-","")) -> 1580 | F121: =+CONCATENATE(C121," ",D121) -> Pizarra Nescafé Pai | G121: =A121 -> DESHABILITADOS
...

Sheet Concuna
A1: Index | B1: Posicion | C1: COD | D1: Posición2 | E1: SKU | F1: MEDIDA | G1: BARRAS UNIDADES | H1: BARRAS DISPLAY | I1: BARRAS CAJAS | J1: DISPLAY x CAJA | K1: CATEGORIA | L1: COD2 | M1: BARRAS CAJAS3 | P1: Posicion | Q1: Sin Stock
A2: 1 | B2: Posicion A01 | C2: 46694 | D2: Posición A01 | E2: NATURNES Carne Verduras 4(6x205g) CL | F2: 4(6x205g) | G2: 8445291769885 | I2: 8445291769908 | K2: TRADICIONAL | L2: A01 | M2: cajas | N2: A01 | O2: A01 | P2: Igual | Q2: 10618
A3: 2 | B3: Posicion A02 | C3: 46669 | D3: Posición A02 | E3: NATURNES Pollo Verduras 4(6x205g) CL | F3: 4(6x205g) | G3: 8445291770218 | I3: 8445291770232 | K3: TRADICIONAL | L3: A02 | M3: cajas | N3: A02 | O3: A02 | P3: Igual | Q3: 117723
A4: 3 | B4: Posicion A03 | C4: 46695 | D4: Posición A03 | E4: NATURNES AIP Carne Verduras 4(6x205g) CL | F4: 4(6x205g) | G4: 8445291770027 | I4: 8445291770041 | K4: TRADICIONAL | L4: A03 | M4: cajas | N4: A03 | O4: A03 | P4: Igual | Q4: 124520
A5: 4 | B5: Posicion A04 | C5: 46716 | D5: Posición A04 | E5: NESTLE AIP Pollo Verduras 4(6x205g) CL | F5: 4(6x205g) | G5: 8445292266062 | I5: 8445292266086 | K5: TRADICIONAL | L5: A04 | M5: cajas | N5: A04 | O5: A04 | P5: Igual | Q5: 2784
A6: 5 | B6: Posicion A05 | C6: 46730 | D6: Posición A05 | E6: Picado NESTLE NATURNES Carbonada12x250g | F6: 12x250g | G6: 7613030264569 | I6: 7613033207266 | K6: TRADICIONAL | L6: A05 | M6: cajas | N6: A05 | O6: A05 | P6: Igual | Q6: 13510
A7: 6 | B7: Posicion A06 | C7: 46740 | D7: Posición A06 | E7: Picado NESTLE NATURNES Cazuela de Ave 24x250g | F7: 24x250g | G7: 7613030264705 | I7: 7613031415090 | K7: TRADICIONAL | L7: A06 | M7: cajas | N7: A06 | O7: A06 | P7: Igual | Q7: 11310
A8: 7 | B8: Posicion A07 | C8: 46750 | D8: Posición A07 | E8: Picado NESTLE NATURNES Cazuela de Vacuno24x250g | F8: 24x250g | G8: 7613030692669 | I8: 7613031415113 | K8: TRADICIONAL | L8: A07 | M8: cajas | N8: A07 | O8: A07 | P8: Igual | Q8: 11711
A9: 8 | B9: Posicion A08 | C9: 46760 | D9: Posición A08 | E9: Picado NESTLE NATURNES Charquican12x250g | F9: 12x250g | G9: 7613030692577 | I9: 7613033207020 | K9: TRADICIONAL | L9: A08 | M9: cajas | N9: A08 | O9: A08 | P9: Igual | Q9: 1170
A10: 9 | B10: Posicion A09 | C10: 5670 | D10: Posición A09 | E10: Colado NESTLE NATURNES Carne Verdura 8(6x115g) | F10: 8(6x115g) | G10: 7613036653961 | I10: 7613036653985 | K10: TRADICIONAL | L10: A09 | M10: cajas | N10: A09 | O10: A09 | P10: Igual | Q10: 1235
A11: 10 | B11: Posicion A10 | C11: 56420 | D11: Posición A10 | E11: Colado NESTLE NATURNES Pollo Verduras 8x6x115g | F11: 8(6x115g) | G11: 7613036749565 | I11: 7613036654098 | K11: TRADICIONAL | L11: A10 | M11: cajas | N11: A10 | O11: A10 | P11: Igual | Q11: 1360
A12: 11 | B12: Posicion A11 | C12: 1330 | D12: Posición A11 | E12: Crema de leche NESTLE Lata48 x 157 GRM | F12: 48 x 157 GRM | G12: 7613032414580 | I12: 7613032414597 | K12: TRADICIONAL | L12: A11 | M12: cajas | N12: A11 | O12: A11 | P12: Igual | Q12: 7656
A13: 12 | B13: Posicion A11 | C13: 79760 | D13: Posición A11 | E13: NESTLE Crema de leche tarro 3840x157g | F13: 3840x157g | G13: 7613032414580 | I13: 7613287221766 | K13: TRADICIONAL | L13: A11 | M13: PDQ | N13: A11 | O13: A11 | P13: Igual | Q13: 0
... A54: 53 | B54: Posicion C01 | C54: 36535 | D54: Posición C01 | E54: NESCAFE CAPPUCCINO 6(8x14g) N2 CL | F54: 6(8x14g) | G54: 8445291239043 | I54: 8445291239012 | K54: TRADICIONAL | L54: C01 | M54: cajas | N54: C01 | O54: C01 | P54: Igual | Q54: 0
A55: 54 | B55: Posicion C02 | C55: 5320 | D55: Posición C02 | E55: Cafe NESCAFE Tradicion sobres77x172.8g | F55: 77x172.8g | G55: 7613035671621 | I55: 7613035671638 | J55: 77 | K55: TRADICIONAL | L55: C02 | M55: cajas | N55: C02 | O55: C02 | P55: Igual | Q55: 0
A56: 55 | B56: Posicion C03 | C56: 38850 | D56: Posición C03 | E56: Cafe NESCAFE Tradicion tarro24 X 50 gr. | F56: 24 X 50 gr. | G56: 7802950002119 | I56: 7613034092472 | K56: TRADICIONAL | L56: C03 | M56: cajas | N56: C03 | O56: C03 | P56: Igual | Q56: 14282
A57: 56 | B57: Posicion C04 | C57: 2130 | D57: Posición C04 | E57: Cafe NESCAFE Tradicion tarro24 x 100 GRS | F57: 24 x 100 GRS | G57: 7802950002133 | I57: 17802950002130 | K57: TRADICIONAL | L57: C04 | M57: cajas | N57: C04 | O57: C04 | P57: Igual | Q57: 40419
A58: 57 | B58: Posicion C05 | C58: 2120 | D58: Posición C05 | E58: Cafe NESCAFE Tradicion tarro24 x 170 GRS | F58: 24 x 170 GRS | G58: 7802950002126 | I58: 17802950002123 | K58: TRADICIONAL | L58: C05 | M58: cajas | N58: C05 | O58: C05 | P58: Igual | Q58: 61920
A59: 58 | B59: Posicion C06 | C59: 50940 | D59: Posición C06 | E59: Cafe NESCAFE Tradicion tarro12X400G | F59: 12X400G | G59: 7802950002720 | I59: 17802950002727 | K59: TRADICIONAL | L59: C06 | M59: cajas | N59: C06 | O59: C06 | P59: Igual | Q59: 558
A60: 59 | B60: Posicion C07 | C60: 96570 | D60: Posición C07 | E60: NESTUM BL Prob CI 5Cereales 24x250gN1CL | F60: 24x250gN1CL | G60: 7613035939110 | I60: 7613035939127 | K60: TRADICIONAL | L60: C07 | M60: cajas | N60: C07 | O60: C07 | P60: Igual | Q60: 0
A61: 60 | B61: Posicion C08 | C61: 11780 | D61: Posición C08 | E61: Cereal infantil NESTUM Arroz24x250g | F61: 24x250g | G61: 7613036048132 | I61: 7613036048149 | K61: TRADICIONAL | L61: C08 | M61: cajas | N61: C08 | O61: C08 | P61: Igual | Q61: 201
A62: 61 | B62: Posicion C09 | C62: 90000 | D62: Posición C09 | E62: NESTUM BL Prob CI TrigoFruta 24x250gN2CL | F62: 24x250gN2CL | G62: 7613035939400 | I62: 7613035939417 | K62: TRADICIONAL | L62: C09 | M62: cajas | N62: C09 | O62: C09 | P62: Igual | Q62: 0
A63: 62 | B63: Posicion C10 | C63: 99020 | D63: Posición C10 | E63: NESTUM BL PROB CI TrigoMiel 24x250gN1CL | F63: 24x250gN1CL | G63: 7613035939370 | I63: 7613035939387 | K63: TRADICIONAL | L63: C10 | M63: cajas | N63: C10 | O63: C10 | P63: Igual | Q63: 0
A64: 63 | B64: Posicion C11 | C64: 11790 | D64: Posición C11 | E64: Cereal infantil NESTUM Avena y Arroz24x250g | F64: 24x250g | G64: 7613036048040 | I64: 7613036048057 | K64: TRADICIONAL | L64: C11 | M64: cajas | N64: C11 | O64: C11 | P64: Igual | Q64: 2113
A65: 64 | B65: Posicion C14 | C65: 69780 | D65: Posición C14 | E65: NESTLE EL MANJAR Bolsa 48x200g | F65: 48x200g | G65: 7802950009408 | I65: 8445290882585 | K65: TRADICIONAL | L65: C14 | M65: cajas | N65: C14 | O65: C14 | P65: Igual | Q65: 62920
A66: 65 | B66: Posicion C15 | C66: 43020 | D66: Posición C15 | E66: Manjar NESTLE El Manjar24x500g | F66: 24x500g | G66: 7802950009415 | I66: 17802950009412 | K66: TRADICIONAL | L66: C15 | M66: cajas | N66: C15 | O66: C15 | P66: Igual | Q66: 26920
A67: 66 | B67: Posicion C16 | C67: 72290 | D67: Posición C16 | E67: Manjar NESTLE El Manjar Doypack12x800g | F67: 12x800g | G67: 7613038639161 | I67: 7613038639178 | K67: TRADICIONAL | L67: C16 | M67: cajas | N67: C16 | O67: C16 | P67: Igual | Q67: 1691
... A127: 126 | B127: Posicion E25 | C127: 12310 | D127: Posición E25 | E127: Salsa de tomate MAGGI Tuco con Carne Lata24 x 245 GRS | F127: 24 x 245 GRS | G127: 7802950012316 | I127: 17802950012313 | K127: TRADICIONAL | L127: E25 | M127: cajas | N127: E25 | O127: E25 | P127: Igual | Q127: 17
A128: 127 | B128: Posicion E26 | C128: 5110 | D128: Posición E26 | E128: IMPERIAL POLVO HORNEAR SOBRE10 x 50 x 20 GRM | F128: 10 x 50 x 20 GRM | G128: 7802950105117 | H128: 7802950105117 | I128: 17802950005117 | K128: TRADICIONAL | L128: E26 | M128: cajas | N128: E26 | O128: E26 | P128: Igual | Q128: 11480
A129: 128 | B129: Posicion F01 | C129: 8770 | D129: Posición F01 | E129: Polvo de hornear IMPERIAL Sobres6 x 12 x 100 GRM | F129: 6 x 12 x 100 GRM | G129: 7802950108774 | H129: 7802950108774 | I129: 17802950008774 | K129: TRADICIONAL | L129: F01 | M129: cajas | N129: F01 | O129: F01 | P129: Igual | Q129: 3930
A130: 129 | B130: Posicion F02 | C130: 5020 | D130: Posición F02 | E130: Polvo de hornear IMPERIAL Lata24 x 200 GRM | F130: 24 x 200 GRM | G130: 7802950005028 | I130: 17802950005025 | K130: TRADICIONAL | L130: F02 | M130: cajas | N130: F02 | O130: F02 | P130: Igual | Q130: 24523
A131: 130 | B131: Posicion F03 | C131: 35700 | D131: Posición F03 | E131: STARBUCKS Caramel Latte 10(4x23)g N3 XJ | F131: 10(4x23)g | G131: 8445290216816 | I131: 8445290216700 | K131: TRADICIONAL | L131: F03 | M131: cajas | N131: F03 | O131: F03 | P131: Igual | Q131: 469
A132: 131 | B132: Posicion F04 | C132: 35710 | D132: Posición F04 | E132: STARBUCKS Mocha 1(4x22)g N3 XJ | F132: 10(4x22)g | G132: 7613038631189 | I132: 7613038630373 | K132: TRADICIONAL | L132: F04 | M132: cajas | N132: F04 | O132: F04 | P132: Igual | Q132: 600
A133: 132 | B133: Posicion F05 | C133: 96670 | D133: Posición F05 | E133: NATURNES Organico Manzana Pouch 16x100gCL | F133: 16x100gCL | G133: 7506475110303 | I133: 17506475110300 | K133: TRADICIONAL | L133: F05 | M133: cajas | N133: F05 | O133: F05 | P133: Igual | Q133: 0
A134: 133 | B134: Posicion F06 | C134: 96630 | D134: Posición F06 | E134: NATURNESOrganicoPlatanoMangoPch 16x100gCL | F134: 16x100gCL | G134: 7506475110280 | I134: 17506475110287 | K134: TRADICIONAL | L134: F06 | M134: cajas | N134: F06 | O134: F06 | P134: Igual | Q134: 0
A135: 134 | B135: Posicion F07 | C135: 77370 | D135: Posición F07 | E135: NESC DLC GST Skny Capp N1XR 16Cap3x161.6g | F135: 16Cap3x161.6g | G135: 7613031587377 | I135: 17501059273709 | K135: TRADICIONAL | L135: F07 | M135: cajas | N135: F07 | O135: F07 | P135: Igual | Q135: 0
A136: 135 | B136: Posicion F08 | C136: 63401 | D136: Posición F08 | E136: NDG AMERICANO 10Caps 6x80g XR | F136: 6x80g | G136: 7891000405772 | I136: 17891000405779 | K136: TRADICIONAL | L136: F08 | M136: cajas | N136: F08 | O136: F08 | P136: Igual | Q136: 0
A137: 136 | B137: Posicion F09 | C137: 36920 | D137: Posición F09 | E137: STARBUCKS Vanilla Latte 10(4x215g)N3 XJ | F137: 4x21.5g | G137: 7613038630977 | I137: 7613038630960 | K137: TRADICIONAL | L137: F09 | M137: cajas | N137: F09 | O137: F09 | P137: Igual | Q137: 433
A138: 137 | B138: Posicion F10 | C138: 976901 | D138: Posición F10 | E138: NDG MOCHA 10Caps 6x135g XR | F138: 6x135g | G138: 7891000405871 | I138: 17891000405878 | K138: TRADICIONAL | L138: F10 | M138: cajas | N138: F10 | O138: F10 | P138: Igual | Q138: 0
A139: 138 | B139: Posicion F11 | C139: 8760 | D139: Posición F11 | E139: NIDO SmDescr Chocolate 19%MG 15x700g CL | F139: 15x700g CL | G139: 8445291195509 | I139: 8445291195615 | K139: TRADICIONAL | L139: F11 | M139: cajas | N139: F11 | O139: F11 | P139: Igual | Q139: 0
A140: 139 | B140: Posicion F12 | C140: 977101 | D140: Posición F12 | E140: NDG LUNGO 10Caps 6x70g XR | F140: 6x70g | G140: 7891000406052 | I140: 17891000406059 | K140: TRADICIONAL | L140: F12 | M140: cajas | N140: F12 | O140: F12 | P140: Igual | Q140: 0
A141: 140 | B141: Posicion F14 | C141: 983001 | D141: Posición F14 | E141: NDG CAFE AU LAIT 10Caps 6x100g XR | F141: 6x100g | G141: 7891000405901 | I141: 17891000405908 | K141: TRADICIONAL | L141: F14 | M141: cajas | N141: F14 | O141: F14 | P141: Igual | Q141: 0
... A159: 158 | B159: Posicion F32 | C159: 82400 | D159: Posición F32 | E159: NESCAFE Fina Seleccion Colombia 6x100g | F159: 6x100g | G159: 7613037071368 | I159: 7613037071375 | K159: TRADICIONAL | L159: F32 | M159: cajas | N159: F32 | O159: F32 | P159: Igual | Q159: 3
A160: 159 | B160: Posicion F33 | C160: 31730 | D160: Posición F33 | E160: Sopa para Uno MAGGI Esparragos Sobre 6 X 24 X14 GRS | F160: 6 X 24 X14 GRS | G160: 7613033609992 | H160: 7613033610004 | I160: 7613033610011 | K160: TRADICIONAL | L160: F33 | M160: cajas | N160: F33 | O160: F33 | P160: Igual | Q160: 111
A161: 160 | B161: Posicion F34 | C161: 79690 | D161: Posición F34 | E161: MAGGI SPPU Costillas Fideo 4(16x16g) | F161: 4(16x16g) | G161: 7613287552389 | I161: 7613287552396 | K161: TRADICIONAL | L161: F34 | M161: cajas | N161: F34 | O161: F34 | P161: Igual | Q161: 3023
A162: 161 | B162: Posicion F35 | C162: 77270 | D162: Posición F35 | E162: MAGGI Caldo En Polvo de Cstll28(10x7g) | F162: 28(10x7g) | G162: 7613287222022 | I162: 7613287316646 | K162: TRADICIONAL | L162: F35 | M162: cajas | N162: F35 | O162: F35 | P162: Igual | Q162: 254
A163: 162 | B163: Posicion F36 | C163: 77280 | D163: Posición F36 | E163: MAGGI Caldo En Polvo de Glln 28(10x7g) | F163: 28(10x7g) | G163: 7613287221841 | I163: 7613287315687 | K163: TRADICIONAL | L163: F36 | M163: cajas | N163: F36 | O163: F36 | P163: Igual | Q163: 23
A164: 163 | B164: Posicion F37 | C164: 77290 | D164: Posición F37 | E164: MAGGI Caldo En Polvo de Verd 28(10x7g) | F164: 28(10x7g) | G164: 7613287221889 | I164: 7613287316608 | K164: TRADICIONAL | L164: F37 | M164: cajas | N164: F37 | O164: F37 | P164: Igual | Q164: 144
A165: 164 | B165: Posicion F38 | C165: 6080 | D165: Posición F38 | E165: MAGGI SPPU Consome de Pollo 4(16x12g) | F165: 4(16x12g) | G165: 8445290855329 | I165: 8445290855336 | K165: TRADICIONAL | L165: F38 | M165: cajas | N165: F38 | O165: F38 | P165: Igual | Q165: 538
A166: 165 | B166: Posicion F39 | C166: 79460 | D166: Posición F39 | E166: MAGGI Caldo de Costilla N130(12x10g) | F166: 30(12x10g) | G166: 7613033822254 | I166: 7613033822261 | K166: TRADICIONAL | L166: F39 | M166: cajas | N166: F39 | O166: F39 | P166: Igual | Q166: 3628
A167: 166 | B167: Posicion F40 | C167: 79470 | D167: Posición F40 | E167: MAGGI Caldo de Verdura N130(8x10g) | F167: 30 x 8 x 10 GRM | G167: 7613033822285 | I167: 7613033822292 | K167: TRADICIONAL | L167: F40 | M167: cajas | N167: F40 | O167: F40 | P167: Igual | Q167: 1410
A168: 167 | B168: Posicion F41 | C168: 79510 | D168: Posición F41 | E168: MAGGI Caldo Verduras N130(12x10g) | F168: 30(12x10g) | G168: 7613033821523 | I168: 7613033821530 | K168: TRADICIONAL | L168: F41 | M168: cajas | N168: F41 | O168: F41 | P168: Igual | Q168: 503
A169: 168 | B169: Posicion F42 | C169: 68190 | D169: Posición F42 | E169: MAGGI Caldo Gallina 30(8x11g) N2 CL | F169: 30(8x11g) | G169: 7802950005936 | I169: 7613033533396 | K169: TRADICIONAL | L169: F42 | M169: cajas | N169: F42 | O169: F42 | P169: Igual | Q169: 0
A170: 169 | B170: Posicion F43 | C170: 79550 | D170: Posición F43 | E170: MAGGI Caldo de Carne N130(8x10g) | F170: 30 x 8 x 10 GRM | G170: 7802950005967 | I170: 7613033540288 | K170: TRADICIONAL | L170: F43 | M170: cajas | N170: F43 | O170: F43 | P170: Igual | Q170: 3728
A171: 170 | B171: Posicion F44 | C171: 68980 | D171: Posición F44 | E171: MAGGI Caldo Gallina 30(12x11g) N2 CL | F171: 12x11g | G171: 7802950005943 | I171: 7613033541759 | K171: TRADICIONAL | L171: F44 | M171: cajas | N171: F44 | O171: F44 | P171: Igual | Q171: 514
A172: 171 | B172: Posicion F45 | C172: 79600 | D172: Posición F45 | E172: MAGGI Caldo de Carne N130(12x10g) | F172: 30(12x10g) | G172: 7802950005974 | I172: 7613033541810 | K172: TRADICIONAL | L172: F45 | M172: cajas | N172: F45 | O172: F45 | P172: Igual | Q172: 8317
... A178: 177 | B178: Posicion F51 | C178: 85010 | D178: Posición F51 | E178: MAGGI Caldo En Polvo de Carne 28(10x7g) | F178: 28(10x7g) | G178: 7613287610843 | I178: 7613287648242 | K178: TRADICIONAL | L178: F51 | M178: cajas | N178: F51 | O178: F51 | P178: Igual | Q178: 2512
A179: 178 | B179: Posicion G01 | C179: a | D179: Posición G01 | K179: TRADICIONAL | L179: G01 | M179: cajas | N179: G01 | O179: G01 | P179: Igual | Q179: 0
A180: 179 | B180: Posicion G02 | C180: a | D180: Posición G02 | K180: TRADICIONAL | L180: G02 | M180: cajas | N180: G02 | O180: G02 | P180: Igual | Q180: 0
A181: 180 | B181: Posicion G03 | C181: a | D181: Posición G03 | K181: TRADICIONAL | L181: G03 | M181: cajas | N181: G03 | O181: G03 | P181: Igual | Q181: 0
A182: 181 | B182: Posicion G04 | C182: a | D182: Posición G04 | K182: TRADICIONAL | L182: G04 | M182: cajas | N182: G04 | O182: G04 | P182: Igual | Q182: 0
A183: 182 | B183: Posicion G05 | C183: a | D183: Posición G05 | K183: TRADICIONAL | L183: G05 | M183: cajas | N183: G05 | O183: G05 | P183: Igual | Q183: 0
A184: 183 | B184: Posicion G06 | C184: a | D184: Posición G06 | K184: TRADICIONAL | L184: G06 | M184: cajas | N184: G06 | O184: G06 | P184: Igual | Q184: 0
A185: 184 | B185: Posicion G07 | C185: a | D185: Posición G07 | K185: TRADICIONAL | L185: G07 | M185: cajas | N185: G07 | O185: G07 | P185: Igual | Q185: 0
A186: 185 | B186: Posicion G08 | C186: a | D186: Posición G08 | K186: TRADICIONAL | L186: G08 | M186: cajas | N186: G08 | O186: G08 | P186: Igual | Q186: 0
A187: 186 | B187: Posicion G09 | C187: a | D187: Posición G09 | K187: TRADICIONAL | L187: G09 | M187: cajas | N187: G09 | O187: G09 | P187: Igual | Q187: 0
A188: 187 | B188: Posicion G10 | C188: a | D188: Posición G10 | K188: TRADICIONAL | L188: G10 | M188: cajas | N188: G10 | O188: G10 | P188: Igual | Q188: 0
A189: 188 | B189: Posicion G11 | C189: a | D189: Posición G11 | K189: TRADICIONAL | L189: G11 | M189: cajas | N189: G11 | O189: G11 | P189: Igual | Q189: 0
A190: 189 | B190: Posicion G14 | C190: a | D190: Posición G14 | K190: TRADICIONAL | L190: G14 | M190: cajas | N190: G14 | O190: G14 | P190: Igual | Q190: 0
A191: 190 | B191: Posicion G15 | C191: 75950 | D191: Posición G15 | E191: Complemento nutricional NESSUCAR Tarro12x500g | F191: 12 x 550 GRM | G191: 7891000299265 | I191: 7891000299289 | K191: TRADICIONAL | L191: G15 | M191: cajas | N191: G15 | O191: G15 | P191: Igual | Q191: 18
A192: 191 | B192: Posicion G16 | C192: 21040 | D192: Posición G16 | E192: Chocolate en polvo NESTLE Tarro24 x 400 GRM | F192: 24 x 400 GRM | G192: 7613031215867 | I192: 7613031215850 | K192: TRADICIONAL | L192: G16 | M192: cajas | N192: G16 | O192: G16 | P192: Igual | Q192: 121
A193: 192 | B193: Posicion G17 | C193: a | D193: Posición G17 | K193: TRADICIONAL | L193: G17 | M193: cajas | N193: G17 | O193: G17 | P193: Igual | Q193: 0
A194: 193 | B194: Posicion G18 | C194: a | D194: Posición G18 | K194: TRADICIONAL | L194: G18 | M194: cajas | N194: G18 | O194: G18 | P194: Igual | Q194: 0
A195: 194 | B195: Posicion G20 | C195: 67330 | D195: Posición G20 | E195: NESTLE Lec Cond Doypack 36x180g CL | F195: 36x180g | G195: 8445291404380 | I195: 8445291404397 | K195: TRADICIONAL | L195: G20 | M195: cajas | N195: G20 | O195: G20 | P195: Igual | Q195: 12732
A196: 195 | B196: Posicion G21 | C196: 36713 | D196: Posición G21 | E196: NESTLE EL MANJAR 12x810g CL | F196: 12x810g | G196: 8445291986558 | I196: 8445291986565 | K196: TRADICIONAL | L196: G21 | M196: cajas | N196: G21 | O196: G21 | P196: Igual | Q196: 0
A197: 196 | B197: Posicion G22 | C197: 36910 | D197: Posición G22 | E197: MILO ACTIV-GO BebChoc Stabilo 24x200g CL | F197: 24x200g | G197: 8445291797727 | I197: 8445291797710 | K197: TRADICIONAL | L197: G22 | M197: cajas | N197: G22 | O197: G22 | P197: Igual | Q197: 16811
A198: 197 | B198: Posicion G23 | C198: a | D198: Posición G23 | K198: TRADICIONAL | L198: G23 | M198: cajas | N198: G23 | O198: G23 | P198: Igual | Q198: 0
A199: 198 | B199: Posicion G24 | C199: 36890 | D199: Posición G24 | E199: GLORIA Leche Condensada Tarro 48x397g CL | F199: 48x397g | G199: 8445291964006 | I199: 8445291964518 | K199: TRADICIONAL | L199: G24 | M199: cajas | N199: G24 | O199: G24 | P199: Igual | Q199: 2276
A200: 199 | B200: Posicion G25 | C200: 25773 | D200: Posición G25 | E200: MILO Mixes Mainstream 6(8x14g) CL | F200: 6(8x14g) | G200: 8445291790063 | I200: 8445291790049 | K200: TRADICIONAL | L200: G25 | M200: cajas | N200: G25 | O200: G25 | P200: Igual | Q200: 0
A201: 200 | B201: Posicion G26 | C201: 97241 | D201: Posición G26 | E201: SVELTY Skimmed Sfpk 12x800g CL | F201: 12x800g | G201: 7613032425616 | I201: 8445292283526 | K201: TRADICIONAL | L201: G26 | M201: cajas | N201: G26 | O201: G26 | P201: Igual | Q201: 0
A202: 201 | B202: Posicion G27 | C202: 94950 | D202: Posición G27 | E202: NESCAFE TRADICION Tarro PDQ 768x170gN1CL | F202: 768x170gN1CL | G202: 7613036653435 | I202: 8445290609847 | K202: TRADICIONAL | L202: G27 | M202: PDQ | N202: G27 | O202: G27 | P202: Igual | Q202: 0
A203: 202 | B203: Posicion G28 | C203: 359301 | D203: Posición G28 | E203: NATURNES AIP VegMix Carne 4(6x205g) CL | F203: 4(6x205g) | G203: 7613032414580 | I203: 8445291427570 | K203: TRADICIONAL | L203: G28 | M203: cajas | N203: G28 | O203: G28 | P203: Igual | Q203: 0
A204: 203 | B204: Posicion G29 | C204: 359501 | D204: Posición G29 | E204: NATURNES AIC VegMix Carne 4(6x205g) CL | F204: 4(6x205g) | G204: 8445291427129 | I204: 8445291427136 | K204: TRADICIONAL | L204: G29 | M204: cajas | N204: G29 | O204: G29 | P204: Igual | Q204: 0
A205: 204 | B205: Posicion G30 | C205: 1732 | D205: Posición G30 | E205: NIDO Entera 6(20x25g) CL | F205: 6(20x25g) | G205: 8445292353687 | H205: 8445292356183 | I205: 8445292353700 | K205: TRADICIONAL | L205: G30 | M205: cajas | N205: G30 | O205: G30 | P205: Igual | Q205: 0
A206: 205 | B206: Posicion G31 | C206: a | D206: Posición G31 | K206: TRADICIONAL | L206: G31 | M206: cajas | N206: G31 | O206: G31 | P206: Igual | Q206: 0
A207: 206 | B207: Posicion G32 | C207: a | D207: Posición G32 | K207: TRADICIONAL | L207: G32 | M207: cajas | N207: G32 | O207: G32 | P207: Igual | Q207: 0
A208: 207 | B208: Posicion G33 | C208: 14174 | D208: Posición G33 | E208: NESCAFE Brownie Caramel 6(7x20g) CL | F208: 6(7x20g) | G208: 8445291904170 | I208: 8445291886568 | K208: TRADICIONAL | L208: G33 | M208: cajas | N208: G33 | O208: G33 | P208: Igual | Q208: 0
A209: 208 | B209: Posicion G34 | C209: 84510 | D209: Posición G34 | E209: NESCAFE DOLCA Tarro 768x170g | F209: 768x170g | G209: 7802950002171 | I209: 7613287694317 | K209: TRADICIONAL | L209: G34 | M209: PDQ | N209: G34 | O209: G34 | P209: Igual | Q209: 0
A210: 209 | B210: Posicion G35 | C210: 69790 | D210: Posición G35 | E210: NIDO LEP Instan 26%MG Sfpk 192x800g | F210: 192x800g | G210: 8445290262646 | I210: 8445290981912 | K210: TRADICIONAL | L210: G35 | M210: PDQ | N210: G35 | O210: G35 | P210: Igual | Q210: 3
A211: 210 | B211: Posicion G36 | C211: 57830 | D211: Posición G36 | E211: Leche en polvo SVELTY Move 12x800g | F211: 12x800g | G211: 7613034335661 | I211: 7613034335678 | K211: TRADICIONAL | L211: G36 | M211: cajas | N211: G36 | O211: G36 | P211: Igual | Q211: 4410
A212: 211 | B212: Posicion G37 | C212: a | D212: Posición G37 | K212: TRADICIONAL | L212: G37 | M212: cajas | N212: G37 | O212: G37 | P212: Igual | Q212: 0
A213: 212 | B213: Posicion G38 | C213: 7380 | D213: Posición G38 | E213: Cafe NESCAFE Tradicion sobres 77x194,4g CL | F213: 77x194,4g CL | G213: 8445290794963 | I213: 8445290794994 | K213: TRADICIONAL | L213: G38 | M213: cajas | N213: G38 | O213: G38 | P213: Igual | Q213: 1
A214: 213 | B214: Posicion H01 | C214: a | D214: Posición H01 | K214: TRADICIONAL | L214: H01 | M214: PDQ | N214: H01 | O214: H01 | P214: Igual | Q214: 0
A215: 214 | B215: Posicion H02 | C215: a | D215: Posición H02 | K215: TRADICIONAL | L215: H02 | M215: PDQ | N215: H02 | O215: H02 | P215: Igual | Q215: 0
A216: 215 | B216: Posicion H03 | C216: a | D216: Posición H03 | K216: TRADICIONAL | L216: H03 | M216: PDQ | N216: H03 | O216: H03 | P216: Igual | Q216: 0
A217: 216 | B217: Posicion H04 | C217: a | D217: Posición H04 | K217: TRADICIONAL | L217: H04 | M217: cajas | N217: H04 | O217: H04 | P217: Igual | Q217: 0
A218: 217 | B218: Posicion H05 | C218: a | D218: Posición H05 | K218: TRADICIONAL | L218: H05 | M218: cajas | N218: H05 | O218: H05 | P218: Igual | Q218: 0
A219: 218 | B219: Posicion H06 | C219: a | D219: Posición H06 | K219: TRADICIONAL | L219: H06 | M219: cajas | N219: H06 | O219: H06 | P219: Igual | Q219: 0
A220: 219 | B220: Posicion H07 | C220: a | D220: Posición H07 | K220: TRADICIONAL | L220: H07 | M220: cajas | N220: H07 | O220: H07 | P220: Igual | Q220: 0
A221: 220 | B221: Posicion H08 | C221: a | D221: Posición H08 | K221: TRADICIONAL | L221: H08 | M221: cajas | N221: H08 | O221: H08 | P221: Igual | Q221: 0
...

Sheet Etiquetas
A1: 1 | B1: =+VLOOKUP(A1,'Sectorizacion Racks'!$A$2:$F$1332,5,FALSE) -> A1 | C1: =+VLOOKUP(A1+1,'Sectorizacion Racks'!$A$2:$F$1332,5,FALSE) -> A2 | E1: A1 | F1: A2
A2: =+A1+2 -> 3 | B2: =+VLOOKUP(A2,'Sectorizacion Racks'!$A$2:$F$1332,5,FALSE) -> A3 | C2: =+VLOOKUP(A2+1,'Sectorizacion Racks'!$A$2:$F$1332,5,FALSE) -> A4 | E2: A3 | F2: A4
A3: =+A2+2 -> 5 | B3: =+VLOOKUP(A3,'Sectorizacion Racks'!$A$2:$F$1332,5,FALSE) -> A5 | C3: =+VLOOKUP(A3+1,'Sectorizacion Racks'!$A$2:$F$1332,5,FALSE) -> A6 | E3: A5 | F3: A6
A4: =+A3+2 -> 7 | B4: =+VLOOKUP(A4,'Sectorizacion Racks'!$A$2:$F$1332,5,FALSE) -> A7 | C4: =+VLOOKUP(A4+1,'Sectorizacion Racks'!$A$2:$F$1332,5,FALSE) -> A8 | E4: A7 | F4: A8
A5: =+A4+2 -> 9 | B5: =+VLOOKUP(A5,'Sectorizacion Racks'!$A$2:$F$1332,5,FALSE) -> A9 | C5: =+VLOOKUP(A5+1,'Sectorizacion Racks'!$A$2:$F$1332,5,FALSE) -> A10 | E5: A9 | F5: A10
A6: =+A5+2 -> 11 | B6: =+VLOOKUP(A6,'Sectorizacion Racks'!$A$2:$F$1332,5,FALSE) -> A11 | C6: =+VLOOKUP(A6+1,'Sectorizacion Racks'!$A$2:$F$1332,5,FALSE) -> A12 | E6: A11 | F6: A12
A7: =+A6+2 -> 13 | B7: =+VLOOKUP(A7,'Sectorizacion Racks'!$A$2:$F$1332,5,FALSE) -> A13 | C7: =+VLOOKUP(A7+1,'Sectorizacion Racks'!$A$2:$F$1332,5,FALSE) -> A14 | E7: A13 | F7: A14
A8: =+A7+2 -> 15 | B8: =+VLOOKUP(A8,'Sectorizacion Racks'!$A$2:$F$1332,5,FALSE) -> A15 | C8: =+VLOOKUP(A8+1,'Sectorizacion Racks'!$A$2:$F$1332,5,FALSE) -> A16 | E8: A15 | F8: A16
A9: =+A8+2 -> 17 | B9: =+VLOOKUP(A9,'Sectorizacion Racks'!$A$2:$F$1332,5,FALSE) -> A17 | C9: =+VLOOKUP(A9+1,'Sectorizacion Racks'!$A$2:$F$1332,5,FALSE) -> A18 | E9: A17 | F9: A18
A10: =+A9+2 -> 19 | B10: =+VLOOKUP(A10,'Sectorizacion Racks'!$A$2:$F$1332,5,FALSE) -> A19 | C10: =+VLOOKUP(A10+1,'Sectorizacion Racks'!$A$2:$F$1332,5,FALSE) -> A20 | E10: A19 | F10: A20
A11: =+A10+2 -> 21 | B11: =+VLOOKUP(A11,'Sectorizacion Racks'!$A$2:$F$1332,5,FALSE) -> A21 | C11: =+VLOOKUP(A11+1,'Sectorizacion Racks'!$A$2:$F$1332,5,FALSE) -> A22 | E11: A21 | F11: A22
A12: =+A11+2 -> 23 | B12: =+VLOOKUP(A12,'Sectorizacion Racks'!$A$2:$F$1332,5,FALSE) -> A23 | C12: =+VLOOKUP(A12+1,'Sectorizacion Racks'!$A$2:$F$1332,5,FALSE) -> A24 | E12: A23 | F12: A24
A13: =+A12+2 -> 25 | B13: =+VLOOKUP(A13,'Sectorizacion Racks'!$A$2:$F$1332,5,FALSE) -> B1 | C13: =+VLOOKUP(A13+1,'Sectorizacion Racks'!$A$2:$F$1332,5,FALSE) -> B2 | E13: B1 | F13: B2
... A382: =+A381+2 -> 763 | B382: =+VLOOKUP(A382,'Sectorizacion Racks'!$A$2:$F$1332,5,FALSE) -> A4 | C382: =+VLOOKUP(A382+1,'Sectorizacion Racks'!$A$2:$F$1332,5,FALSE) -> A5 | E382: B1 | F382: B2
